Workbook

Sheet Overview
A1: Silver — detailed completed-backtest workbook
A3: Purpose | B3: Reconstruct the selected strategy path from the completed backtest holding ledger, with visible holding P&L, book valuation, underlying-return decomposition, NAV reconciliation, and model checks.
A4: Holding interval | B4: Each row applies the start-date close holdings through the end-date close. Exchange holidays naturally create multi-calendar-day intervals.
A5: Template version | B5: 1
A6: Commodity scope | B6: Silver; this template version requires exactly one commodity sleeve.
A7: Mode | B7: positive = long futures only; neutral = no futures; negative = short futures only; long_and_short = both.
A8: Futures value | B8: Exchange-traded futures are carried at zero after daily settlement. Notional is exposure; economic P&L settles into the attributed cash/margin holding.
A9: Book valuation | B9: Lease and keep values are independently reconstructed from attributed holdings and from opening value + accumulated P&L + external/rebalancing transfers.
A10: Returns | B10: Standalone book return uses that book's start value. Contribution uses total lease + keep start value. Total return is reconstructed as underlying price change compounded with the combined book return quoted in the underlying.
A11: Prices | B11: A future's spot fields contain the actual commodity spot quote. Futures notional and quantity do not rescale that spot price. The normalized underlying index is shown separately.
A13: Selected result summary
A14: First holding date | B14: 25205
A15: Final interval end | B15: 25568
A16: Holding intervals | B16: 242
A17: Maximum simultaneous ledger holdings | B17: 10
A18: Ending NAV | B18: 2.0433695
A19: Portfolio rebalancing | B19: daily

Sheet Parameters
A1: Silver — completed-backtest parameters
A3: Parameter path | B3: Saved value | C3: Use | D3: Notes
A4: weight_silver | B4: 100 | C4: Exact completed-run input | D4: Nested commodity parameters are expanded for auditability.
A5: weight_gold | B5: 0 | C5: Exact completed-run input | D5: Nested commodity parameters are expanded for auditability.
A6: weight_sp500 | B6: 0 | C6: Exact completed-run input | D6: Nested commodity parameters are expanded for auditability.
A7: weight_btc | B7: 0 | C7: Exact completed-run input | D7: Nested commodity parameters are expanded for auditability.
A8: weight_treasury | B8: 0 | C8: Exact completed-run input | D8: Nested commodity parameters are expanded for auditability.
A9: portfolio_rebalancing | B9: daily | C9: Exact completed-run input | D9: Nested commodity parameters are expanded for auditability.
A10: reactivity | B10: same_day | C10: Exact completed-run input | D10: Nested commodity parameters are expanded for auditability.
A11: min_days | B11: 10 | C11: Exact completed-run input | D11: Nested commodity parameters are expanded for auditability.
A12: roll_only_if_better | B12: true | C12: Exact completed-run input | D12: Nested commodity parameters are expanded for auditability.
A13: force_roll_at_min_days | B13: true | C13: Exact completed-run input | D13: Nested commodity parameters are expanded for auditability.
A14: long_allocation_half_life_days | B14: 0 | C14: Exact completed-run input | D14: Nested commodity parameters are expanded for auditability.
... A167: commodity_parameters.sp500.max_short_fraction_of_long_leg | B167: 50 | C167: Exact completed-run input | D167: Nested commodity parameters are expanded for auditability.

Sheet Daily Holdings
A1: Interval and NAV | M1: Underlying and return reconstruction | AH1: Book valuation and roll-forward | BD1: Detailed return contributions | BK1: Holding 1 | CF1: Holding 2 | DA1: Holding 3 | DV1: Holding 4 | EQ1: Holding 5 | FL1: Holding 6 | GG1: Holding 7 | HB1: Holding 8 | HW1: Holding 9 | IR1: Holding 10
A2: Start date | B2: End date | C2: Elapsed days | D2: Signal date | E2: Mode | F2: Start NAV | G2: Source total daily return | H2: Calculated holdings return | I2: Holdings return difference | J2: Formula end NAV | K2: Engine end NAV | L2: NAV difference | M2: Underlying start spot | N2: Underlying end spot | O2: Underlying index start | P2: Underlying index end | Q2: Underlying price change | R2: Lease book start — holdings sum | S2: Lease book end — holdings sum | T2: Keep book start — holdings sum | U2: Keep book end — holdings sum | V2: Lease book start in underlying | W2: Lease book end in underlying | X2: Keep book start in underlying | Y2: Keep book end in underlying | Z2: Total books start in underlying | AA2: Lease standalone return in underlying | AB2: Lease contribution to combined book return | AC2: Keep standalone return in underlying | AD2: Keep contribution to combined book return | AE2: Combined books return in underlying | AF2: Reconstructed total daily return | AG2: Underlying/book return difference | AH2: Lease book interval P&L | AI2: Keep book interval P&L | AJ2: Lease internal transfer check | AK2: Keep internal transfer check | AL2: Lease external/rebalancing transfer | AM2: Keep external/rebalancing transfer | AN2: Lease opening value | AO2: Lease accumulated P&L | AP2: Lease accumulated external transfers | AQ2: Lease book end — roll-forward | AR2: Lease holdings vs roll-forward difference | AS2: Keep opening value | AT2: Keep accumulated P&L | AU2: Keep accumulated external transfers | AV2: Keep book end — roll-forward | AW2: Keep holdings vs roll-forward difference | AX2: Lease book start — engine audit | AY2: Lease book end — engine audit | AZ2: Lease book engine audit difference | BA2: Keep book start — engine audit | BB2: Keep book end — engine audit | BC2: Keep book engine audit difference | BD2: Direct/replicating contribution | BE2: Treasury contribution | BF2: Futures contribution | BG2: Cash/financing contribution | BH2: Detailed contribution sum | BI2: Detailed return difference | BJ2: Actual holding count | BK2: Name | BL2: Type | BM2: Book | BN2: Side | BO2: Contract type | BP2: Start price | BQ2: End price | BR2: Quantity / units | BS2: Position (% NAV) | BT2: Value / notional | BU2: Start value | BV2: End value | BW2: Economic P&L | BX2: Internal transfer | BY2: Spot price — start | BZ2: Spot price — end | CA2: Premium | CB2: Matched USD rate | CC2: Lease rate | CD2: Maturity (days) | CE2: Return contribution | CF2: Name | CG2: Type | CH2: Book | CI2: Side | CJ2: Contract type | CK2: Start price | CL2: End price | CM2: Quantity / units | CN2: Position (% NAV) | CO2: Value / notional | CP2: Start value | CQ2: End value | CR2: Economic P&L | CS2: Internal transfer | CT2: Spot price — start | CU2: Spot price — end | CV2: Premium | CW2: Matched USD rate | CX2: Lease rate | CY2: Maturity (days) | CZ2: Return contribution | DA2: Name | DB2: Type | DC2: Book | DD2: Side | DE2: Contract type | DF2: Start price | DG2: End price | DH2: Quantity / units | DI2: Position (% NAV) | DJ2: Value / notional | DK2: Start value | DL2: End value | DM2: Economic P&L | DN2: Internal transfer | DO2: Spot price — start | DP2: Spot price — end | DQ2: Premium | DR2: Matched USD rate | DS2: Lease rate | DT2: Maturity (days) | DU2: Return contribution | DV2: Name | DW2: Type | DX2: Book | DY2: Side | DZ2: Contract type | EA2: Start price | EB2: End price | EC2: Quantity / units | ED2: Position (% NAV) | EE2: Value / notional | EF2: Start value | EG2: End value | EH2: Economic P&L | EI2: Internal transfer | EJ2: Spot price — start | EK2: Spot price — end | EL2: Premium | EM2: Matched USD rate | EN2: Lease rate | EO2: Maturity (days) | EP2: Return contribution | EQ2: Name | ER2: Type | ES2: Book | ET2: Side | EU2: Contract type | EV2: Start price | EW2: End price | EX2: Quantity / units | EY2: Position (% NAV) | EZ2: Value / notional | FA2: Start value | FB2: End value | FC2: Economic P&L | FD2: Internal transfer | FE2: Spot price — start | FF2: Spot price — end | FG2: Premium | FH2: Matched USD rate | FI2: Lease rate | FJ2: Maturity (days) | FK2: Return contribution | FL2: Name | FM2: Type | FN2: Book | FO2: Side | FP2: Contract type | FQ2: Start price | FR2: End price | FS2: Quantity / units | FT2: Position (% NAV) | FU2: Value / notional | FV2: Start value | FW2: End value | FX2: Economic P&L | FY2: Internal transfer | FZ2: Spot price — start | GA2: Spot price — end | GB2: Premium | GC2: Matched USD rate | GD2: Lease rate | GE2: Maturity (days) | GF2: Return contribution | GG2: Name | GH2: Type | GI2: Book | GJ2: Side | GK2: Contract type | GL2: Start price | GM2: End price | GN2: Quantity / units | GO2: Position (% NAV) | GP2: Value / notional | GQ2: Start value | GR2: End value | GS2: Economic P&L | GT2: Internal transfer | GU2: Spot price — start | GV2: Spot price — end | GW2: Premium | GX2: Matched USD rate | GY2: Lease rate | GZ2: Maturity (days) | HA2: Return contribution | HB2: Name | HC2: Type | HD2: Book | HE2: Side | HF2: Contract type | HG2: Start price | HH2: End price | HI2: Quantity / units | HJ2: Position (% NAV) | HK2: Value / notional | HL2: Start value | HM2: End value | HN2: Economic P&L | HO2: Internal transfer | HP2: Spot price — start | HQ2: Spot price — end | HR2: Premium | HS2: Matched USD rate | HT2: Lease rate | HU2: Maturity (days) | HV2: Return contribution | HW2: Name | HX2: Type | HY2: Book | HZ2: Side | IA2: Contract type | IB2: Start price | IC2: End price | ID2: Quantity / units | IE2: Position (% NAV) | IF2: Value / notional | IG2: Start value | IH2: End value | II2: Economic P&L | IJ2: Internal transfer | IK2: Spot price — start | IL2: Spot price — end | IM2: Premium | IN2: Matched USD rate | IO2: Lease rate | IP2: Maturity (days) | IQ2: Return contribution | IR2: Name | IS2: Type | IT2: Book | IU2: Side | IV2: Contract type | IW2: Start price | IX2: End price | IY2: Quantity / units | IZ2: Position (% NAV) | JA2: Value / notional | JB2: Start value | JC2: End value | JD2: Economic P&L | JE2: Internal transfer | JF2: Spot price — start | JG2: Spot price — end | JH2: Premium | JI2: Matched USD rate | JJ2: Lease rate | JK2: Maturity (days) | JL2: Return contribution
A3: 25205 | B3: 25206 | C3: =B3-A3 -> 1 | D3: 25205 | E3: positive | F3: 1 | G3: 0.00048216334 | H3: =SUM(CE3,CZ3,DU3,EP3,FK3,GF3,HA3,HV3,IQ3,JL3) -> 0.00048216334 | I3: =G3-H3 -> 0 | J3: =F3*(1+H3) -> 1.0004822 | K3: 1.0004822 | L3: =K3-J3 -> 0 | M3: 1.958 | N3: 1.967 | O3: =M3/$M$3 -> 1 | P3: =N3/$M$3 -> 1.0045965 | Q3: =IFERROR(N3/M3-1,0) -> 0.0045965271 | R3: =SUM(IF(BM3="lease",BU3,0),IF(CH3="lease",CP3,0),IF(DC3="lease",DK3,0),IF(DX3="lease",EF3,0),IF(ES3="lease",FA3,0),IF(FN3="lease",FV3,0),IF(GI3="lease",GQ3,0),IF(HD3="lease",HL3,0),IF(HY3="lease",IG3,0),IF(IT3="lease",JB3,0)) -> 1 | S3: =SUM(IF(BM3="lease",BV3,0),IF(CH3="lease",CQ3,0),IF(DC3="lease",DL3,0),IF(DX3="lease",EG3,0),IF(ES3="lease",FB3,0),IF(FN3="lease",FW3,0),IF(GI3="lease",GR3,0),IF(HD3="lease",HM3,0),IF(HY3="lease",IH3,0),IF(IT3="lease",JC3,0)) -> 1.0004822 | T3: =SUM(IF(BM3="keep",BU3,0),IF(CH3="keep",CP3,0),IF(DC3="keep",DK3,0),IF(DX3="keep",EF3,0),IF(ES3="keep",FA3,0),IF(FN3="keep",FV3,0),IF(GI3="keep",GQ3,0),IF(HD3="keep",HL3,0),IF(HY3="keep",IG3,0),IF(IT3="keep",JB3,0)) -> 0 | U3: =SUM(IF(BM3="keep",BV3,0),IF(CH3="keep",CQ3,0),IF(DC3="keep",DL3,0),IF(DX3="keep",EG3,0),IF(ES3="keep",FB3,0),IF(FN3="keep",FW3,0),IF(GI3="keep",GR3,0),IF(HD3="keep",HM3,0),IF(HY3="keep",IH3,0),IF(IT3="keep",JC3,0)) -> 0 | V3: =R3/O3 -> 1 | W3: =S3/P3 -> 0.99590446 | X3: =T3/O3 -> 0 | Y3: =U3/P3 -> 0 | Z3: =V3+X3 -> 1 | AA3: =IFERROR(W3/V3-1,0) -> -0.0040955385 | AB3: =IFERROR((W3-V3)/Z3,0) -> -0.0040955385 | AC3: =IFERROR(Y3/X3-1,0) -> 0 | AD3: =IFERROR((Y3-X3)/Z3,0) -> 0 | AE3: =AB3+AD3 -> -0.0040955385 | AF3: =(1+Q3)*(1+AE3)-1 -> 0.00048216334 | AG3: =G3-AF3 -> 5.2041704e-17 | AH3: =SUM(IF(BM3="lease",BW3,0),IF(CH3="lease",CR3,0),IF(DC3="lease",DM3,0),IF(DX3="lease",EH3,0),IF(ES3="lease",FC3,0),IF(FN3="lease",FX3,0),IF(GI3="lease",GS3,0),IF(HD3="lease",HN3,0),IF(HY3="lease",II3,0),IF(IT3="lease",JD3,0)) -> 0.00048216334 | AI3: =SUM(IF(BM3="keep",BW3,0),IF(CH3="keep",CR3,0),IF(DC3="keep",DM3,0),IF(DX3="keep",EH3,0),IF(ES3="keep",FC3,0),IF(FN3="keep",FX3,0),IF(GI3="keep",GS3,0),IF(HD3="keep",HN3,0),IF(HY3="keep",II3,0),IF(IT3="keep",JD3,0)) -> 0 | AJ3: =SUM(IF(BM3="lease",BX3,0),IF(CH3="lease",CS3,0),IF(DC3="lease",DN3,0),IF(DX3="lease",EI3,0),IF(ES3="lease",FD3,0),IF(FN3="lease",FY3,0),IF(GI3="lease",GT3,0),IF(HD3="lease",HO3,0),IF(HY3="lease",IJ3,0),IF(IT3="lease",JE3,0)) -> 0 | AK3: =SUM(IF(BM3="keep",BX3,0),IF(CH3="keep",CS3,0),IF(DC3="keep",DN3,0),IF(DX3="keep",EI3,0),IF(ES3="keep",FD3,0),IF(FN3="keep",FY3,0),IF(GI3="keep",GT3,0),IF(HD3="keep",HO3,0),IF(HY3="keep",IJ3,0),IF(IT3="keep",JE3,0)) -> 0 | AL3: =0 -> 0 | AM3: =0 -> 0 | AN3: =R3 -> 1 | AO3: =AH3 -> 0.00048216334 | AP3: =AL3 -> 0 | AQ3: =AN3+AO3+AP3 -> 1.0004822 | AR3: =S3-AQ3 -> 0 | AS3: =T3 -> 0 | AT3: =AI3 -> 0 | AU3: =AM3 -> 0 | AV3: =AS3+AT3+AU3 -> 0 | AW3: =U3-AV3 -> 0 | AX3: 1 | AY3: 1.0004822 | AZ3: =S3-AY3 -> 0 | BA3: 0 | BB3: 0 | BC3: =U3-BB3 -> 0 | BD3: =SUM(IF(BL3="direct",CE3,0),IF(CG3="direct",CZ3,0),IF(DB3="direct",DU3,0),IF(DW3="direct",EP3,0),IF(ER3="direct",FK3,0),IF(FM3="direct",GF3,0),IF(GH3="direct",HA3,0),IF(HC3="direct",HV3,0),IF(HX3="direct",IQ3,0),IF(IS3="direct",JL3,0)) -> 0.0024997145 | BE3: =SUM(IF(BL3="treasury",CE3,0),IF(CG3="treasury",CZ3,0),IF(DB3="treasury",DU3,0),IF(DW3="treasury",EP3,0),IF(ER3="treasury",FK3,0),IF(FM3="treasury",GF3,0),IF(GH3="treasury",HA3,0),IF(HC3="treasury",HV3,0),IF(HX3="treasury",IQ3,0),IF(IS3="treasury",JL3,0)) -> 7.6600564e-05 | BF3: =SUM(IF(BL3="future",CE3,0),IF(CG3="future",CZ3,0),IF(DB3="future",DU3,0),IF(DW3="future",EP3,0),IF(ER3="future",FK3,0),IF(FM3="future",GF3,0),IF(GH3="future",HA3,0),IF(HC3="future",HV3,0),IF(HX3="future",IQ3,0),IF(IS3="future",JL3,0)) -> -0.0020941517 | BG3: =SUM(IF(BL3="cash",CE3,0),IF(CG3="cash",CZ3,0),IF(DB3="cash",DU3,0),IF(DW3="cash",EP3,0),IF(ER3="cash",FK3,0),IF(FM3="cash",GF3,0),IF(GH3="cash",HA3,0),IF(HC3="cash",HV3,0),IF(HX3="cash",IQ3,0),IF(IS3="cash",JL3,0)) -> 0 | BH3: =SUM(BD3:BG3) -> 0.00048216334 | BI3: =G3-BH3 -> 0 | BJ3: =COUNTA(BK3,CF3,DA3,DV3,EQ3,FL3,GG3,HB3,HW3,IR3) -> 5 | BK3: Direct commodity holding | BL3: direct | BM3: lease | BN3: long | BP3: 1.958 | BQ3: 1.967 | BR3: 0.27816054 | BS3: 0.54463834 | BT3: 0.54463834 | BU3: 0.54463834 | BV3: 0.54714179 | BW3: 0.0024997145 | BX3: 3.7303996e-06 | BY3: 1.958 | BZ3: 1.967 | CE3: =IFERROR(BW3/F3,0) -> 0.0024997145 | CF3: Treasury collateral | CG3: treasury | CH3: lease | CI3: long | CK3: 100 | CL3: 100.01682 | CM3: 0.0045536166 | CN3: 0.45536166 | CO3: 0.45536166 | CP3: 0.45536166 | CQ3: 0.45543826 | CR3: 7.6600564e-05 | CS3: 7.727651e-17 | CT3: 1.958 | CU3: 1.967 | CY3: 27 | CZ3: =IFERROR(CR3/F3,0) -> 7.6600564e-05 | DA3: SI69F | DB3: future | DC3: lease | DD3: long | DE3: regular | DF3: 1.957 | DG3: 1.948 | DH3: 0.23268352 | DI3: 0.45536166 | DJ3: 0.45536166 | DK3: 0 | DL3: 0 | DM3: -0.0020941517 | DN3: 0.0020941517 | DO3: 1.958 | DP3: 1.967 | DQ3: -0.00051072523 | DR3: 0.0614 | DS3: 0.068304248 | DT3: 27 | DU3: =IFERROR(DM3/F3,0) -> -0.0020941517 | DV3: Lease cash / margin / financing | DW3: cash | DX3: lease | DY3: cash | EA3: 1 | EB3: 1 | EC3: 0 | EE3: 0 | EF3: 0 | EG3: -0.0020978821 | EH3: 0 | EI3: -0.0020978821 | EJ3: 1.958 | EK3: 1.967 | EP3: =IFERROR(EH3/F3,0) -> 0 | EQ3: Keep cash / margin / financing | ER3: cash | ES3: keep | ET3: cash | EV3: 1 | EW3: 1 | EX3: 0 | EZ3: 0 | FA3: 0 | FB3: 0 | FC3: 0 | FD3: 0 | FE3: 1.958 | FF3: 1.967 | FK3: =IFERROR(FC3/F3,0) -> 0
A4: 25206 | B4: 25209 | C4: =B4-A4 -> 3 | D4: 25206 | E4: positive | F4: 1.0004822 | G4: -0.0036029406 | H4: =SUM(CE4,CZ4,DU4,EP4,FK4,GF4,HA4,HV4,IQ4,JL4) -> -0.0036029406 | I4: =G4-H4 -> 4.3368087e-19 | J4: =F4*(1+H4) -> 0.99687749 | K4: 0.99687749 | L4: =K4-J4 -> 0 | M4: 1.967 | N4: 1.972 | O4: =M4/$M$3 -> 1.0045965 | P4: =N4/$M$3 -> 1.0071502 | Q4: =IFERROR(N4/M4-1,0) -> 0.002541942 | R4: =SUM(IF(BM4="lease",BU4,0),IF(CH4="lease",CP4,0),IF(DC4="lease",DK4,0),IF(DX4="lease",EF4,0),IF(ES4="lease",FA4,0),IF(FN4="lease",FV4,0),IF(GI4="lease",GQ4,0),IF(HD4="lease",HL4,0),IF(HY4="lease",IG4,0),IF(IT4="lease",JB4,0)) -> 1.0004822 | S4: =SUM(IF(BM4="lease",BV4,0),IF(CH4="lease",CQ4,0),IF(DC4="lease",DL4,0),IF(DX4="lease",EG4,0),IF(ES4="lease",FB4,0),IF(FN4="lease",FW4,0),IF(GI4="lease",GR4,0),IF(HD4="lease",HM4,0),IF(HY4="lease",IH4,0),IF(IT4="lease",JC4,0)) -> 0.99687749 | T4: =SUM(IF(BM4="keep",BU4,0),IF(CH4="keep",CP4,0),IF(DC4="keep",DK4,0),IF(DX4="keep",EF4,0),IF(ES4="keep",FA4,0),IF(FN4="keep",FV4,0),IF(GI4="keep",GQ4,0),IF(HD4="keep",HL4,0),IF(HY4="keep",IG4,0),IF(IT4="keep",JB4,0)) -> 0 | U4: =SUM(IF(BM4="keep",BV4,0),IF(CH4="keep",CQ4,0),IF(DC4="keep",DL4,0),IF(DX4="keep",EG4,0),IF(ES4="keep",FB4,0),IF(FN4="keep",FW4,0),IF(GI4="keep",GR4,0),IF(HD4="keep",HM4,0),IF(HY4="keep",IH4,0),IF(IT4="keep",JC4,0)) -> 0 | V4: =R4/O4 -> 0.99590446 | W4: =S4/P4 -> 0.98980026 | X4: =T4/O4 -> 0 | Y4: =U4/P4 -> 0 | Z4: =V4+X4 -> 0.99590446 | AA4: =IFERROR(W4/V4-1,0) -> -0.0061293023 | AB4: =IFERROR((W4-V4)/Z4,0) -> -0.0061293023 | AC4: =IFERROR(Y4/X4-1,0) -> 0 | AD4: =IFERROR((Y4-X4)/Z4,0) -> 0 | AE4: =AB4+AD4 -> -0.0061293023 | AF4: =(1+Q4)*(1+AE4)-1 -> -0.0036029406 | AG4: =G4-AF4 -> -5.2041704e-17 | AH4: =SUM(IF(BM4="lease",BW4,0),IF(CH4="lease",CR4,0),IF(DC4="lease",DM4,0),IF(DX4="lease",EH4,0),IF(ES4="lease",FC4,0),IF(FN4="lease",FX4,0),IF(GI4="lease",GS4,0),IF(HD4="lease",HN4,0),IF(HY4="lease",II4,0),IF(IT4="lease",JD4,0)) -> -0.0036046778 | AI4: =SUM(IF(BM4="keep",BW4,0),IF(CH4="keep",CR4,0),IF(DC4="keep",DM4,0),IF(DX4="keep",EH4,0),IF(ES4="keep",FC4,0),IF(FN4="keep",FX4,0),IF(GI4="keep",GS4,0),IF(HD4="keep",HN4,0),IF(HY4="keep",II4,0),IF(IT4="keep",JD4,0)) -> 0 | AJ4: =SUM(IF(BM4="lease",BX4,0),IF(CH4="lease",CS4,0),IF(DC4="lease",DN4,0),IF(DX4="lease",EI4,0),IF(ES4="lease",FD4,0),IF(FN4="lease",FY4,0),IF(GI4="lease",GT4,0),IF(HD4="lease",HO4,0),IF(HY4="lease",IJ4,0),IF(IT4="lease",JE4,0)) -> 0 | AK4: =SUM(IF(BM4="keep",BX4,0),IF(CH4="keep",CS4,0),IF(DC4="keep",DN4,0),IF(DX4="keep",EI4,0),IF(ES4="keep",FD4,0),IF(FN4="keep",FY4,0),IF(GI4="keep",GT4,0),IF(HD4="keep",HO4,0),IF(HY4="keep",IJ4,0),IF(IT4="keep",JE4,0)) -> 0 | AL4: =R4-S3 -> 0 | AM4: =T4-U3 -> 0 | AN4: =AN3 -> 1 | AO4: =AO3+AH4 -> -0.0031225144 | AP4: =AP3+AL4 -> 0 | AQ4: =AN4+AO4+AP4 -> 0.99687749 | AR4: =S4-AQ4 -> -1.110223e-16 | AS4: =AS3 -> 0 | AT4: =AT3+AI4 -> 0 | AU4: =AU3+AM4 -> 0 | AV4: =AS4+AT4+AU4 -> 0 | AW4: =U4-AV4 -> 0 | AX4: 1.0004822 | AY4: 0.99687749 | AZ4: =S4-AY4 -> 0 | BA4: 0 | BB4: 0 | BC4: =U4-BB4 -> 0 | BD4: =SUM(IF(BL4="direct",CE4,0),IF(CG4="direct",CZ4,0),IF(DB4="direct",DU4,0),IF(DW4="direct",EP4,0),IF(ER4="direct",FK4,0),IF(FM4="direct",GF4,0),IF(GH4="direct",HA4,0),IF(HC4="direct",HV4,0),IF(HX4="direct",IQ4,0),IF(IS4="direct",JL4,0)) -> 0 | BE4: =SUM(IF(BL4="treasury",CE4,0),IF(CG4="treasury",CZ4,0),IF(DB4="treasury",DU4,0),IF(DW4="treasury",EP4,0),IF(ER4="treasury",FK4,0),IF(FM4="treasury",GF4,0),IF(GH4="treasury",HA4,0),IF(HC4="treasury",HV4,0),IF(HX4="treasury",IQ4,0),IF(IS4="treasury",JL4,0)) -> 0.00050383562 | BF4: =SUM(IF(BL4="future",CE4,0),IF(CG4="future",CZ4,0),IF(DB4="future",DU4,0),IF(DW4="future",EP4,0),IF(ER4="future",FK4,0),IF(FM4="future",GF4,0),IF(GH4="future",HA4,0),IF(HC4="future",HV4,0),IF(HX4="future",IQ4,0),IF(IS4="future",JL4,0)) -> -0.0041067762 | BG4: =SUM(IF(BL4="cash",CE4,0),IF(CG4="cash",CZ4,0),IF(DB4="cash",DU4,0),IF(DW4="cash",EP4,0),IF(ER4="cash",FK4,0),IF(FM4="cash",GF4,0),IF(GH4="cash",HA4,0),IF(HC4="cash",HV4,0),IF(HX4="cash",IQ4,0),IF(IS4="cash",JL4,0)) -> 0 | BH4: =SUM(BD4:BG4) -> -0.0036029406 | BI4: =G4-BH4 -> 0 | BJ4: =COUNTA(BK4,CF4,DA4,DV4,EQ4,FL4,GG4,HB4,HW4,IR4) -> 4 | BK4: Treasury collateral | BL4: treasury | BM4: lease | BN4: long | BP4: 100.01682 | BQ4: 100.06721 | BR4: 0.010003139 | BS4: 1 | BT4: 1.0004822 | BU4: 1.0004822 | BV4: 1.0009862 | BW4: 0.00050407855 | BX4: 9.7795036e-17 | BY4: 1.967 | BZ4: 1.972 | CD4: 26 | CE4: =IFERROR(BW4/F4,0) -> 0.00050383562 | CF4: SI69F | CG4: future | CH4: lease | CI4: long | CJ4: regular | CK4: 1.948 | CL4: 1.94 | CM4: 0.51359454 | CN4: 1 | CO4: 1.0004822 | CP4: 0 | CQ4: 0 | CR4: -0.0041087563 | CS4: 0.0041087563 | CT4: 1.967 | CU4: 1.972 | CV4: -0.0096593798 | CW4: 0.0613 | CX4: 0.19690283 | CY4: 26 | CZ4: =IFERROR(CR4/F4,0) -> -0.0041067762 | DA4: Lease cash / margin / financing | DB4: cash | DC4: lease | DD4: cash | DF4: 1 | DG4: 1 | DH4: 0 | DJ4: 0 | DK4: 0 | DL4: -0.0041087563 | DM4: 0 | DN4: -0.0041087563 | DO4: 1.967 | DP4: 1.972 | DU4: =IFERROR(DM4/F4,0) -> 0 | DV4: Keep cash / margin / financing | DW4: cash | DX4: keep | DY4: cash | EA4: 1 | EB4: 1 | EC4: 0 | EE4: 0 | EF4: 0 | EG4: 0 | EH4: 0 | EI4: 0 | EJ4: 1.967 | EK4: 1.972 | EP4: =IFERROR(EH4/F4,0) -> 0
A5: 25209 | B5: 25210 | C5: =B5-A5 -> 1 | D5: 25209 | E5: positive | F5: 0.99687749 | G5: 0.0053239542 | H5: =SUM(CE5,CZ5,DU5,EP5,FK5,GF5,HA5,HV5,IQ5,JL5) -> 0.0053239542 | I5: =G5-H5 -> 0 | J5: =F5*(1+H5) -> 1.0021848 | K5: 1.0021848 | L5: =K5-J5 -> 0 | M5: 1.972 | N5: 1.977 | O5: =M5/$M$3 -> 1.0071502 | P5: =N5/$M$3 -> 1.0097038 | Q5: =IFERROR(N5/M5-1,0) -> 0.002535497 | R5: =SUM(IF(BM5="lease",BU5,0),IF(CH5="lease",CP5,0),IF(DC5="lease",DK5,0),IF(DX5="lease",EF5,0),IF(ES5="lease",FA5,0),IF(FN5="lease",FV5,0),IF(GI5="lease",GQ5,0),IF(HD5="lease",HL5,0),IF(HY5="lease",IG5,0),IF(IT5="lease",JB5,0)) -> 0.99687749 | S5: =SUM(IF(BM5="lease",BV5,0),IF(CH5="lease",CQ5,0),IF(DC5="lease",DL5,0),IF(DX5="lease",EG5,0),IF(ES5="lease",FB5,0),IF(FN5="lease",FW5,0),IF(GI5="lease",GR5,0),IF(HD5="lease",HM5,0),IF(HY5="lease",IH5,0),IF(IT5="lease",JC5,0)) -> 1.0021848 | T5: =SUM(IF(BM5="keep",BU5,0),IF(CH5="keep",CP5,0),IF(DC5="keep",DK5,0),IF(DX5="keep",EF5,0),IF(ES5="keep",FA5,0),IF(FN5="keep",FV5,0),IF(GI5="keep",GQ5,0),IF(HD5="keep",HL5,0),IF(HY5="keep",IG5,0),IF(IT5="keep",JB5,0)) -> 0 | U5: =SUM(IF(BM5="keep",BV5,0),IF(CH5="keep",CQ5,0),IF(DC5="keep",DL5,0),IF(DX5="keep",EG5,0),IF(ES5="keep",FB5,0),IF(FN5="keep",FW5,0),IF(GI5="keep",GR5,0),IF(HD5="keep",HM5,0),IF(HY5="keep",IH5,0),IF(IT5="keep",JC5,0)) -> 0 | V5: =R5/O5 -> 0.98980026 | W5: =S5/P5 -> 0.9925533 | X5: =T5/O5 -> 0 | Y5: =U5/P5 -> 0 | Z5: =V5+X5 -> 0.98980026 | AA5: =IFERROR(W5/V5-1,0) -> 0.002781405 | AB5: =IFERROR((W5-V5)/Z5,0) -> 0.002781405 | AC5: =IFERROR(Y5/X5-1,0) -> 0 | AD5: =IFERROR((Y5-X5)/Z5,0) -> 0 | AE5: =AB5+AD5 -> 0.002781405 | AF5: =(1+Q5)*(1+AE5)-1 -> 0.0053239542 | AG5: =G5-AF5 -> 2.1423835e-16 | AH5: =SUM(IF(BM5="lease",BW5,0),IF(CH5="lease",CR5,0),IF(DC5="lease",DM5,0),IF(DX5="lease",EH5,0),IF(ES5="lease",FC5,0),IF(FN5="lease",FX5,0),IF(GI5="lease",GS5,0),IF(HD5="lease",HN5,0),IF(HY5="lease",II5,0),IF(IT5="lease",JD5,0)) -> 0.0053073301 | AI5: =SUM(IF(BM5="keep",BW5,0),IF(CH5="keep",CR5,0),IF(DC5="keep",DM5,0),IF(DX5="keep",EH5,0),IF(ES5="keep",FC5,0),IF(FN5="keep",FX5,0),IF(GI5="keep",GS5,0),IF(HD5="keep",HN5,0),IF(HY5="keep",II5,0),IF(IT5="keep",JD5,0)) -> 0 | AJ5: =SUM(IF(BM5="lease",BX5,0),IF(CH5="lease",CS5,0),IF(DC5="lease",DN5,0),IF(DX5="lease",EI5,0),IF(ES5="lease",FD5,0),IF(FN5="lease",FY5,0),IF(GI5="lease",GT5,0),IF(HD5="lease",HO5,0),IF(HY5="lease",IJ5,0),IF(IT5="lease",JE5,0)) -> 0 | AK5: =SUM(IF(BM5="keep",BX5,0),IF(CH5="keep",CS5,0),IF(DC5="keep",DN5,0),IF(DX5="keep",EI5,0),IF(ES5="keep",FD5,0),IF(FN5="keep",FY5,0),IF(GI5="keep",GT5,0),IF(HD5="keep",HO5,0),IF(HY5="keep",IJ5,0),IF(IT5="keep",JE5,0)) -> 0 | AL5: =R5-S4 -> 0 | AM5: =T5-U4 -> 0 | AN5: =AN4 -> 1 | AO5: =AO4+AH5 -> 0.0021848157 | AP5: =AP4+AL5 -> 0 | AQ5: =AN5+AO5+AP5 -> 1.0021848 | AR5: =S5-AQ5 -> 0 | AS5: =AS4 -> 0 | AT5: =AT4+AI5 -> 0 | AU5: =AU4+AM5 -> 0 | AV5: =AS5+AT5+AU5 -> 0 | AW5: =U5-AV5 -> 0 | AX5: 0.99687749 | AY5: 1.0021848 | AZ5: =S5-AY5 -> 0 | BA5: 0 | BB5: 0 | BC5: =U5-BB5 -> 0 | BD5: =SUM(IF(BL5="direct",CE5,0),IF(CG5="direct",CZ5,0),IF(DB5="direct",DU5,0),IF(DW5="direct",EP5,0),IF(ER5="direct",FK5,0),IF(FM5="direct",GF5,0),IF(GH5="direct",HA5,0),IF(HC5="direct",HV5,0),IF(HX5="direct",IQ5,0),IF(IS5="direct",JL5,0)) -> 0 | BE5: =SUM(IF(BL5="treasury",CE5,0),IF(CG5="treasury",CZ5,0),IF(DB5="treasury",DU5,0),IF(DW5="treasury",EP5,0),IF(ER5="treasury",FK5,0),IF(FM5="treasury",GF5,0),IF(GH5="treasury",HA5,0),IF(HC5="treasury",HV5,0),IF(HX5="treasury",IQ5,0),IF(IS5="treasury",JL5,0)) -> 0.00016931507 | BF5: =SUM(IF(BL5="future",CE5,0),IF(CG5="future",CZ5,0),IF(DB5="future",DU5,0),IF(DW5="future",EP5,0),IF(ER5="future",FK5,0),IF(FM5="future",GF5,0),IF(GH5="future",HA5,0),IF(HC5="future",HV5,0),IF(HX5="future",IQ5,0),IF(IS5="future",JL5,0)) -> 0.0051546392 | BG5: =SUM(IF(BL5="cash",CE5,0),IF(CG5="cash",CZ5,0),IF(DB5="cash",DU5,0),IF(DW5="cash",EP5,0),IF(ER5="cash",FK5,0),IF(FM5="cash",GF5,0),IF(GH5="cash",HA5,0),IF(HC5="cash",HV5,0),IF(HX5="cash",IQ5,0),IF(IS5="cash",JL5,0)) -> 0 | BH5: =SUM(BD5:BG5) -> 0.0053239542 | BI5: =G5-BH5 -> 0 | BJ5: =COUNTA(BK5,CF5,DA5,DV5,EQ5,FL5,GG5,HB5,HW5,IR5) -> 4 | BK5: Treasury collateral | BL5: treasury | BM5: lease | BN5: long | BP5: 100.06721 | BQ5: 100.08416 | BR5: 0.0099620789 | BS5: 1 | BT5: 0.99687749 | BU5: 0.99687749 | BV5: 0.99704627 | BW5: 0.00016878638 | BX5: 4.5617806e-17 | BY5: 1.972 | BZ5: 1.977 | CD5: 23 | CE5: =IFERROR(BW5/F5,0) -> 0.00016931507 | CF5: SI69F | CG5: future | CH5: lease | CI5: long | CJ5: regular | CK5: 1.94 | CL5: 1.95 | CM5: 0.51385437 | CN5: 1 | CO5: 0.99687749 | CP5: 0 | CQ5: 0 | CR5: 0.0051385437 | CS5: -0.0051385437 | CT5: 1.972 | CU5: 1.977 | CV5: -0.016227181 | CW5: 0.0618 | CX5: 0.3193183 | CY5: 23 | CZ5: =IFERROR(CR5/F5,0) -> 0.0051546392 | DA5: Lease cash / margin / financing | DB5: cash | DC5: lease | DD5: cash | DF5: 1 | DG5: 1 | DH5: -1.110223e-16 | DJ5: -1.110223e-16 | DK5: -1.110223e-16 | DL5: 0.0051385437 | DM5: 0 | DN5: 0.0051385437 | DO5: 1.972 | DP5: 1.977 | DU5: =IFERROR(DM5/F5,0) -> 0 | DV5: Keep cash / margin / financing | DW5: cash | DX5: keep | DY5: cash | EA5: 1 | EB5: 1 | EC5: 0 | EE5: 0 | EF5: 0 | EG5: 0 | EH5: 0 | EI5: 0 | EJ5: 1.972 | EK5: 1.977 | EP5: =IFERROR(EH5/F5,0) -> 0
A6: 25210 | B6: 25211 | C6: =B6-A6 -> 1 | D6: 25210 | E6: positive | F6: 1.0021848 | G6: 0.018119951 | H6: =SUM(CE6,CZ6,DU6,EP6,FK6,GF6,HA6,HV6,IQ6,JL6) -> 0.018119951 | I6: =G6-H6 -> 0 | J6: =F6*(1+H6) -> 1.0203444 | K6: 1.0203444 | L6: =K6-J6 -> 0 | M6: 1.977 | N6: 2.017 | O6: =M6/$M$3 -> 1.0097038 | P6: =N6/$M$3 -> 1.0301328 | Q6: =IFERROR(N6/M6-1,0) -> 0.020232676 | R6: =SUM(IF(BM6="lease",BU6,0),IF(CH6="lease",CP6,0),IF(DC6="lease",DK6,0),IF(DX6="lease",EF6,0),IF(ES6="lease",FA6,0),IF(FN6="lease",FV6,0),IF(GI6="lease",GQ6,0),IF(HD6="lease",HL6,0),IF(HY6="lease",IG6,0),IF(IT6="lease",JB6,0)) -> 1.0021848 | S6: =SUM(IF(BM6="lease",BV6,0),IF(CH6="lease",CQ6,0),IF(DC6="lease",DL6,0),IF(DX6="lease",EG6,0),IF(ES6="lease",FB6,0),IF(FN6="lease",FW6,0),IF(GI6="lease",GR6,0),IF(HD6="lease",HM6,0),IF(HY6="lease",IH6,0),IF(IT6="lease",JC6,0)) -> 1.0203444 | T6: =SUM(IF(BM6="keep",BU6,0),IF(CH6="keep",CP6,0),IF(DC6="keep",DK6,0),IF(DX6="keep",EF6,0),IF(ES6="keep",FA6,0),IF(FN6="keep",FV6,0),IF(GI6="keep",GQ6,0),IF(HD6="keep",HL6,0),IF(HY6="keep",IG6,0),IF(IT6="keep",JB6,0)) -> 0 | U6: =SUM(IF(BM6="keep",BV6,0),IF(CH6="keep",CQ6,0),IF(DC6="keep",DL6,0),IF(DX6="keep",EG6,0),IF(ES6="keep",FB6,0),IF(FN6="keep",FW6,0),IF(GI6="keep",GR6,0),IF(HD6="keep",HM6,0),IF(HY6="keep",IH6,0),IF(IT6="keep",JC6,0)) -> 0 | V6: =R6/O6 -> 0.9925533 | W6: =S6/P6 -> 0.99049789 | X6: =T6/O6 -> 0 | Y6: =U6/P6 -> 0 | Z6: =V6+X6 -> 0.9925533 | AA6: =IFERROR(W6/V6-1,0) -> -0.0020708266 | AB6: =IFERROR((W6-V6)/Z6,0) -> -0.0020708266 | AC6: =IFERROR(Y6/X6-1,0) -> 0 | AD6: =IFERROR((Y6-X6)/Z6,0) -> 0 | AE6: =AB6+AD6 -> -0.0020708266 | AF6: =(1+Q6)*(1+AE6)-1 -> 0.018119951 | AG6: =G6-AF6 -> 4.8572257e-17 | AH6: =SUM(IF(BM6="lease",BW6,0),IF(CH6="lease",CR6,0),IF(DC6="lease",DM6,0),IF(DX6="lease",EH6,0),IF(ES6="lease",FC6,0),IF(FN6="lease",FX6,0),IF(GI6="lease",GS6,0),IF(HD6="lease",HN6,0),IF(HY6="lease",II6,0),IF(IT6="lease",JD6,0)) -> 0.01815954 | AI6: =SUM(IF(BM6="keep",BW6,0),IF(CH6="keep",CR6,0),IF(DC6="keep",DM6,0),IF(DX6="keep",EH6,0),IF(ES6="keep",FC6,0),IF(FN6="keep",FX6,0),IF(GI6="keep",GS6,0),IF(HD6="keep",HN6,0),IF(HY6="keep",II6,0),IF(IT6="keep",JD6,0)) -> 0 | AJ6: =SUM(IF(BM6="lease",BX6,0),IF(CH6="lease",CS6,0),IF(DC6="lease",DN6,0),IF(DX6="lease",EI6,0),IF(ES6="lease",FD6,0),IF(FN6="lease",FY6,0),IF(GI6="lease",GT6,0),IF(HD6="lease",HO6,0),IF(HY6="lease",IJ6,0),IF(IT6="lease",JE6,0)) -> 0 | AK6: =SUM(IF(BM6="keep",BX6,0),IF(CH6="keep",CS6,0),IF(DC6="keep",DN6,0),IF(DX6="keep",EI6,0),IF(ES6="keep",FD6,0),IF(FN6="keep",FY6,0),IF(GI6="keep",GT6,0),IF(HD6="keep",HO6,0),IF(HY6="keep",IJ6,0),IF(IT6="keep",JE6,0)) -> 0 | AL6: =R6-S5 -> 0 | AM6: =T6-U5 -> 0 | AN6: =AN5 -> 1 | AO6: =AO5+AH6 -> 0.020344355 | AP6: =AP5+AL6 -> 0 | AQ6: =AN6+AO6+AP6 -> 1.0203444 | AR6: =S6-AQ6 -> 0 | AS6: =AS5 -> 0 | AT6: =AT5+AI6 -> 0 | AU6: =AU5+AM6 -> 0 | AV6: =AS6+AT6+AU6 -> 0 | AW6: =U6-AV6 -> 0 | AX6: 1.0021848 | AY6: 1.0203444 | AZ6: =S6-AY6 -> 0 | BA6: 0 | BB6: 0 | BC6: =U6-BB6 -> 0 | BD6: =SUM(IF(BL6="direct",CE6,0),IF(CG6="direct",CZ6,0),IF(DB6="direct",DU6,0),IF(DW6="direct",EP6,0),IF(ER6="direct",FK6,0),IF(FM6="direct",GF6,0),IF(GH6="direct",HA6,0),IF(HC6="direct",HV6,0),IF(HX6="direct",IQ6,0),IF(IS6="direct",JL6,0)) -> 0 | BE6: =SUM(IF(BL6="treasury",CE6,0),IF(CG6="treasury",CZ6,0),IF(DB6="treasury",DU6,0),IF(DW6="treasury",EP6,0),IF(ER6="treasury",FK6,0),IF(FM6="treasury",GF6,0),IF(GH6="treasury",HA6,0),IF(HC6="treasury",HV6,0),IF(HX6="treasury",IQ6,0),IF(IS6="treasury",JL6,0)) -> 0.00017123288 | BF6: =SUM(IF(BL6="future",CE6,0),IF(CG6="future",CZ6,0),IF(DB6="future",DU6,0),IF(DW6="future",EP6,0),IF(ER6="future",FK6,0),IF(FM6="future",GF6,0),IF(GH6="future",HA6,0),IF(HC6="future",HV6,0),IF(HX6="future",IQ6,0),IF(IS6="future",JL6,0)) -> 0.017948718 | BG6: =SUM(IF(BL6="cash",CE6,0),IF(CG6="cash",CZ6,0),IF(DB6="cash",DU6,0),IF(DW6="cash",EP6,0),IF(ER6="cash",FK6,0),IF(FM6="cash",GF6,0),IF(GH6="cash",HA6,0),IF(HC6="cash",HV6,0),IF(HX6="cash",IQ6,0),IF(IS6="cash",JL6,0)) -> 0 | BH6: =SUM(BD6:BG6) -> 0.018119951 | BI6: =G6-BH6 -> 0 | BJ6: =COUNTA(BK6,CF6,DA6,DV6,EQ6,FL6,GG6,HB6,HW6,IR6) -> 4 | BK6: Treasury collateral | BL6: treasury | BM6: lease | BN6: long | BP6: 100.08416 | BQ6: 100.10129 | BR6: 0.010013421 | BS6: 1 | BT6: 1.0021848 | BU6: 1.0021848 | BV6: 1.0023564 | BW6: 0.00017160699 | BX6: -7.3508907e-17 | BY6: 1.977 | BZ6: 2.017 | CD6: 22 | CE6: =IFERROR(BW6/F6,0) -> 0.00017123288 | CF6: SI69F | CG6: future | CH6: lease | CI6: long | CJ6: regular | CK6: 1.95 | CL6: 1.985 | CM6: 0.51394093 | CN6: 1 | CO6: 1.0021848 | CP6: 0 | CQ6: 0 | CR6: 0.017987933 | CS6: -0.017987933 | CT6: 1.977 | CU6: 2.017 | CV6: -0.013657056 | CW6: 0.0625 | CX6: 0.28908298 | CY6: 22 | CZ6: =IFERROR(CR6/F6,0) -> 0.017948718 | DA6: Lease cash / margin / financing | DB6: cash | DC6: lease | DD6: cash | DF6: 1 | DG6: 1 | DH6: 0 | DJ6: 0 | DK6: 0 | DL6: 0.017987933 | DM6: 0 | DN6: 0.017987933 | DO6: 1.977 | DP6: 2.017 | DU6: =IFERROR(DM6/F6,0) -> 0 | DV6: Keep cash / margin / financing | DW6: cash | DX6: keep | DY6: cash | EA6: 1 | EB6: 1 | EC6: 0 | EE6: 0 | EF6: 0 | EG6: 0 | EH6: 0 | EI6: 0 | EJ6: 1.977 | EK6: 2.017 | EP6: =IFERROR(EH6/F6,0) -> 0
A7: 25211 | B7: 25212 | C7: =B7-A7 -> 1 | D7: 25211 | E7: positive | F7: 1.0203444 | G7: 0.021328279 | H7: =SUM(CE7,CZ7,DU7,EP7,FK7,GF7,HA7,HV7,IQ7,JL7) -> 0.021328279 | I7: =G7-H7 -> 0 | J7: =F7*(1+H7) -> 1.0421065 | K7: 1.0421065 | L7: =K7-J7 -> 0 | M7: 2.017 | N7: 2.007 | O7: =M7/$M$3 -> 1.0301328 | P7: =N7/$M$3 -> 1.0250255 | Q7: =IFERROR(N7/M7-1,0) -> -0.0049578582 | R7: =SUM(IF(BM7="lease",BU7,0),IF(CH7="lease",CP7,0),IF(DC7="lease",DK7,0),IF(DX7="lease",EF7,0),IF(ES7="lease",FA7,0),IF(FN7="lease",FV7,0),IF(GI7="lease",GQ7,0),IF(HD7="lease",HL7,0),IF(HY7="lease",IG7,0),IF(IT7="lease",JB7,0)) -> 1.0203444 | S7: =SUM(IF(BM7="lease",BV7,0),IF(CH7="lease",CQ7,0),IF(DC7="lease",DL7,0),IF(DX7="lease",EG7,0),IF(ES7="lease",FB7,0),IF(FN7="lease",FW7,0),IF(GI7="lease",GR7,0),IF(HD7="lease",HM7,0),IF(HY7="lease",IH7,0),IF(IT7="lease",JC7,0)) -> 1.0421065 | T7: =SUM(IF(BM7="keep",BU7,0),IF(CH7="keep",CP7,0),IF(DC7="keep",DK7,0),IF(DX7="keep",EF7,0),IF(ES7="keep",FA7,0),IF(FN7="keep",FV7,0),IF(GI7="keep",GQ7,0),IF(HD7="keep",HL7,0),IF(HY7="keep",IG7,0),IF(IT7="keep",JB7,0)) -> 0 | U7: =SUM(IF(BM7="keep",BV7,0),IF(CH7="keep",CQ7,0),IF(DC7="keep",DL7,0),IF(DX7="keep",EG7,0),IF(ES7="keep",FB7,0),IF(FN7="keep",FW7,0),IF(GI7="keep",GR7,0),IF(HD7="keep",HM7,0),IF(HY7="keep",IH7,0),IF(IT7="keep",JC7,0)) -> 0 | V7: =R7/O7 -> 0.99049789 | W7: =S7/P7 -> 1.016664 | X7: =T7/O7 -> 0 | Y7: =U7/P7 -> 0 | Z7: =V7+X7 -> 0.99049789 | AA7: =IFERROR(W7/V7-1,0) -> 0.02641711 | AB7: =IFERROR((W7-V7)/Z7,0) -> 0.02641711 | AC7: =IFERROR(Y7/X7-1,0) -> 0 | AD7: =IFERROR((Y7-X7)/Z7,0) -> 0 | AE7: =AB7+AD7 -> 0.02641711 | AF7: =(1+Q7)*(1+AE7)-1 -> 0.021328279 | AG7: =G7-AF7 -> -3.1571967e-16 | AH7: =SUM(IF(BM7="lease",BW7,0),IF(CH7="lease",CR7,0),IF(DC7="lease",DM7,0),IF(DX7="lease",EH7,0),IF(ES7="lease",FC7,0),IF(FN7="lease",FX7,0),IF(GI7="lease",GS7,0),IF(HD7="lease",HN7,0),IF(HY7="lease",II7,0),IF(IT7="lease",JD7,0)) -> 0.021762189 | AI7: =SUM(IF(BM7="keep",BW7,0),IF(CH7="keep",CR7,0),IF(DC7="keep",DM7,0),IF(DX7="keep",EH7,0),IF(ES7="keep",FC7,0),IF(FN7="keep",FX7,0),IF(GI7="keep",GS7,0),IF(HD7="keep",HN7,0),IF(HY7="keep",II7,0),IF(IT7="keep",JD7,0)) -> 0 | AJ7: =SUM(IF(BM7="lease",BX7,0),IF(CH7="lease",CS7,0),IF(DC7="lease",DN7,0),IF(DX7="lease",EI7,0),IF(ES7="lease",FD7,0),IF(FN7="lease",FY7,0),IF(GI7="lease",GT7,0),IF(HD7="lease",HO7,0),IF(HY7="lease",IJ7,0),IF(IT7="lease",JE7,0)) -> 0 | AK7: =SUM(IF(BM7="keep",BX7,0),IF(CH7="keep",CS7,0),IF(DC7="keep",DN7,0),IF(DX7="keep",EI7,0),IF(ES7="keep",FD7,0),IF(FN7="keep",FY7,0),IF(GI7="keep",GT7,0),IF(HD7="keep",HO7,0),IF(HY7="keep",IJ7,0),IF(IT7="keep",JE7,0)) -> 0 | AL7: =R7-S6 -> 0 | AM7: =T7-U6 -> 0 | AN7: =AN6 -> 1 | AO7: =AO6+AH7 -> 0.042106545 | AP7: =AP6+AL7 -> 0 | AQ7: =AN7+AO7+AP7 -> 1.0421065 | AR7: =S7-AQ7 -> 0 | AS7: =AS6 -> 0 | AT7: =AT6+AI7 -> 0 | AU7: =AU6+AM7 -> 0 | AV7: =AS7+AT7+AU7 -> 0 | AW7: =U7-AV7 -> 0 | AX7: 1.0203444 | AY7: 1.0421065 | AZ7: =S7-AY7 -> 0 | BA7: 0 | BB7: 0 | BC7: =U7-BB7 -> 0 | BD7: =SUM(IF(BL7="direct",CE7,0),IF(CG7="direct",CZ7,0),IF(DB7="direct",DU7,0),IF(DW7="direct",EP7,0),IF(ER7="direct",FK7,0),IF(FM7="direct",GF7,0),IF(GH7="direct",HA7,0),IF(HC7="direct",HV7,0),IF(HX7="direct",IQ7,0),IF(IS7="direct",JL7,0)) -> 0 | BE7: =SUM(IF(BL7="treasury",CE7,0),IF(CG7="treasury",CZ7,0),IF(DB7="treasury",DU7,0),IF(DW7="treasury",EP7,0),IF(ER7="treasury",FK7,0),IF(FM7="treasury",GF7,0),IF(GH7="treasury",HA7,0),IF(HC7="treasury",HV7,0),IF(HX7="treasury",IQ7,0),IF(IS7="treasury",JL7,0)) -> 0.00016958904 | BF7: =SUM(IF(BL7="future",CE7,0),IF(CG7="future",CZ7,0),IF(DB7="future",DU7,0),IF(DW7="future",EP7,0),IF(ER7="future",FK7,0),IF(FM7="future",GF7,0),IF(GH7="future",HA7,0),IF(HC7="future",HV7,0),IF(HX7="future",IQ7,0),IF(IS7="future",JL7,0)) -> 0.02115869 | BG7: =SUM(IF(BL7="cash",CE7,0),IF(CG7="cash",CZ7,0),IF(DB7="cash",DU7,0),IF(DW7="cash",EP7,0),IF(ER7="cash",FK7,0),IF(FM7="cash",GF7,0),IF(GH7="cash",HA7,0),IF(HC7="cash",HV7,0),IF(HX7="cash",IQ7,0),IF(IS7="cash",JL7,0)) -> 0 | BH7: =SUM(BD7:BG7) -> 0.021328279 | BI7: =G7-BH7 -> 0 | BJ7: =COUNTA(BK7,CF7,DA7,DV7,EQ7,FL7,GG7,HB7,HW7,IR7) -> 4 | BK7: Treasury collateral | BL7: treasury | BM7: lease | BN7: long | BP7: 100.10129 | BQ7: 100.11827 | BR7: 0.010193118 | BS7: 1 | BT7: 1.0203444 | BU7: 1.0203444 | BV7: 1.0205174 | BW7: 0.00017303922 | BX7: 2.0841076e-16 | BY7: 2.017 | BZ7: 2.007 | CD7: 21 | CE7: =IFERROR(BW7/F7,0) -> 0.00016958904 | CF7: SI69F | CG7: future | CH7: lease | CI7: long | CJ7: regular | CK7: 1.985 | CL7: 2.027 | CM7: 0.51402738 | CN7: 1 | CO7: 1.0203444 | CP7: 0 | CQ7: 0 | CR7: 0.02158915 | CS7: -0.02158915 | CT7: 2.017 | CU7: 2.007 | CV7: -0.015865146 | CW7: 0.0619 | CX7: 0.33765135 | CY7: 21 | CZ7: =IFERROR(CR7/F7,0) -> 0.02115869 | DA7: Lease cash / margin / financing | DB7: cash | DC7: lease | DD7: cash | DF7: 1 | DG7: 1 | DH7: 0 | DJ7: 0 | DK7: 0 | DL7: 0.02158915 | DM7: 0 | DN7: 0.02158915 | DO7: 2.017 | DP7: 2.007 | DU7: =IFERROR(DM7/F7,0) -> 0 | DV7: Keep cash / margin / financing | DW7: cash | DX7: keep | DY7: cash | EA7: 1 | EB7: 1 | EC7: 0 | EE7: 0 | EF7: 0 | EG7: 0 | EH7: 0 | EI7: 0 | EJ7: 2.017 | EK7: 2.007 | EP7: =IFERROR(EH7/F7,0) -> 0
A8: 25212 | B8: 25213 | C8: =B8-A8 -> 1 | D8: 25212 | E8: neutral | F8: 1.0421065 | G8: 0.017432114 | H8: =SUM(CE8,CZ8,DU8,EP8,FK8,GF8,HA8,HV8,IQ8,JL8) -> 0.017432114 | I8: =G8-H8 -> 0 | J8: =F8*(1+H8) -> 1.0602727 | K8: 1.0602727 | L8: =K8-J8 -> 0 | M8: 2.007 | N8: 2.042 | O8: =M8/$M$3 -> 1.0250255 | P8: =N8/$M$3 -> 1.0429009 | Q8: =IFERROR(N8/M8-1,0) -> 0.017438964 | R8: =SUM(IF(BM8="lease",BU8,0),IF(CH8="lease",CP8,0),IF(DC8="lease",DK8,0),IF(DX8="lease",EF8,0),IF(ES8="lease",FA8,0),IF(FN8="lease",FV8,0),IF(GI8="lease",GQ8,0),IF(HD8="lease",HL8,0),IF(HY8="lease",IG8,0),IF(IT8="lease",JB8,0)) -> 1.0421065 | S8: =SUM(IF(BM8="lease",BV8,0),IF(CH8="lease",CQ8,0),IF(DC8="lease",DL8,0),IF(DX8="lease",EG8,0),IF(ES8="lease",FB8,0),IF(FN8="lease",FW8,0),IF(GI8="lease",GR8,0),IF(HD8="lease",HM8,0),IF(HY8="lease",IH8,0),IF(IT8="lease",JC8,0)) -> 1.0602727 | T8: =SUM(IF(BM8="keep",BU8,0),IF(CH8="keep",CP8,0),IF(DC8="keep",DK8,0),IF(DX8="keep",EF8,0),IF(ES8="keep",FA8,0),IF(FN8="keep",FV8,0),IF(GI8="keep",GQ8,0),IF(HD8="keep",HL8,0),IF(HY8="keep",IG8,0),IF(IT8="keep",JB8,0)) -> 0 | U8: =SUM(IF(BM8="keep",BV8,0),IF(CH8="keep",CQ8,0),IF(DC8="keep",DL8,0),IF(DX8="keep",EG8,0),IF(ES8="keep",FB8,0),IF(FN8="keep",FW8,0),IF(GI8="keep",GR8,0),IF(HD8="keep",HM8,0),IF(HY8="keep",IH8,0),IF(IT8="keep",JC8,0)) -> 0 | V8: =R8/O8 -> 1.016664 | W8: =S8/P8 -> 1.0166571 | X8: =T8/O8 -> 0 | Y8: =U8/P8 -> 0 | Z8: =V8+X8 -> 1.016664 | AA8: =IFERROR(W8/V8-1,0) -> -6.7319174e-06 | AB8: =IFERROR((W8-V8)/Z8,0) -> -6.7319174e-06 | AC8: =IFERROR(Y8/X8-1,0) -> 0 | AD8: =IFERROR((Y8-X8)/Z8,0) -> 0 | AE8: =AB8+AD8 -> -6.7319174e-06 | AF8: =(1+Q8)*(1+AE8)-1 -> 0.017432114 | AG8: =G8-AF8 -> -4.510281e-17 | AH8: =SUM(IF(BM8="lease",BW8,0),IF(CH8="lease",CR8,0),IF(DC8="lease",DM8,0),IF(DX8="lease",EH8,0),IF(ES8="lease",FC8,0),IF(FN8="lease",FX8,0),IF(GI8="lease",GS8,0),IF(HD8="lease",HN8,0),IF(HY8="lease",II8,0),IF(IT8="lease",JD8,0)) -> 0.01816612 | AI8: =SUM(IF(BM8="keep",BW8,0),IF(CH8="keep",CR8,0),IF(DC8="keep",DM8,0),IF(DX8="keep",EH8,0),IF(ES8="keep",FC8,0),IF(FN8="keep",FX8,0),IF(GI8="keep",GS8,0),IF(HD8="keep",HN8,0),IF(HY8="keep",II8,0),IF(IT8="keep",JD8,0)) -> 0 | AJ8: =SUM(IF(BM8="lease",BX8,0),IF(CH8="lease",CS8,0),IF(DC8="lease",DN8,0),IF(DX8="lease",EI8,0),IF(ES8="lease",FD8,0),IF(FN8="lease",FY8,0),IF(GI8="lease",GT8,0),IF(HD8="lease",HO8,0),IF(HY8="lease",IJ8,0),IF(IT8="lease",JE8,0)) -> 0 | AK8: =SUM(IF(BM8="keep",BX8,0),IF(CH8="keep",CS8,0),IF(DC8="keep",DN8,0),IF(DX8="keep",EI8,0),IF(ES8="keep",FD8,0),IF(FN8="keep",FY8,0),IF(GI8="keep",GT8,0),IF(HD8="keep",HO8,0),IF(HY8="keep",IJ8,0),IF(IT8="keep",JE8,0)) -> 0 | AL8: =R8-S7 -> 0 | AM8: =T8-U7 -> 0 | AN8: =AN7 -> 1 | AO8: =AO7+AH8 -> 0.060272665 | AP8: =AP7+AL8 -> 0 | AQ8: =AN8+AO8+AP8 -> 1.0602727 | AR8: =S8-AQ8 -> 0 | AS8: =AS7 -> 0 | AT8: =AT7+AI8 -> 0 | AU8: =AU7+AM8 -> 0 | AV8: =AS8+AT8+AU8 -> 0 | AW8: =U8-AV8 -> 0 | AX8: 1.0421065 | AY8: 1.0602727 | AZ8: =S8-AY8 -> 0 | BA8: 0 | BB8: 0 | BC8: =U8-BB8 -> 0 | BD8: =SUM(IF(BL8="direct",CE8,0),IF(CG8="direct",CZ8,0),IF(DB8="direct",DU8,0),IF(DW8="direct",EP8,0),IF(ER8="direct",FK8,0),IF(FM8="direct",GF8,0),IF(GH8="direct",HA8,0),IF(HC8="direct",HV8,0),IF(HX8="direct",IQ8,0),IF(IS8="direct",JL8,0)) -> 0.017432114 | BE8: =SUM(IF(BL8="treasury",CE8,0),IF(CG8="treasury",CZ8,0),IF(DB8="treasury",DU8,0),IF(DW8="treasury",EP8,0),IF(ER8="treasury",FK8,0),IF(FM8="treasury",GF8,0),IF(GH8="treasury",HA8,0),IF(HC8="treasury",HV8,0),IF(HX8="treasury",IQ8,0),IF(IS8="treasury",JL8,0)) -> 0 | BF8: =SUM(IF(BL8="future",CE8,0),IF(CG8="future",CZ8,0),IF(DB8="future",DU8,0),IF(DW8="future",EP8,0),IF(ER8="future",FK8,0),IF(FM8="future",GF8,0),IF(GH8="future",HA8,0),IF(HC8="future",HV8,0),IF(HX8="future",IQ8,0),IF(IS8="future",JL8,0)) -> 0 | BG8: =SUM(IF(BL8="cash",CE8,0),IF(CG8="cash",CZ8,0),IF(DB8="cash",DU8,0),IF(DW8="cash",EP8,0),IF(ER8="cash",FK8,0),IF(FM8="cash",GF8,0),IF(GH8="cash",HA8,0),IF(HC8="cash",HV8,0),IF(HX8="cash",IQ8,0),IF(IS8="cash",JL8,0)) -> 0 | BH8: =SUM(BD8:BG8) -> 0.017432114 | BI8: =G8-BH8 -> 0 | BJ8: =COUNTA(BK8,CF8,DA8,DV8,EQ8,FL8,GG8,HB8,HW8,IR8) -> 3 | BK8: Direct commodity holding | BL8: direct | BM8: lease | BN8: long | BP8: 2.007 | BQ8: 2.042 | BR8: 0.51923595 | BS8: 1 | BT8: 1.0421065 | BU8: 1.0421065 | BV8: 1.0602798 | BW8: 0.01816612 | BX8: 7.1377161e-06 | BY8: 2.007 | BZ8: 2.042 | CE8: =IFERROR(BW8/F8,0) -> 0.017432114 | CF8: Lease cash / margin / financing | CG8: cash | CH8: lease | CI8: cash | CK8: 1 | CL8: 1 | CM8: 0 | CO8: 0 | CP8: 0 | CQ8: -7.1377161e-06 | CR8: 0 | CS8: -7.1377161e-06 | CT8: 2.007 | CU8: 2.042 | CZ8: =IFERROR(CR8/F8,0) -> 0 | DA8: Keep cash / margin / financing | DB8: cash | DC8: keep | DD8: cash | DF8: 1 | DG8: 1 | DH8: 0 | DJ8: 0 | DK8: 0 | DL8: 0 | DM8: 0 | DN8: 0 | DO8: 2.007 | DP8: 2.042 | DU8: =IFERROR(DM8/F8,0) -> 0
A9: 25213 | B9: 25216 | C9: =B9-A9 -> 3 | D9: 25213 | E9: positive | F9: 1.0602727 | G9: -0.0019978082 | H9: =SUM(CE9,CZ9,DU9,EP9,FK9,GF9,HA9,HV9,IQ9,JL9) -> -0.0019978082 | I9: =G9-H9 -> -4.3368087e-19 | J9: =F9*(1+H9) -> 1.0581544 | K9: 1.0581544 | L9: =K9-J9 -> 0 | M9: 2.042 | N9: 2.016 | O9: =M9/$M$3 -> 1.0429009 | P9: =N9/$M$3 -> 1.0296221 | Q9: =IFERROR(N9/M9-1,0) -> -0.012732615 | R9: =SUM(IF(BM9="lease",BU9,0),IF(CH9="lease",CP9,0),IF(DC9="lease",DK9,0),IF(DX9="lease",EF9,0),IF(ES9="lease",FA9,0),IF(FN9="lease",FV9,0),IF(GI9="lease",GQ9,0),IF(HD9="lease",HL9,0),IF(HY9="lease",IG9,0),IF(IT9="lease",JB9,0)) -> 1.0602727 | S9: =SUM(IF(BM9="lease",BV9,0),IF(CH9="lease",CQ9,0),IF(DC9="lease",DL9,0),IF(DX9="lease",EG9,0),IF(ES9="lease",FB9,0),IF(FN9="lease",FW9,0),IF(GI9="lease",GR9,0),IF(HD9="lease",HM9,0),IF(HY9="lease",IH9,0),IF(IT9="lease",JC9,0)) -> 1.0581544 | T9: =SUM(IF(BM9="keep",BU9,0),IF(CH9="keep",CP9,0),IF(DC9="keep",DK9,0),IF(DX9="keep",EF9,0),IF(ES9="keep",FA9,0),IF(FN9="keep",FV9,0),IF(GI9="keep",GQ9,0),IF(HD9="keep",HL9,0),IF(HY9="keep",IG9,0),IF(IT9="keep",JB9,0)) -> 0 | U9: =SUM(IF(BM9="keep",BV9,0),IF(CH9="keep",CQ9,0),IF(DC9="keep",DL9,0),IF(DX9="keep",EG9,0),IF(ES9="keep",FB9,0),IF(FN9="keep",FW9,0),IF(GI9="keep",GR9,0),IF(HD9="keep",HM9,0),IF(HY9="keep",IH9,0),IF(IT9="keep",JC9,0)) -> 0 | V9: =R9/O9 -> 1.0166571 | W9: =S9/P9 -> 1.0277115 | X9: =T9/O9 -> 0 | Y9: =U9/P9 -> 0 | Z9: =V9+X9 -> 1.0166571 | AA9: =IFERROR(W9/V9-1,0) -> 0.010873252 | AB9: =IFERROR((W9-V9)/Z9,0) -> 0.010873252 | AC9: =IFERROR(Y9/X9-1,0) -> 0 | AD9: =IFERROR((Y9-X9)/Z9,0) -> 0 | AE9: =AB9+AD9 -> 0.010873252 | AF9: =(1+Q9)*(1+AE9)-1 -> -0.0019978082 | AG9: =G9-AF9 -> -8.5435131e-17 | AH9: =SUM(IF(BM9="lease",BW9,0),IF(CH9="lease",CR9,0),IF(DC9="lease",DM9,0),IF(DX9="lease",EH9,0),IF(ES9="lease",FC9,0),IF(FN9="lease",FX9,0),IF(GI9="lease",GS9,0),IF(HD9="lease",HN9,0),IF(HY9="lease",II9,0),IF(IT9="lease",JD9,0)) -> -0.0021182214 | AI9: =SUM(IF(BM9="keep",BW9,0),IF(CH9="keep",CR9,0),IF(DC9="keep",DM9,0),IF(DX9="keep",EH9,0),IF(ES9="keep",FC9,0),IF(FN9="keep",FX9,0),IF(GI9="keep",GS9,0),IF(HD9="keep",HN9,0),IF(HY9="keep",II9,0),IF(IT9="keep",JD9,0)) -> 0 | AJ9: =SUM(IF(BM9="lease",BX9,0),IF(CH9="lease",CS9,0),IF(DC9="lease",DN9,0),IF(DX9="lease",EI9,0),IF(ES9="lease",FD9,0),IF(FN9="lease",FY9,0),IF(GI9="lease",GT9,0),IF(HD9="lease",HO9,0),IF(HY9="lease",IJ9,0),IF(IT9="lease",JE9,0)) -> 0 | AK9: =SUM(IF(BM9="keep",BX9,0),IF(CH9="keep",CS9,0),IF(DC9="keep",DN9,0),IF(DX9="keep",EI9,0),IF(ES9="keep",FD9,0),IF(FN9="keep",FY9,0),IF(GI9="keep",GT9,0),IF(HD9="keep",HO9,0),IF(HY9="keep",IJ9,0),IF(IT9="keep",JE9,0)) -> 0 | AL9: =R9-S8 -> 0 | AM9: =T9-U8 -> 0 | AN9: =AN8 -> 1 | AO9: =AO8+AH9 -> 0.058154444 | AP9: =AP8+AL9 -> 0 | AQ9: =AN9+AO9+AP9 -> 1.0581544 | AR9: =S9-AQ9 -> 0 | AS9: =AS8 -> 0 | AT9: =AT8+AI9 -> 0 | AU9: =AU8+AM9 -> 0 | AV9: =AS9+AT9+AU9 -> 0 | AW9: =U9-AV9 -> 0 | AX9: 1.0602727 | AY9: 1.0581544 | AZ9: =S9-AY9 -> 0 | BA9: 0 | BB9: 0 | BC9: =U9-BB9 -> 0 | BD9: =SUM(IF(BL9="direct",CE9,0),IF(CG9="direct",CZ9,0),IF(DB9="direct",DU9,0),IF(DW9="direct",EP9,0),IF(ER9="direct",FK9,0),IF(FM9="direct",GF9,0),IF(GH9="direct",HA9,0),IF(HC9="direct",HV9,0),IF(HX9="direct",IQ9,0),IF(IS9="direct",JL9,0)) -> 0 | BE9: =SUM(IF(BL9="treasury",CE9,0),IF(CG9="treasury",CZ9,0),IF(DB9="treasury",DU9,0),IF(DW9="treasury",EP9,0),IF(ER9="treasury",FK9,0),IF(FM9="treasury",GF9,0),IF(GH9="treasury",HA9,0),IF(HC9="treasury",HV9,0),IF(HX9="treasury",IQ9,0),IF(IS9="treasury",JL9,0)) -> 0.00050219178 | BF9: =SUM(IF(BL9="future",CE9,0),IF(CG9="future",CZ9,0),IF(DB9="future",DU9,0),IF(DW9="future",EP9,0),IF(ER9="future",FK9,0),IF(FM9="future",GF9,0),IF(GH9="future",HA9,0),IF(HC9="future",HV9,0),IF(HX9="future",IQ9,0),IF(IS9="future",JL9,0)) -> -0.0025 | BG9: =SUM(IF(BL9="cash",CE9,0),IF(CG9="cash",CZ9,0),IF(DB9="cash",DU9,0),IF(DW9="cash",EP9,0),IF(ER9="cash",FK9,0),IF(FM9="cash",GF9,0),IF(GH9="cash",HA9,0),IF(HC9="cash",HV9,0),IF(HX9="cash",IQ9,0),IF(IS9="cash",JL9,0)) -> 0 | BH9: =SUM(BD9:BG9) -> -0.0019978082 | BI9: =G9-BH9 -> -4.3368087e-19 | BJ9: =COUNTA(BK9,CF9,DA9,DV9,EQ9,FL9,GG9,HB9,HW9,IR9) -> 4 | BK9: Treasury collateral | BL9: treasury | BM9: lease | BN9: long | BP9: 100.13514 | BQ9: 100.18543 | BR9: 0.010588417 | BS9: 1 | BT9: 1.0602727 | BU9: 1.0602727 | BV9: 1.0608051 | BW9: 0.00053246022 | BX9: 1.4419889e-17 | BY9: 2.042 | BZ9: 2.016 | CD9: 19 | CE9: =IFERROR(BW9/F9,0) -> 0.00050219178 | CF9: SI69F | CG9: future | CH9: lease | CI9: long | CJ9: regular | CK9: 2 | CL9: 1.995 | CM9: 0.53013633 | CN9: 1 | CO9: 1.0602727 | CP9: 0 | CQ9: 0 | CR9: -0.0026506817 | CS9: 0.0026506817 | CT9: 2.042 | CU9: 2.016 | CV9: -0.020568071 | CW9: 0.0611 | CX9: 0.45622346 | CY9: 19 | CZ9: =IFERROR(CR9/F9,0) -> -0.0025 | DA9: Lease cash / margin / financing | DB9: cash | DC9: lease | DD9: cash | DF9: 1 | DG9: 1 | DH9: 0 | DJ9: 0 | DK9: 0 | DL9: -0.0026506817 | DM9: 0 | DN9: -0.0026506817 | DO9: 2.042 | DP9: 2.016 | DU9: =IFERROR(DM9/F9,0) -> 0 | DV9: Keep cash / margin / financing | DW9: cash | DX9: keep | DY9: cash | EA9: 1 | EB9: 1 | EC9: 0 | EE9: 0 | EF9: 0 | EG9: 0 | EH9: 0 | EI9: 0 | EJ9: 2.042 | EK9: 2.016 | EP9: =IFERROR(EH9/F9,0) -> 0
A10: 25216 | B10: 25217 | C10: =B10-A10 -> 1 | D10: 25216 | E10: positive | F10: 1.0581544 | G10: 0.0086892485 | H10: =SUM(CE10,CZ10,DU10,EP10,FK10,GF10,HA10,HV10,IQ10,JL10) -> 0.0086892485 | I10: =G10-H10 -> 1.7347235e-18 | J10: =F10*(1+H10) -> 1.067349 | K10: 1.067349 | L10: =K10-J10 -> 0 | M10: 2.016 | N10: 2.027 | O10: =M10/$M$3 -> 1.0296221 | P10: =N10/$M$3 -> 1.03524 | Q10: =IFERROR(N10/M10-1,0) -> 0.0054563492 | R10: =SUM(IF(BM10="lease",BU10,0),IF(CH10="lease",CP10,0),IF(DC10="lease",DK10,0),IF(DX10="lease",EF10,0),IF(ES10="lease",FA10,0),IF(FN10="lease",FV10,0),IF(GI10="lease",GQ10,0),IF(HD10="lease",HL10,0),IF(HY10="lease",IG10,0),IF(IT10="lease",JB10,0)) -> 1.0581544 | S10: =SUM(IF(BM10="lease",BV10,0),IF(CH10="lease",CQ10,0),IF(DC10="lease",DL10,0),IF(DX10="lease",EG10,0),IF(ES10="lease",FB10,0),IF(FN10="lease",FW10,0),IF(GI10="lease",GR10,0),IF(HD10="lease",HM10,0),IF(HY10="lease",IH10,0),IF(IT10="lease",JC10,0)) -> 1.067349 | T10: =SUM(IF(BM10="keep",BU10,0),IF(CH10="keep",CP10,0),IF(DC10="keep",DK10,0),IF(DX10="keep",EF10,0),IF(ES10="keep",FA10,0),IF(FN10="keep",FV10,0),IF(GI10="keep",GQ10,0),IF(HD10="keep",HL10,0),IF(HY10="keep",IG10,0),IF(IT10="keep",JB10,0)) -> 0 | U10: =SUM(IF(BM10="keep",BV10,0),IF(CH10="keep",CQ10,0),IF(DC10="keep",DL10,0),IF(DX10="keep",EG10,0),IF(ES10="keep",FB10,0),IF(FN10="keep",FW10,0),IF(GI10="keep",GR10,0),IF(HD10="keep",HM10,0),IF(HY10="keep",IH10,0),IF(IT10="keep",JC10,0)) -> 0 | V10: =R10/O10 -> 1.0277115 | W10: =S10/P10 -> 1.031016 | X10: =T10/O10 -> 0 | Y10: =U10/P10 -> 0 | Z10: =V10+X10 -> 1.0277115 | AA10: =IFERROR(W10/V10-1,0) -> 0.0032153552 | AB10: =IFERROR((W10-V10)/Z10,0) -> 0.0032153552 | AC10: =IFERROR(Y10/X10-1,0) -> 0 | AD10: =IFERROR((Y10-X10)/Z10,0) -> 0 | AE10: =AB10+AD10 -> 0.0032153552 | AF10: =(1+Q10)*(1+AE10)-1 -> 0.0086892485 | AG10: =G10-AF10 -> 2.0469737e-16 | AH10: =SUM(IF(BM10="lease",BW10,0),IF(CH10="lease",CR10,0),IF(DC10="lease",DM10,0),IF(DX10="lease",EH10,0),IF(ES10="lease",FC10,0),IF(FN10="lease",FX10,0),IF(GI10="lease",GS10,0),IF(HD10="lease",HN10,0),IF(HY10="lease",II10,0),IF(IT10="lease",JD10,0)) -> 0.0091945669 | AI10: =SUM(IF(BM10="keep",BW10,0),IF(CH10="keep",CR10,0),IF(DC10="keep",DM10,0),IF(DX10="keep",EH10,0),IF(ES10="keep",FC10,0),IF(FN10="keep",FX10,0),IF(GI10="keep",GS10,0),IF(HD10="keep",HN10,0),IF(HY10="keep",II10,0),IF(IT10="keep",JD10,0)) -> 0 | AJ10: =SUM(IF(BM10="lease",BX10,0),IF(CH10="lease",CS10,0),IF(DC10="lease",DN10,0),IF(DX10="lease",EI10,0),IF(ES10="lease",FD10,0),IF(FN10="lease",FY10,0),IF(GI10="lease",GT10,0),IF(HD10="lease",HO10,0),IF(HY10="lease",IJ10,0),IF(IT10="lease",JE10,0)) -> 0 | AK10: =SUM(IF(BM10="keep",BX10,0),IF(CH10="keep",CS10,0),IF(DC10="keep",DN10,0),IF(DX10="keep",EI10,0),IF(ES10="keep",FD10,0),IF(FN10="keep",FY10,0),IF(GI10="keep",GT10,0),IF(HD10="keep",HO10,0),IF(HY10="keep",IJ10,0),IF(IT10="keep",JE10,0)) -> 0 | AL10: =R10-S9 -> 0 | AM10: =T10-U9 -> 0 | AN10: =AN9 -> 1 | AO10: =AO9+AH10 -> 0.06734901 | AP10: =AP9+AL10 -> 0 | AQ10: =AN10+AO10+AP10 -> 1.067349 | AR10: =S10-AQ10 -> 0 | AS10: =AS9 -> 0 | AT10: =AT9+AI10 -> 0 | AU10: =AU9+AM10 -> 0 | AV10: =AS10+AT10+AU10 -> 0 | AW10: =U10-AV10 -> 0 | AX10: 1.0581544 | AY10: 1.067349 | AZ10: =S10-AY10 -> 0 | BA10: 0 | BB10: 0 | BC10: =U10-BB10 -> 0 | BD10: =SUM(IF(BL10="direct",CE10,0),IF(CG10="direct",CZ10,0),IF(DB10="direct",DU10,0),IF(DW10="direct",EP10,0),IF(ER10="direct",FK10,0),IF(FM10="direct",GF10,0),IF(GH10="direct",HA10,0),IF(HC10="direct",HV10,0),IF(HX10="direct",IQ10,0),IF(IS10="direct",JL10,0)) -> 0 | BE10: =SUM(IF(BL10="treasury",CE10,0),IF(CG10="treasury",CZ10,0),IF(DB10="treasury",DU10,0),IF(DW10="treasury",EP10,0),IF(ER10="treasury",FK10,0),IF(FM10="treasury",GF10,0),IF(GH10="treasury",HA10,0),IF(HC10="treasury",HV10,0),IF(HX10="treasury",IQ10,0),IF(IS10="treasury",JL10,0)) -> 0.00016794521 | BF10: =SUM(IF(BL10="future",CE10,0),IF(CG10="future",CZ10,0),IF(DB10="future",DU10,0),IF(DW10="future",EP10,0),IF(ER10="future",FK10,0),IF(FM10="future",GF10,0),IF(GH10="future",HA10,0),IF(HC10="future",HV10,0),IF(HX10="future",IQ10,0),IF(IS10="future",JL10,0)) -> 0.0085213033 | BG10: =SUM(IF(BL10="cash",CE10,0),IF(CG10="cash",CZ10,0),IF(DB10="cash",DU10,0),IF(DW10="cash",EP10,0),IF(ER10="cash",FK10,0),IF(FM10="cash",GF10,0),IF(GH10="cash",HA10,0),IF(HC10="cash",HV10,0),IF(HX10="cash",IQ10,0),IF(IS10="cash",JL10,0)) -> 0 | BH10: =SUM(BD10:BG10) -> 0.0086892485 | BI10: =G10-BH10 -> 1.7347235e-18 | BJ10: =COUNTA(BK10,CF10,DA10,DV10,EQ10,FL10,GG10,HB10,HW10,IR10) -> 4 | BK10: Treasury collateral | BL10: treasury | BM10: lease | BN10: long | BP10: 100.18543 | BQ10: 100.20225 | BR10: 0.01056196 | BS10: 1 | BT10: 1.0581544 | BU10: 1.0581544 | BV10: 1.0583322 | BW10: 0.00017771197 | BX10: -9.2645076e-17 | BY10: 2.016 | BZ10: 2.027 | CD10: 16 | CE10: =IFERROR(BW10/F10,0) -> 0.00016794521 | CF10: SI69F | CG10: future | CH10: lease | CI10: long | CJ10: regular | CK10: 1.995 | CL10: 2.012 | CM10: 0.53040323 | CN10: 1 | CO10: 1.0581544 | CP10: 0 | CQ10: 0 | CR10: 0.0090168549 | CS10: -0.0090168549 | CT10: 2.016 | CU10: 2.027 | CV10: -0.010416667 | CW10: 0.0613 | CX10: 0.29893021 | CY10: 16 | CZ10: =IFERROR(CR10/F10,0) -> 0.0085213033 | DA10: Lease cash / margin / financing | DB10: cash | DC10: lease | DD10: cash | DF10: 1 | DG10: 1 | DH10: 0 | DJ10: 0 | DK10: 0 | DL10: 0.0090168549 | DM10: 0 | DN10: 0.0090168549 | DO10: 2.016 | DP10: 2.027 | DU10: =IFERROR(DM10/F10,0) -> 0 | DV10: Keep cash / margin / financing | DW10: cash | DX10: keep | DY10: cash | EA10: 1 | EB10: 1 | EC10: 0 | EE10: 0 | EF10: 0 | EG10: 0 | EH10: 0 | EI10: 0 | EJ10: 2.016 | EK10: 2.027 | EP10: =IFERROR(EH10/F10,0) -> 0
A11: 25217 | B11: 25218 | C11: =B11-A11 -> 1 | D11: 25217 | E11: positive | F11: 1.067349 | G11: -0.0028127923 | H11: =SUM(CE11,CZ11,DU11,EP11,FK11,GF11,HA11,HV11,IQ11,JL11) -> -0.0028127923 | I11: =G11-H11 -> -4.3368087e-19 | J11: =F11*(1+H11) -> 1.0643468 | K11: 1.0643468 | L11: =K11-J11 -> 0 | M11: 2.027 | N11: 2.038 | O11: =M11/$M$3 -> 1.03524 | P11: =N11/$M$3 -> 1.040858 | Q11: =IFERROR(N11/M11-1,0) -> 0.005426739 | R11: =SUM(IF(BM11="lease",BU11,0),IF(CH11="lease",CP11,0),IF(DC11="lease",DK11,0),IF(DX11="lease",EF11,0),IF(ES11="lease",FA11,0),IF(FN11="lease",FV11,0),IF(GI11="lease",GQ11,0),IF(HD11="lease",HL11,0),IF(HY11="lease",IG11,0),IF(IT11="lease",JB11,0)) -> 1.067349 | S11: =SUM(IF(BM11="lease",BV11,0),IF(CH11="lease",CQ11,0),IF(DC11="lease",DL11,0),IF(DX11="lease",EG11,0),IF(ES11="lease",FB11,0),IF(FN11="lease",FW11,0),IF(GI11="lease",GR11,0),IF(HD11="lease",HM11,0),IF(HY11="lease",IH11,0),IF(IT11="lease",JC11,0)) -> 1.0643468 | T11: =SUM(IF(BM11="keep",BU11,0),IF(CH11="keep",CP11,0),IF(DC11="keep",DK11,0),IF(DX11="keep",EF11,0),IF(ES11="keep",FA11,0),IF(FN11="keep",FV11,0),IF(GI11="keep",GQ11,0),IF(HD11="keep",HL11,0),IF(HY11="keep",IG11,0),IF(IT11="keep",JB11,0)) -> 0 | U11: =SUM(IF(BM11="keep",BV11,0),IF(CH11="keep",CQ11,0),IF(DC11="keep",DL11,0),IF(DX11="keep",EG11,0),IF(ES11="keep",FB11,0),IF(FN11="keep",FW11,0),IF(GI11="keep",GR11,0),IF(HD11="keep",HM11,0),IF(HY11="keep",IH11,0),IF(IT11="keep",JC11,0)) -> 0 | V11: =R11/O11 -> 1.031016 | W11: =S11/P11 -> 1.0225667 | X11: =T11/O11 -> 0 | Y11: =U11/P11 -> 0 | Z11: =V11+X11 -> 1.031016 | AA11: =IFERROR(W11/V11-1,0) -> -0.0081950589 | AB11: =IFERROR((W11-V11)/Z11,0) -> -0.0081950589 | AC11: =IFERROR(Y11/X11-1,0) -> 0 | AD11: =IFERROR((Y11-X11)/Z11,0) -> 0 | AE11: =AB11+AD11 -> -0.0081950589 | AF11: =(1+Q11)*(1+AE11)-1 -> -0.0028127923 | AG11: =G11-AF11 -> 1.0278237e-16 | AH11: =SUM(IF(BM11="lease",BW11,0),IF(CH11="lease",CR11,0),IF(DC11="lease",DM11,0),IF(DX11="lease",EH11,0),IF(ES11="lease",FC11,0),IF(FN11="lease",FX11,0),IF(GI11="lease",GS11,0),IF(HD11="lease",HN11,0),IF(HY11="lease",II11,0),IF(IT11="lease",JD11,0)) -> -0.0030022311 | AI11: =SUM(IF(BM11="keep",BW11,0),IF(CH11="keep",CR11,0),IF(DC11="keep",DM11,0),IF(DX11="keep",EH11,0),IF(ES11="keep",FC11,0),IF(FN11="keep",FX11,0),IF(GI11="keep",GS11,0),IF(HD11="keep",HN11,0),IF(HY11="keep",II11,0),IF(IT11="keep",JD11,0)) -> 0 | AJ11: =SUM(IF(BM11="lease",BX11,0),IF(CH11="lease",CS11,0),IF(DC11="lease",DN11,0),IF(DX11="lease",EI11,0),IF(ES11="lease",FD11,0),IF(FN11="lease",FY11,0),IF(GI11="lease",GT11,0),IF(HD11="lease",HO11,0),IF(HY11="lease",IJ11,0),IF(IT11="lease",JE11,0)) -> 0 | AK11: =SUM(IF(BM11="keep",BX11,0),IF(CH11="keep",CS11,0),IF(DC11="keep",DN11,0),IF(DX11="keep",EI11,0),IF(ES11="keep",FD11,0),IF(FN11="keep",FY11,0),IF(GI11="keep",GT11,0),IF(HD11="keep",HO11,0),IF(HY11="keep",IJ11,0),IF(IT11="keep",JE11,0)) -> 0 | AL11: =R11-S10 -> 0 | AM11: =T11-U10 -> 0 | AN11: =AN10 -> 1 | AO11: =AO10+AH11 -> 0.064346779 | AP11: =AP10+AL11 -> 0 | AQ11: =AN11+AO11+AP11 -> 1.0643468 | AR11: =S11-AQ11 -> 0 | AS11: =AS10 -> 0 | AT11: =AT10+AI11 -> 0 | AU11: =AU10+AM11 -> 0 | AV11: =AS11+AT11+AU11 -> 0 | AW11: =U11-AV11 -> 0 | AX11: 1.067349 | AY11: 1.0643468 | AZ11: =S11-AY11 -> 0 | BA11: 0 | BB11: 0 | BC11: =U11-BB11 -> 0 | BD11: =SUM(IF(BL11="direct",CE11,0),IF(CG11="direct",CZ11,0),IF(DB11="direct",DU11,0),IF(DW11="direct",EP11,0),IF(ER11="direct",FK11,0),IF(FM11="direct",GF11,0),IF(GH11="direct",HA11,0),IF(HC11="direct",HV11,0),IF(HX11="direct",IQ11,0),IF(IS11="direct",JL11,0)) -> 0 | BE11: =SUM(IF(BL11="treasury",CE11,0),IF(CG11="treasury",CZ11,0),IF(DB11="treasury",DU11,0),IF(DW11="treasury",EP11,0),IF(ER11="treasury",FK11,0),IF(FM11="treasury",GF11,0),IF(GH11="treasury",HA11,0),IF(HC11="treasury",HV11,0),IF(HX11="treasury",IQ11,0),IF(IS11="treasury",JL11,0)) -> 0.00016931507 | BF11: =SUM(IF(BL11="future",CE11,0),IF(CG11="future",CZ11,0),IF(DB11="future",DU11,0),IF(DW11="future",EP11,0),IF(ER11="future",FK11,0),IF(FM11="future",GF11,0),IF(GH11="future",HA11,0),IF(HC11="future",HV11,0),IF(HX11="future",IQ11,0),IF(IS11="future",JL11,0)) -> -0.0029821074 | BG11: =SUM(IF(BL11="cash",CE11,0),IF(CG11="cash",CZ11,0),IF(DB11="cash",DU11,0),IF(DW11="cash",EP11,0),IF(ER11="cash",FK11,0),IF(FM11="cash",GF11,0),IF(GH11="cash",HA11,0),IF(HC11="cash",HV11,0),IF(HX11="cash",IQ11,0),IF(IS11="cash",JL11,0)) -> 0 | BH11: =SUM(BD11:BG11) -> -0.0028127923 | BI11: =G11-BH11 -> -4.3368087e-19 | BJ11: =COUNTA(BK11,CF11,DA11,DV11,EQ11,FL11,GG11,HB11,HW11,IR11) -> 4 | BK11: Treasury collateral | BL11: treasury | BM11: lease | BN11: long | BP11: 100.20225 | BQ11: 100.21922 | BR11: 0.010651946 | BS11: 1 | BT11: 1.067349 | BU11: 1.067349 | BV11: 1.0675297 | BW11: 0.00018071827 | BX11: -2.4015078e-17 | BY11: 2.027 | BZ11: 2.038 | CD11: 15 | CE11: =IFERROR(BW11/F11,0) -> 0.00016931507 | CF11: SI69F | CG11: future | CH11: lease | CI11: long | CJ11: regular | CK11: 2.012 | CL11: 2.006 | CM11: 0.53049156 | CN11: 1 | CO11: 1.067349 | CP11: 0 | CQ11: 0 | CR11: -0.0031829493 | CS11: 0.0031829493 | CT11: 2.027 | CU11: 2.038 | CV11: -0.0074000987 | CW11: 0.0618 | CX11: 0.24186907 | CY11: 15 | CZ11: =IFERROR(CR11/F11,0) -> -0.0029821074 | DA11: Lease cash / margin / financing | DB11: cash | DC11: lease | DD11: cash | DF11: 1 | DG11: 1 | DH11: 0 | DJ11: 0 | DK11: 0 | DL11: -0.0031829493 | DM11: 0 | DN11: -0.0031829493 | DO11: 2.027 | DP11: 2.038 | DU11: =IFERROR(DM11/F11,0) -> 0 | DV11: Keep cash / margin / financing | DW11: cash | DX11: keep | DY11: cash | EA11: 1 | EB11: 1 | EC11: 0 | EE11: 0 | EF11: 0 | EG11: 0 | EH11: 0 | EI11: 0 | EJ11: 2.027 | EK11: 2.038 | EP11: =IFERROR(EH11/F11,0) -> 0
A12: 25218 | B12: 25219 | C12: =B12-A12 -> 1 | D12: 25218 | E12: positive | F12: 1.0643468 | G12: -0.018775225 | H12: =SUM(CE12,CZ12,DU12,EP12,FK12,GF12,HA12,HV12,IQ12,JL12) -> -0.018775225 | I12: =G12-H12 -> 0 | J12: =F12*(1+H12) -> 1.0443634 | K12: 1.0443634 | L12: =K12-J12 -> 0 | M12: 2.038 | N12: 2.017 | O12: =M12/$M$3 -> 1.040858 | P12: =N12/$M$3 -> 1.0301328 | Q12: =IFERROR(N12/M12-1,0) -> -0.01030422 | R12: =SUM(IF(BM12="lease",BU12,0),IF(CH12="lease",CP12,0),IF(DC12="lease",DK12,0),IF(DX12="lease",EF12,0),IF(ES12="lease",FA12,0),IF(FN12="lease",FV12,0),IF(GI12="lease",GQ12,0),IF(HD12="lease",HL12,0),IF(HY12="lease",IG12,0),IF(IT12="lease",JB12,0)) -> 1.0643468 | S12: =SUM(IF(BM12="lease",BV12,0),IF(CH12="lease",CQ12,0),IF(DC12="lease",DL12,0),IF(DX12="lease",EG12,0),IF(ES12="lease",FB12,0),IF(FN12="lease",FW12,0),IF(GI12="lease",GR12,0),IF(HD12="lease",HM12,0),IF(HY12="lease",IH12,0),IF(IT12="lease",JC12,0)) -> 1.0443634 | T12: =SUM(IF(BM12="keep",BU12,0),IF(CH12="keep",CP12,0),IF(DC12="keep",DK12,0),IF(DX12="keep",EF12,0),IF(ES12="keep",FA12,0),IF(FN12="keep",FV12,0),IF(GI12="keep",GQ12,0),IF(HD12="keep",HL12,0),IF(HY12="keep",IG12,0),IF(IT12="keep",JB12,0)) -> 0 | U12: =SUM(IF(BM12="keep",BV12,0),IF(CH12="keep",CQ12,0),IF(DC12="keep",DL12,0),IF(DX12="keep",EG12,0),IF(ES12="keep",FB12,0),IF(FN12="keep",FW12,0),IF(GI12="keep",GR12,0),IF(HD12="keep",HM12,0),IF(HY12="keep",IH12,0),IF(IT12="keep",JC12,0)) -> 0 | V12: =R12/O12 -> 1.0225667 | W12: =S12/P12 -> 1.0138144 | X12: =T12/O12 -> 0 | Y12: =U12/P12 -> 0 | Z12: =V12+X12 -> 1.0225667 | AA12: =IFERROR(W12/V12-1,0) -> -0.0085592014 | AB12: =IFERROR((W12-V12)/Z12,0) -> -0.0085592014 | AC12: =IFERROR(Y12/X12-1,0) -> 0 | AD12: =IFERROR((Y12-X12)/Z12,0) -> 0 | AE12: =AB12+AD12 -> -0.0085592014 | AF12: =(1+Q12)*(1+AE12)-1 -> -0.018775225 | AG12: =G12-AF12 -> 9.3675068e-17 | AH12: =SUM(IF(BM12="lease",BW12,0),IF(CH12="lease",CR12,0),IF(DC12="lease",DM12,0),IF(DX12="lease",EH12,0),IF(ES12="lease",FC12,0),IF(FN12="lease",FX12,0),IF(GI12="lease",GS12,0),IF(HD12="lease",HN12,0),IF(HY12="lease",II12,0),IF(IT12="lease",JD12,0)) -> -0.019983351 | AI12: =SUM(IF(BM12="keep",BW12,0),IF(CH12="keep",CR12,0),IF(DC12="keep",DM12,0),IF(DX12="keep",EH12,0),IF(ES12="keep",FC12,0),IF(FN12="keep",FX12,0),IF(GI12="keep",GS12,0),IF(HD12="keep",HN12,0),IF(HY12="keep",II12,0),IF(IT12="keep",JD12,0)) -> 0 | AJ12: =SUM(IF(BM12="lease",BX12,0),IF(CH12="lease",CS12,0),IF(DC12="lease",DN12,0),IF(DX12="lease",EI12,0),IF(ES12="lease",FD12,0),IF(FN12="lease",FY12,0),IF(GI12="lease",GT12,0),IF(HD12="lease",HO12,0),IF(HY12="lease",IJ12,0),IF(IT12="lease",JE12,0)) -> 0 | AK12: =SUM(IF(BM12="keep",BX12,0),IF(CH12="keep",CS12,0),IF(DC12="keep",DN12,0),IF(DX12="keep",EI12,0),IF(ES12="keep",FD12,0),IF(FN12="keep",FY12,0),IF(GI12="keep",GT12,0),IF(HD12="keep",HO12,0),IF(HY12="keep",IJ12,0),IF(IT12="keep",JE12,0)) -> 0 | AL12: =R12-S11 -> 0 | AM12: =T12-U11 -> 0 | AN12: =AN11 -> 1 | AO12: =AO11+AH12 -> 0.044363429 | AP12: =AP11+AL12 -> 0 | AQ12: =AN12+AO12+AP12 -> 1.0443634 | AR12: =S12-AQ12 -> 0 | AS12: =AS11 -> 0 | AT12: =AT11+AI12 -> 0 | AU12: =AU11+AM12 -> 0 | AV12: =AS12+AT12+AU12 -> 0 | AW12: =U12-AV12 -> 0 | AX12: 1.0643468 | AY12: 1.0443634 | AZ12: =S12-AY12 -> 0 | BA12: 0 | BB12: 0 | BC12: =U12-BB12 -> 0 | BD12: =SUM(IF(BL12="direct",CE12,0),IF(CG12="direct",CZ12,0),IF(DB12="direct",DU12,0),IF(DW12="direct",EP12,0),IF(ER12="direct",FK12,0),IF(FM12="direct",GF12,0),IF(GH12="direct",HA12,0),IF(HC12="direct",HV12,0),IF(HX12="direct",IQ12,0),IF(IS12="direct",JL12,0)) -> 0 | BE12: =SUM(IF(BL12="treasury",CE12,0),IF(CG12="treasury",CZ12,0),IF(DB12="treasury",DU12,0),IF(DW12="treasury",EP12,0),IF(ER12="treasury",FK12,0),IF(FM12="treasury",GF12,0),IF(GH12="treasury",HA12,0),IF(HC12="treasury",HV12,0),IF(HX12="treasury",IQ12,0),IF(IS12="treasury",JL12,0)) -> 0.00016794521 | BF12: =SUM(IF(BL12="future",CE12,0),IF(CG12="future",CZ12,0),IF(DB12="future",DU12,0),IF(DW12="future",EP12,0),IF(ER12="future",FK12,0),IF(FM12="future",GF12,0),IF(GH12="future",HA12,0),IF(HC12="future",HV12,0),IF(HX12="future",IQ12,0),IF(IS12="future",JL12,0)) -> -0.01894317 | BG12: =SUM(IF(BL12="cash",CE12,0),IF(CG12="cash",CZ12,0),IF(DB12="cash",DU12,0),IF(DW12="cash",EP12,0),IF(ER12="cash",FK12,0),IF(FM12="cash",GF12,0),IF(GH12="cash",HA12,0),IF(HC12="cash",HV12,0),IF(HX12="cash",IQ12,0),IF(IS12="cash",JL12,0)) -> 0 | BH12: =SUM(BD12:BG12) -> -0.018775225 | BI12: =G12-BH12 -> 0 | BJ12: =COUNTA(BK12,CF12,DA12,DV12,EQ12,FL12,GG12,HB12,HW12,IR12) -> 4 | BK12: Treasury collateral | BL12: treasury | BM12: lease | BN12: long | BP12: 100.21922 | BQ12: 100.23605 | BR12: 0.010620186 | BS12: 1 | BT12: 1.0643468 | BU12: 1.0643468 | BV12: 1.0645255 | BW12: 0.00017875194 | BX12: 2.4530074e-17 | BY12: 2.038 | BZ12: 2.017 | CD12: 14 | CE12: =IFERROR(BW12/F12,0) -> 0.00016794521 | CF12: SI69F | CG12: future | CH12: lease | CI12: long | CJ12: regular | CK12: 2.006 | CL12: 1.968 | CM12: 0.53058164 | CN12: 1 | CO12: 1.0643468 | CP12: 0 | CQ12: 0 | CR12: -0.020162103 | CS12: 0.020162103 | CT12: 2.038 | CU12: 2.017 | CV12: -0.015701668 | CW12: 0.0613 | CX12: 0.47066492 | CY12: 14 | CZ12: =IFERROR(CR12/F12,0) -> -0.01894317 | DA12: Lease cash / margin / financing | DB12: cash | DC12: lease | DD12: cash | DF12: 1 | DG12: 1 | DH12: 0 | DJ12: 0 | DK12: 0 | DL12: -0.020162103 | DM12: 0 | DN12: -0.020162103 | DO12: 2.038 | DP12: 2.017 | DU12: =IFERROR(DM12/F12,0) -> 0 | DV12: Keep cash / margin / financing | DW12: cash | DX12: keep | DY12: cash | EA12: 1 | EB12: 1 | EC12: 0 | EE12: 0 | EF12: 0 | EG12: 0 | EH12: 0 | EI12: 0 | EJ12: 2.038 | EK12: 2.017 | EP12: =IFERROR(EH12/F12,0) -> 0
A13: 25219 | B13: 25220 | C13: =B13-A13 -> 1 | D13: 25219 | E13: positive | F13: 1.0443634 | G13: 0.00067388351 | H13: =SUM(CE13,CZ13,DU13,EP13,FK13,GF13,HA13,HV13,IQ13,JL13) -> 0.00067388351 | I13: =G13-H13 -> 1.0842022e-19 | J13: =F13*(1+H13) -> 1.0450672 | K13: 1.0450672 | L13: =K13-J13 -> 0 | M13: 2.017 | N13: 1.994 | O13: =M13/$M$3 -> 1.0301328 | P13: =N13/$M$3 -> 1.0183861 | Q13: =IFERROR(N13/M13-1,0) -> -0.011403074 | R13: =SUM(IF(BM13="lease",BU13,0),IF(CH13="lease",CP13,0),IF(DC13="lease",DK13,0),IF(DX13="lease",EF13,0),IF(ES13="lease",FA13,0),IF(FN13="lease",FV13,0),IF(GI13="lease",GQ13,0),IF(HD13="lease",HL13,0),IF(HY13="lease",IG13,0),IF(IT13="lease",JB13,0)) -> 1.0443634 | S13: =SUM(IF(BM13="lease",BV13,0),IF(CH13="lease",CQ13,0),IF(DC13="lease",DL13,0),IF(DX13="lease",EG13,0),IF(ES13="lease",FB13,0),IF(FN13="lease",FW13,0),IF(GI13="lease",GR13,0),IF(HD13="lease",HM13,0),IF(HY13="lease",IH13,0),IF(IT13="lease",JC13,0)) -> 1.0450672 | T13: =SUM(IF(BM13="keep",BU13,0),IF(CH13="keep",CP13,0),IF(DC13="keep",DK13,0),IF(DX13="keep",EF13,0),IF(ES13="keep",FA13,0),IF(FN13="keep",FV13,0),IF(GI13="keep",GQ13,0),IF(HD13="keep",HL13,0),IF(HY13="keep",IG13,0),IF(IT13="keep",JB13,0)) -> 0 | U13: =SUM(IF(BM13="keep",BV13,0),IF(CH13="keep",CQ13,0),IF(DC13="keep",DL13,0),IF(DX13="keep",EG13,0),IF(ES13="keep",FB13,0),IF(FN13="keep",FW13,0),IF(GI13="keep",GR13,0),IF(HD13="keep",HM13,0),IF(HY13="keep",IH13,0),IF(IT13="keep",JC13,0)) -> 0 | V13: =R13/O13 -> 1.0138144 | W13: =S13/P13 -> 1.0261994 | X13: =T13/O13 -> 0 | Y13: =U13/P13 -> 0 | Z13: =V13+X13 -> 1.0138144 | AA13: =IFERROR(W13/V13-1,0) -> 0.01221626 | AB13: =IFERROR((W13-V13)/Z13,0) -> 0.01221626 | AC13: =IFERROR(Y13/X13-1,0) -> 0 | AD13: =IFERROR((Y13-X13)/Z13,0) -> 0 | AE13: =AB13+AD13 -> 0.01221626 | AF13: =(1+Q13)*(1+AE13)-1 -> 0.00067388351 | AG13: =G13-AF13 -> -2.0979312e-16 | AH13: =SUM(IF(BM13="lease",BW13,0),IF(CH13="lease",CR13,0),IF(DC13="lease",DM13,0),IF(DX13="lease",EH13,0),IF(ES13="lease",FC13,0),IF(FN13="lease",FX13,0),IF(GI13="lease",GS13,0),IF(HD13="lease",HN13,0),IF(HY13="lease",II13,0),IF(IT13="lease",JD13,0)) -> 0.00070377929 | AI13: =SUM(IF(BM13="keep",BW13,0),IF(CH13="keep",CR13,0),IF(DC13="keep",DM13,0),IF(DX13="keep",EH13,0),IF(ES13="keep",FC13,0),IF(FN13="keep",FX13,0),IF(GI13="keep",GS13,0),IF(HD13="keep",HN13,0),IF(HY13="keep",II13,0),IF(IT13="keep",JD13,0)) -> 0 | AJ13: =SUM(IF(BM13="lease",BX13,0),IF(CH13="lease",CS13,0),IF(DC13="lease",DN13,0),IF(DX13="lease",EI13,0),IF(ES13="lease",FD13,0),IF(FN13="lease",FY13,0),IF(GI13="lease",GT13,0),IF(HD13="lease",HO13,0),IF(HY13="lease",IJ13,0),IF(IT13="lease",JE13,0)) -> 0 | AK13: =SUM(IF(BM13="keep",BX13,0),IF(CH13="keep",CS13,0),IF(DC13="keep",DN13,0),IF(DX13="keep",EI13,0),IF(ES13="keep",FD13,0),IF(FN13="keep",FY13,0),IF(GI13="keep",GT13,0),IF(HD13="keep",HO13,0),IF(HY13="keep",IJ13,0),IF(IT13="keep",JE13,0)) -> 0 | AL13: =R13-S12 -> 0 | AM13: =T13-U12 -> 0 | AN13: =AN12 -> 1 | AO13: =AO12+AH13 -> 0.045067208 | AP13: =AP12+AL13 -> 0 | AQ13: =AN13+AO13+AP13 -> 1.0450672 | AR13: =S13-AQ13 -> 0 | AS13: =AS12 -> 0 | AT13: =AT12+AI13 -> 0 | AU13: =AU12+AM13 -> 0 | AV13: =AS13+AT13+AU13 -> 0 | AW13: =U13-AV13 -> 0 | AX13: 1.0443634 | AY13: 1.0450672 | AZ13: =S13-AY13 -> 0 | BA13: 0 | BB13: 0 | BC13: =U13-BB13 -> 0 | BD13: =SUM(IF(BL13="direct",CE13,0),IF(CG13="direct",CZ13,0),IF(DB13="direct",DU13,0),IF(DW13="direct",EP13,0),IF(ER13="direct",FK13,0),IF(FM13="direct",GF13,0),IF(GH13="direct",HA13,0),IF(HC13="direct",HV13,0),IF(HX13="direct",IQ13,0),IF(IS13="direct",JL13,0)) -> 0 | BE13: =SUM(IF(BL13="treasury",CE13,0),IF(CG13="treasury",CZ13,0),IF(DB13="treasury",DU13,0),IF(DW13="treasury",EP13,0),IF(ER13="treasury",FK13,0),IF(FM13="treasury",GF13,0),IF(GH13="treasury",HA13,0),IF(HC13="treasury",HV13,0),IF(HX13="treasury",IQ13,0),IF(IS13="treasury",JL13,0)) -> 0.00016575342 | BF13: =SUM(IF(BL13="future",CE13,0),IF(CG13="future",CZ13,0),IF(DB13="future",DU13,0),IF(DW13="future",EP13,0),IF(ER13="future",FK13,0),IF(FM13="future",GF13,0),IF(GH13="future",HA13,0),IF(HC13="future",HV13,0),IF(HX13="future",IQ13,0),IF(IS13="future",JL13,0)) -> 0.00050813008 | BG13: =SUM(IF(BL13="cash",CE13,0),IF(CG13="cash",CZ13,0),IF(DB13="cash",DU13,0),IF(DW13="cash",EP13,0),IF(ER13="cash",FK13,0),IF(FM13="cash",GF13,0),IF(GH13="cash",HA13,0),IF(HC13="cash",HV13,0),IF(HX13="cash",IQ13,0),IF(IS13="cash",JL13,0)) -> 0 | BH13: =SUM(BD13:BG13) -> 0.00067388351 | BI13: =G13-BH13 -> 1.0842022e-19 | BJ13: =COUNTA(BK13,CF13,DA13,DV13,EQ13,FL13,GG13,HB13,HW13,IR13) -> 4 | BK13: Treasury collateral | BL13: treasury | BM13: lease | BN13: long | BP13: 100.23605 | BQ13: 100.25266 | BR13: 0.01041904 | BS13: 1 | BT13: 1.0443634 | BU13: 1.0443634 | BV13: 1.0445365 | BW13: 0.00017310681 | BX13: 3.0981077e-17 | BY13: 2.017 | BZ13: 1.994 | CD13: 13 | CE13: =IFERROR(BW13/F13,0) -> 0.00016575342 | CF13: SI69F | CG13: future | CH13: lease | CI13: long | CJ13: regular | CK13: 1.968 | CL13: 1.969 | CM13: 0.53067247 | CN13: 1 | CO13: 1.0443634 | CP13: 0 | CQ13: 0 | CR13: 0.00053067247 | CS13: -0.00053067247 | CT13: 2.017 | CU13: 1.994 | CV13: -0.024293505 | CW13: 0.0605 | CX13: 0.74258688 | CY13: 13 | CZ13: =IFERROR(CR13/F13,0) -> 0.00050813008 | DA13: Lease cash / margin / financing | DB13: cash | DC13: lease | DD13: cash | DF13: 1 | DG13: 1 | DH13: 0 | DJ13: 0 | DK13: 0 | DL13: 0.00053067247 | DM13: 0 | DN13: 0.00053067247 | DO13: 2.017 | DP13: 1.994 | DU13: =IFERROR(DM13/F13,0) -> 0 | DV13: Keep cash / margin / financing | DW13: cash | DX13: keep | DY13: cash | EA13: 1 | EB13: 1 | EC13: 0 | EE13: 0 | EF13: 0 | EG13: 0 | EH13: 0 | EI13: 0 | EJ13: 2.017 | EK13: 1.994 | EP13: =IFERROR(EH13/F13,0) -> 0
A14: 25220 | B14: 25223 | C14: =B14-A14 -> 3 | D14: 25220 | E14: positive | F14: 1.0450672 | G14: 0.016242937 | H14: =SUM(CE14,CZ14,DU14,EP14,FK14,GF14,HA14,HV14,IQ14,JL14) -> 0.016242937 | I14: =G14-H14 -> 0 | J14: =F14*(1+H14) -> 1.0620422 | K14: 1.0620422 | L14: =K14-J14 -> 0 | M14: 1.994 | N14: 1.994 | O14: =M14/$M$3 -> 1.0183861 | P14: =N14/$M$3 -> 1.0183861 | Q14: =IFERROR(N14/M14-1,0) -> 0 | R14: =SUM(IF(BM14="lease",BU14,0),IF(CH14="lease",CP14,0),IF(DC14="lease",DK14,0),IF(DX14="lease",EF14,0),IF(ES14="lease",FA14,0),IF(FN14="lease",FV14,0),IF(GI14="lease",GQ14,0),IF(HD14="lease",HL14,0),IF(HY14="lease",IG14,0),IF(IT14="lease",JB14,0)) -> 1.0450672 | S14: =SUM(IF(BM14="lease",BV14,0),IF(CH14="lease",CQ14,0),IF(DC14="lease",DL14,0),IF(DX14="lease",EG14,0),IF(ES14="lease",FB14,0),IF(FN14="lease",FW14,0),IF(GI14="lease",GR14,0),IF(HD14="lease",HM14,0),IF(HY14="lease",IH14,0),IF(IT14="lease",JC14,0)) -> 1.0620422 | T14: =SUM(IF(BM14="keep",BU14,0),IF(CH14="keep",CP14,0),IF(DC14="keep",DK14,0),IF(DX14="keep",EF14,0),IF(ES14="keep",FA14,0),IF(FN14="keep",FV14,0),IF(GI14="keep",GQ14,0),IF(HD14="keep",HL14,0),IF(HY14="keep",IG14,0),IF(IT14="keep",JB14,0)) -> 0 | U14: =SUM(IF(BM14="keep",BV14,0),IF(CH14="keep",CQ14,0),IF(DC14="keep",DL14,0),IF(DX14="keep",EG14,0),IF(ES14="keep",FB14,0),IF(FN14="keep",FW14,0),IF(GI14="keep",GR14,0),IF(HD14="keep",HM14,0),IF(HY14="keep",IH14,0),IF(IT14="keep",JC14,0)) -> 0 | V14: =R14/O14 -> 1.0261994 | W14: =S14/P14 -> 1.0428679 | X14: =T14/O14 -> 0 | Y14: =U14/P14 -> 0 | Z14: =V14+X14 -> 1.0261994 | AA14: =IFERROR(W14/V14-1,0) -> 0.016242937 | AB14: =IFERROR((W14-V14)/Z14,0) -> 0.016242937 | AC14: =IFERROR(Y14/X14-1,0) -> 0 | AD14: =IFERROR((Y14-X14)/Z14,0) -> 0 | AE14: =AB14+AD14 -> 0.016242937 | AF14: =(1+Q14)*(1+AE14)-1 -> 0.016242937 | AG14: =G14-AF14 -> 1.8041124e-16 | AH14: =SUM(IF(BM14="lease",BW14,0),IF(CH14="lease",CR14,0),IF(DC14="lease",DM14,0),IF(DX14="lease",EH14,0),IF(ES14="lease",FC14,0),IF(FN14="lease",FX14,0),IF(GI14="lease",GS14,0),IF(HD14="lease",HN14,0),IF(HY14="lease",II14,0),IF(IT14="lease",JD14,0)) -> 0.01697496 | AI14: =SUM(IF(BM14="keep",BW14,0),IF(CH14="keep",CR14,0),IF(DC14="keep",DM14,0),IF(DX14="keep",EH14,0),IF(ES14="keep",FC14,0),IF(FN14="keep",FX14,0),IF(GI14="keep",GS14,0),IF(HD14="keep",HN14,0),IF(HY14="keep",II14,0),IF(IT14="keep",JD14,0)) -> 0 | AJ14: =SUM(IF(BM14="lease",BX14,0),IF(CH14="lease",CS14,0),IF(DC14="lease",DN14,0),IF(DX14="lease",EI14,0),IF(ES14="lease",FD14,0),IF(FN14="lease",FY14,0),IF(GI14="lease",GT14,0),IF(HD14="lease",HO14,0),IF(HY14="lease",IJ14,0),IF(IT14="lease",JE14,0)) -> 0 | AK14: =SUM(IF(BM14="keep",BX14,0),IF(CH14="keep",CS14,0),IF(DC14="keep",DN14,0),IF(DX14="keep",EI14,0),IF(ES14="keep",FD14,0),IF(FN14="keep",FY14,0),IF(GI14="keep",GT14,0),IF(HD14="keep",HO14,0),IF(HY14="keep",IJ14,0),IF(IT14="keep",JE14,0)) -> 0 | AL14: =R14-S13 -> 0 | AM14: =T14-U13 -> 0 | AN14: =AN13 -> 1 | AO14: =AO13+AH14 -> 0.062042168 | AP14: =AP13+AL14 -> 0 | AQ14: =AN14+AO14+AP14 -> 1.0620422 | AR14: =S14-AQ14 -> -2.220446e-16 | AS14: =AS13 -> 0 | AT14: =AT13+AI14 -> 0 | AU14: =AU13+AM14 -> 0 | AV14: =AS14+AT14+AU14 -> 0 | AW14: =U14-AV14 -> 0 | AX14: 1.0450672 | AY14: 1.0620422 | AZ14: =S14-AY14 -> 0 | BA14: 0 | BB14: 0 | BC14: =U14-BB14 -> 0 | BD14: =SUM(IF(BL14="direct",CE14,0),IF(CG14="direct",CZ14,0),IF(DB14="direct",DU14,0),IF(DW14="direct",EP14,0),IF(ER14="direct",FK14,0),IF(FM14="direct",GF14,0),IF(GH14="direct",HA14,0),IF(HC14="direct",HV14,0),IF(HX14="direct",IQ14,0),IF(IS14="direct",JL14,0)) -> 0 | BE14: =SUM(IF(BL14="treasury",CE14,0),IF(CG14="treasury",CZ14,0),IF(DB14="treasury",DU14,0),IF(DW14="treasury",EP14,0),IF(ER14="treasury",FK14,0),IF(FM14="treasury",GF14,0),IF(GH14="treasury",HA14,0),IF(HC14="treasury",HV14,0),IF(HX14="treasury",IQ14,0),IF(IS14="treasury",JL14,0)) -> 0.00049890411 | BF14: =SUM(IF(BL14="future",CE14,0),IF(CG14="future",CZ14,0),IF(DB14="future",DU14,0),IF(DW14="future",EP14,0),IF(ER14="future",FK14,0),IF(FM14="future",GF14,0),IF(GH14="future",HA14,0),IF(HC14="future",HV14,0),IF(HX14="future",IQ14,0),IF(IS14="future",JL14,0)) -> 0.015744033 | BG14: =SUM(IF(BL14="cash",CE14,0),IF(CG14="cash",CZ14,0),IF(DB14="cash",DU14,0),IF(DW14="cash",EP14,0),IF(ER14="cash",FK14,0),IF(FM14="cash",GF14,0),IF(GH14="cash",HA14,0),IF(HC14="cash",HV14,0),IF(HX14="cash",IQ14,0),IF(IS14="cash",JL14,0)) -> 0 | BH14: =SUM(BD14:BG14) -> 0.016242937 | BI14: =G14-BH14 -> 0 | BJ14: =COUNTA(BK14,CF14,DA14,DV14,EQ14,FL14,GG14,HB14,HW14,IR14) -> 4 | BK14: Treasury collateral | BL14: treasury | BM14: lease | BN14: long | BP14: 100.25266 | BQ14: 100.30268 | BR14: 0.010424334 | BS14: 1 | BT14: 1.0450672 | BU14: 1.0450672 | BV14: 1.0455886 | BW14: 0.00052138832 | BX14: -1.3606737e-16 | BY14: 1.994 | BZ14: 1.994 | CD14: 12 | CE14: =IFERROR(BW14/F14,0) -> 0.00049890411 | CF14: SI69F | CG14: future | CH14: lease | CI14: long | CJ14: regular | CK14: 1.969 | CL14: 2 | CM14: 0.53076039 | CN14: 1 | CO14: 1.0450672 | CP14: 0 | CQ14: 0 | CR14: 0.016453572 | CS14: -0.016453572 | CT14: 1.994 | CU14: 1.994 | CV14: -0.012537613 | CW14: 0.0607 | CX14: 0.44205239 | CY14: 12 | CZ14: =IFERROR(CR14/F14,0) -> 0.015744033 | DA14: Lease cash / margin / financing | DB14: cash | DC14: lease | DD14: cash | DF14: 1 | DG14: 1 | DH14: 0 | DJ14: 0 | DK14: 0 | DL14: 0.016453572 | DM14: 0 | DN14: 0.016453572 | DO14: 1.994 | DP14: 1.994 | DU14: =IFERROR(DM14/F14,0) -> 0 | DV14: Keep cash / margin / financing | DW14: cash | DX14: keep | DY14: cash | EA14: 1 | EB14: 1 | EC14: 0 | EE14: 0 | EF14: 0 | EG14: 0 | EH14: 0 | EI14: 0 | EJ14: 1.994 | EK14: 1.994 | EP14: =IFERROR(EH14/F14,0) -> 0
A15: 25223 | B15: 25224 | C15: =B15-A15 -> 1 | D15: 25223 | E15: neutral | F15: 1.0620422 | G15: 0.010524745 | H15: =SUM(CE15,CZ15,DU15,EP15,FK15,GF15,HA15,HV15,IQ15,JL15) -> 0.010524745 | I15: =G15-H15 -> 0 | J15: =F15*(1+H15) -> 1.0732199 | K15: 1.0732199 | L15: =K15-J15 -> 0 | M15: 1.994 | N15: 2.015 | O15: =M15/$M$3 -> 1.0183861 | P15: =N15/$M$3 -> 1.0291113 | Q15: =IFERROR(N15/M15-1,0) -> 0.010531595 | R15: =SUM(IF(BM15="lease",BU15,0),IF(CH15="lease",CP15,0),IF(DC15="lease",DK15,0),IF(DX15="lease",EF15,0),IF(ES15="lease",FA15,0),IF(FN15="lease",FV15,0),IF(GI15="lease",GQ15,0),IF(HD15="lease",HL15,0),IF(HY15="lease",IG15,0),IF(IT15="lease",JB15,0)) -> 1.0620422 | S15: =SUM(IF(BM15="lease",BV15,0),IF(CH15="lease",CQ15,0),IF(DC15="lease",DL15,0),IF(DX15="lease",EG15,0),IF(ES15="lease",FB15,0),IF(FN15="lease",FW15,0),IF(GI15="lease",GR15,0),IF(HD15="lease",HM15,0),IF(HY15="lease",IH15,0),IF(IT15="lease",JC15,0)) -> 1.0732199 | T15: =SUM(IF(BM15="keep",BU15,0),IF(CH15="keep",CP15,0),IF(DC15="keep",DK15,0),IF(DX15="keep",EF15,0),IF(ES15="keep",FA15,0),IF(FN15="keep",FV15,0),IF(GI15="keep",GQ15,0),IF(HD15="keep",HL15,0),IF(HY15="keep",IG15,0),IF(IT15="keep",JB15,0)) -> 0 | U15: =SUM(IF(BM15="keep",BV15,0),IF(CH15="keep",CQ15,0),IF(DC15="keep",DL15,0),IF(DX15="keep",EG15,0),IF(ES15="keep",FB15,0),IF(FN15="keep",FW15,0),IF(GI15="keep",GR15,0),IF(HD15="keep",HM15,0),IF(HY15="keep",IH15,0),IF(IT15="keep",JC15,0)) -> 0 | V15: =R15/O15 -> 1.0428679 | W15: =S15/P15 -> 1.0428608 | X15: =T15/O15 -> 0 | Y15: =U15/P15 -> 0 | Z15: =V15+X15 -> 1.0428679 | AA15: =IFERROR(W15/V15-1,0) -> -6.7779326e-06 | AB15: =IFERROR((W15-V15)/Z15,0) -> -6.7779326e-06 | AC15: =IFERROR(Y15/X15-1,0) -> 0 | AD15: =IFERROR((Y15-X15)/Z15,0) -> 0 | AE15: =AB15+AD15 -> -6.7779326e-06 | AF15: =(1+Q15)*(1+AE15)-1 -> 0.010524745 | AG15: =G15-AF15 -> -4.6837534e-17 | AH15: =SUM(IF(BM15="lease",BW15,0),IF(CH15="lease",CR15,0),IF(DC15="lease",DM15,0),IF(DX15="lease",EH15,0),IF(ES15="lease",FC15,0),IF(FN15="lease",FX15,0),IF(GI15="lease",GS15,0),IF(HD15="lease",HN15,0),IF(HY15="lease",II15,0),IF(IT15="lease",JD15,0)) -> 0.011177724 | AI15: =SUM(IF(BM15="keep",BW15,0),IF(CH15="keep",CR15,0),IF(DC15="keep",DM15,0),IF(DX15="keep",EH15,0),IF(ES15="keep",FC15,0),IF(FN15="keep",FX15,0),IF(GI15="keep",GS15,0),IF(HD15="keep",HN15,0),IF(HY15="keep",II15,0),IF(IT15="keep",JD15,0)) -> 0 | AJ15: =SUM(IF(BM15="lease",BX15,0),IF(CH15="lease",CS15,0),IF(DC15="lease",DN15,0),IF(DX15="lease",EI15,0),IF(ES15="lease",FD15,0),IF(FN15="lease",FY15,0),IF(GI15="lease",GT15,0),IF(HD15="lease",HO15,0),IF(HY15="lease",IJ15,0),IF(IT15="lease",JE15,0)) -> 0 | AK15: =SUM(IF(BM15="keep",BX15,0),IF(CH15="keep",CS15,0),IF(DC15="keep",DN15,0),IF(DX15="keep",EI15,0),IF(ES15="keep",FD15,0),IF(FN15="keep",FY15,0),IF(GI15="keep",GT15,0),IF(HD15="keep",HO15,0),IF(HY15="keep",IJ15,0),IF(IT15="keep",JE15,0)) -> 0 | AL15: =R15-S14 -> 0 | AM15: =T15-U14 -> 0 | AN15: =AN14 -> 1 | AO15: =AO14+AH15 -> 0.073219892 | AP15: =AP14+AL15 -> 0 | AQ15: =AN15+AO15+AP15 -> 1.0732199 | AR15: =S15-AQ15 -> -2.220446e-16 | AS15: =AS14 -> 0 | AT15: =AT14+AI15 -> 0 | AU15: =AU14+AM15 -> 0 | AV15: =AS15+AT15+AU15 -> 0 | AW15: =U15-AV15 -> 0 | AX15: 1.0620422 | AY15: 1.0732199 | AZ15: =S15-AY15 -> 0 | BA15: 0 | BB15: 0 | BC15: =U15-BB15 -> 0 | BD15: =SUM(IF(BL15="direct",CE15,0),IF(CG15="direct",CZ15,0),IF(DB15="direct",DU15,0),IF(DW15="direct",EP15,0),IF(ER15="direct",FK15,0),IF(FM15="direct",GF15,0),IF(GH15="direct",HA15,0),IF(HC15="direct",HV15,0),IF(HX15="direct",IQ15,0),IF(IS15="direct",JL15,0)) -> 0.010524745 | BE15: =SUM(IF(BL15="treasury",CE15,0),IF(CG15="treasury",CZ15,0),IF(DB15="treasury",DU15,0),IF(DW15="treasury",EP15,0),IF(ER15="treasury",FK15,0),IF(FM15="treasury",GF15,0),IF(GH15="treasury",HA15,0),IF(HC15="treasury",HV15,0),IF(HX15="treasury",IQ15,0),IF(IS15="treasury",JL15,0)) -> 0 | BF15: =SUM(IF(BL15="future",CE15,0),IF(CG15="future",CZ15,0),IF(DB15="future",DU15,0),IF(DW15="future",EP15,0),IF(ER15="future",FK15,0),IF(FM15="future",GF15,0),IF(GH15="future",HA15,0),IF(HC15="future",HV15,0),IF(HX15="future",IQ15,0),IF(IS15="future",JL15,0)) -> 0 | BG15: =SUM(IF(BL15="cash",CE15,0),IF(CG15="cash",CZ15,0),IF(DB15="cash",DU15,0),IF(DW15="cash",EP15,0),IF(ER15="cash",FK15,0),IF(FM15="cash",GF15,0),IF(GH15="cash",HA15,0),IF(HC15="cash",HV15,0),IF(HX15="cash",IQ15,0),IF(IS15="cash",JL15,0)) -> 0 | BH15: =SUM(BD15:BG15) -> 0.010524745 | BI15: =G15-BH15 -> 0 | BJ15: =COUNTA(BK15,CF15,DA15,DV15,EQ15,FL15,GG15,HB15,HW15,IR15) -> 3 | BK15: Direct commodity holding | BL15: direct | BM15: lease | BN15: long | BP15: 1.994 | BQ15: 2.015 | BR15: 0.53261894 | BS15: 1 | BT15: 1.0620422 | BU15: 1.0620422 | BV15: 1.0732272 | BW15: 0.011177724 | BX15: 7.2742614e-06 | BY15: 1.994 | BZ15: 2.015 | CE15: =IFERROR(BW15/F15,0) -> 0.010524745 | CF15: Lease cash / margin / financing | CG15: cash | CH15: lease | CI15: cash | CK15: 1 | CL15: 1 | CM15: 0 | CO15: 0 | CP15: 0 | CQ15: -7.2742614e-06 | CR15: 0 | CS15: -7.2742614e-06 | CT15: 1.994 | CU15: 2.015 | CZ15: =IFERROR(CR15/F15,0) -> 0 | DA15: Keep cash / margin / financing | DB15: cash | DC15: keep | DD15: cash | DF15: 1 | DG15: 1 | DH15: 0 | DJ15: 0 | DK15: 0 | DL15: 0 | DM15: 0 | DN15: 0 | DO15: 1.994 | DP15: 2.015 | DU15: =IFERROR(DM15/F15,0) -> 0
A16: 25224 | B16: 25225 | C16: =B16-A16 -> 1 | D16: 25224 | E16: positive | F16: 1.0732199 | G16: -0.0048432881 | H16: =SUM(CE16,CZ16,DU16,EP16,FK16,GF16,HA16,HV16,IQ16,JL16) -> -0.0048432881 | I16: =G16-H16 -> 0 | J16: =F16*(1+H16) -> 1.068022 | K16: 1.068022 | L16: =K16-J16 -> 0 | M16: 2.015 | N16: 2.002 | O16: =M16/$M$3 -> 1.0291113 | P16: =N16/$M$3 -> 1.0224719 | Q16: =IFERROR(N16/M16-1,0) -> -0.0064516129 | R16: =SUM(IF(BM16="lease",BU16,0),IF(CH16="lease",CP16,0),IF(DC16="lease",DK16,0),IF(DX16="lease",EF16,0),IF(ES16="lease",FA16,0),IF(FN16="lease",FV16,0),IF(GI16="lease",GQ16,0),IF(HD16="lease",HL16,0),IF(HY16="lease",IG16,0),IF(IT16="lease",JB16,0)) -> 1.0732199 | S16: =SUM(IF(BM16="lease",BV16,0),IF(CH16="lease",CQ16,0),IF(DC16="lease",DL16,0),IF(DX16="lease",EG16,0),IF(ES16="lease",FB16,0),IF(FN16="lease",FW16,0),IF(GI16="lease",GR16,0),IF(HD16="lease",HM16,0),IF(HY16="lease",IH16,0),IF(IT16="lease",JC16,0)) -> 1.068022 | T16: =SUM(IF(BM16="keep",BU16,0),IF(CH16="keep",CP16,0),IF(DC16="keep",DK16,0),IF(DX16="keep",EF16,0),IF(ES16="keep",FA16,0),IF(FN16="keep",FV16,0),IF(GI16="keep",GQ16,0),IF(HD16="keep",HL16,0),IF(HY16="keep",IG16,0),IF(IT16="keep",JB16,0)) -> 0 | U16: =SUM(IF(BM16="keep",BV16,0),IF(CH16="keep",CQ16,0),IF(DC16="keep",DL16,0),IF(DX16="keep",EG16,0),IF(ES16="keep",FB16,0),IF(FN16="keep",FW16,0),IF(GI16="keep",GR16,0),IF(HD16="keep",HM16,0),IF(HY16="keep",IH16,0),IF(IT16="keep",JC16,0)) -> 0 | V16: =R16/O16 -> 1.0428608 | W16: =S16/P16 -> 1.044549 | X16: =T16/O16 -> 0 | Y16: =U16/P16 -> 0 | Z16: =V16+X16 -> 1.0428608 | AA16: =IFERROR(W16/V16-1,0) -> 0.0016187685 | AB16: =IFERROR((W16-V16)/Z16,0) -> 0.0016187685 | AC16: =IFERROR(Y16/X16-1,0) -> 0 | AD16: =IFERROR((Y16-X16)/Z16,0) -> 0 | AE16: =AB16+AD16 -> 0.0016187685 | AF16: =(1+Q16)*(1+AE16)-1 -> -0.0048432881 | AG16: =G16-AF16 -> -3.6862874e-16 | AH16: =SUM(IF(BM16="lease",BW16,0),IF(CH16="lease",CR16,0),IF(DC16="lease",DM16,0),IF(DX16="lease",EH16,0),IF(ES16="lease",FC16,0),IF(FN16="lease",FX16,0),IF(GI16="lease",GS16,0),IF(HD16="lease",HN16,0),IF(HY16="lease",II16,0),IF(IT16="lease",JD16,0)) -> -0.0051979131 | AI16: =SUM(IF(BM16="keep",BW16,0),IF(CH16="keep",CR16,0),IF(DC16="keep",DM16,0),IF(DX16="keep",EH16,0),IF(ES16="keep",FC16,0),IF(FN16="keep",FX16,0),IF(GI16="keep",GS16,0),IF(HD16="keep",HN16,0),IF(HY16="keep",II16,0),IF(IT16="keep",JD16,0)) -> 0 | AJ16: =SUM(IF(BM16="lease",BX16,0),IF(CH16="lease",CS16,0),IF(DC16="lease",DN16,0),IF(DX16="lease",EI16,0),IF(ES16="lease",FD16,0),IF(FN16="lease",FY16,0),IF(GI16="lease",GT16,0),IF(HD16="lease",HO16,0),IF(HY16="lease",IJ16,0),IF(IT16="lease",JE16,0)) -> 0 | AK16: =SUM(IF(BM16="keep",BX16,0),IF(CH16="keep",CS16,0),IF(DC16="keep",DN16,0),IF(DX16="keep",EI16,0),IF(ES16="keep",FD16,0),IF(FN16="keep",FY16,0),IF(GI16="keep",GT16,0),IF(HD16="keep",HO16,0),IF(HY16="keep",IJ16,0),IF(IT16="keep",JE16,0)) -> 0 | AL16: =R16-S15 -> 0 | AM16: =T16-U15 -> 0 | AN16: =AN15 -> 1 | AO16: =AO15+AH16 -> 0.068021979 | AP16: =AP15+AL16 -> 0 | AQ16: =AN16+AO16+AP16 -> 1.068022 | AR16: =S16-AQ16 -> 0 | AS16: =AS15 -> 0 | AT16: =AT15+AI16 -> 0 | AU16: =AU15+AM16 -> 0 | AV16: =AS16+AT16+AU16 -> 0 | AW16: =U16-AV16 -> 0 | AX16: 1.0732199 | AY16: 1.068022 | AZ16: =S16-AY16 -> 2.220446e-16 | BA16: 0 | BB16: 0 | BC16: =U16-BB16 -> 0 | BD16: =SUM(IF(BL16="direct",CE16,0),IF(CG16="direct",CZ16,0),IF(DB16="direct",DU16,0),IF(DW16="direct",EP16,0),IF(ER16="direct",FK16,0),IF(FM16="direct",GF16,0),IF(GH16="direct",HA16,0),IF(HC16="direct",HV16,0),IF(HX16="direct",IQ16,0),IF(IS16="direct",JL16,0)) -> -0.0035963481 | BE16: =SUM(IF(BL16="treasury",CE16,0),IF(CG16="treasury",CZ16,0),IF(DB16="treasury",DU16,0),IF(DW16="treasury",EP16,0),IF(ER16="treasury",FK16,0),IF(FM16="treasury",GF16,0),IF(GH16="treasury",HA16,0),IF(HC16="treasury",HV16,0),IF(HX16="treasury",IQ16,0),IF(IS16="treasury",JL16,0)) -> 7.3940478e-05 | BF16: =SUM(IF(BL16="future",CE16,0),IF(CG16="future",CZ16,0),IF(DB16="future",DU16,0),IF(DW16="future",EP16,0),IF(ER16="future",FK16,0),IF(FM16="future",GF16,0),IF(GH16="future",HA16,0),IF(HC16="future",HV16,0),IF(HX16="future",IQ16,0),IF(IS16="future",JL16,0)) -> -0.0013208805 | BG16: =SUM(IF(BL16="cash",CE16,0),IF(CG16="cash",CZ16,0),IF(DB16="cash",DU16,0),IF(DW16="cash",EP16,0),IF(ER16="cash",FK16,0),IF(FM16="cash",GF16,0),IF(GH16="cash",HA16,0),IF(HC16="cash",HV16,0),IF(HX16="cash",IQ16,0),IF(IS16="cash",JL16,0)) -> 0 | BH16: =SUM(BD16:BG16) -> -0.0048432881 | BI16: =G16-BH16 -> 0 | BJ16: =COUNTA(BK16,CF16,DA16,DV16,EQ16,FL16,GG16,HB16,HW16,IR16) -> 6 | BK16: Direct commodity holding | BL16: direct | BM16: lease | BN16: long | BP16: 2.015 | BQ16: 2.002 | BR16: 0.296583 | BS16: 0.55684278 | BT16: 0.59761475 | BU16: 0.59761475 | BV16: 0.59375917 | BW16: -0.0038596723 | BX16: 4.0932517e-06 | BY16: 2.015 | BZ16: 2.002 | CE16: =IFERROR(BW16/F16,0) -> -0.0035963481 | CF16: Treasury collateral | CG16: treasury | CH16: lease | CI16: long | CK16: 100.3192 | CL16: 100.33593 | CM16: 0.0047409186 | CN16: 0.44315722 | CO16: 0.47560514 | CP16: 0.47560514 | CQ16: 0.4756845 | CR16: 7.9354392e-05 | CS16: -6.8670655e-17 | CT16: 2.015 | CU16: 2.002 | CY16: 65 | CZ16: =IFERROR(CR16/F16,0) -> 7.3940478e-05 | DA16: SI69H | DB16: future | DC16: lease | DD16: long | DE16: regular | DF16: 2.013 | DG16: 2.007 | DH16: 0.23621204 | DI16: 0.44305443 | DJ16: 0.47549483 | DK16: 0 | DL16: 0 | DM16: -0.0014172722 | DN16: 0.0014172722 | DO16: 2.015 | DP16: 2.002 | DQ16: -0.00099255583 | DR16: 0.0609 | DS16: 0.066473583 | DT16: 65 | DU16: =IFERROR(DM16/F16,0) -> -0.0013205795 | DV16: SI69K | DW16: future | DX16: lease | DY16: long | DZ16: regular | EA16: 2.049 | EB16: 2.043 | EC16: 5.3837495e-05 | ED16: 0.00010278698 | EE16: 0.00011031303 | EF16: 0 | EG16: 0 | EH16: -3.2302497e-07 | EI16: 3.2302497e-07 | EJ16: 2.015 | EK16: 2.002 | EL16: 0.016873449 | EM16: 0.061335165 | EN16: 0.012840606 | EO16: 127 | EP16: =IFERROR(EH16/F16,0) -> -3.0098675e-07 | EQ16: Lease cash / margin / financing | ER16: cash | ES16: lease | ET16: cash | EV16: 1 | EW16: 1 | EX16: -2.220446e-16 | EZ16: -2.220446e-16 | FA16: -2.220446e-16 | FB16: -0.0014216885 | FC16: 0 | FD16: -0.0014216885 | FE16: 2.015 | FF16: 2.002 | FK16: =IFERROR(FC16/F16,0) -> 0 | FL16: Keep cash / margin / financing | FM16: cash | FN16: keep | FO16: cash | FQ16: 1 | FR16: 1 | FS16: 0 | FU16: 0 | FV16: 0 | FW16: 0 | FX16: 0 | FY16: 0 | FZ16: 2.015 | GA16: 2.002 | GF16: =IFERROR(FX16/F16,0) -> 0
A17: 25225 | B17: 25226 | C17: =B17-A17 -> 1 | D17: 25225 | E17: positive | F17: 1.068022 | G17: -0.010246789 | H17: =SUM(CE17,CZ17,DU17,EP17,FK17,GF17,HA17,HV17,IQ17,JL17) -> -0.010246789 | I17: =G17-H17 -> 1.7347235e-18 | J17: =F17*(1+H17) -> 1.0570782 | K17: 1.0570782 | L17: =K17-J17 -> 0 | M17: 2.002 | N17: 1.982 | O17: =M17/$M$3 -> 1.0224719 | P17: =N17/$M$3 -> 1.0122574 | Q17: =IFERROR(N17/M17-1,0) -> -0.00999001 | R17: =SUM(IF(BM17="lease",BU17,0),IF(CH17="lease",CP17,0),IF(DC17="lease",DK17,0),IF(DX17="lease",EF17,0),IF(ES17="lease",FA17,0),IF(FN17="lease",FV17,0),IF(GI17="lease",GQ17,0),IF(HD17="lease",HL17,0),IF(HY17="lease",IG17,0),IF(IT17="lease",JB17,0)) -> 1.068022 | S17: =SUM(IF(BM17="lease",BV17,0),IF(CH17="lease",CQ17,0),IF(DC17="lease",DL17,0),IF(DX17="lease",EG17,0),IF(ES17="lease",FB17,0),IF(FN17="lease",FW17,0),IF(GI17="lease",GR17,0),IF(HD17="lease",HM17,0),IF(HY17="lease",IH17,0),IF(IT17="lease",JC17,0)) -> 1.0570782 | T17: =SUM(IF(BM17="keep",BU17,0),IF(CH17="keep",CP17,0),IF(DC17="keep",DK17,0),IF(DX17="keep",EF17,0),IF(ES17="keep",FA17,0),IF(FN17="keep",FV17,0),IF(GI17="keep",GQ17,0),IF(HD17="keep",HL17,0),IF(HY17="keep",IG17,0),IF(IT17="keep",JB17,0)) -> 0 | U17: =SUM(IF(BM17="keep",BV17,0),IF(CH17="keep",CQ17,0),IF(DC17="keep",DL17,0),IF(DX17="keep",EG17,0),IF(ES17="keep",FB17,0),IF(FN17="keep",FW17,0),IF(GI17="keep",GR17,0),IF(HD17="keep",HM17,0),IF(HY17="keep",IH17,0),IF(IT17="keep",JC17,0)) -> 0 | V17: =R17/O17 -> 1.044549 | W17: =S17/P17 -> 1.044278 | X17: =T17/O17 -> 0 | Y17: =U17/P17 -> 0 | Z17: =V17+X17 -> 1.044549 | AA17: =IFERROR(W17/V17-1,0) -> -0.00025937018 | AB17: =IFERROR((W17-V17)/Z17,0) -> -0.00025937018 | AC17: =IFERROR(Y17/X17-1,0) -> 0 | AD17: =IFERROR((Y17-X17)/Z17,0) -> 0 | AE17: =AB17+AD17 -> -0.00025937018 | AF17: =(1+Q17)*(1+AE17)-1 -> -0.010246789 | AG17: =G17-AF17 -> 2.1163626e-16 | AH17: =SUM(IF(BM17="lease",BW17,0),IF(CH17="lease",CR17,0),IF(DC17="lease",DM17,0),IF(DX17="lease",EH17,0),IF(ES17="lease",FC17,0),IF(FN17="lease",FX17,0),IF(GI17="lease",GS17,0),IF(HD17="lease",HN17,0),IF(HY17="lease",II17,0),IF(IT17="lease",JD17,0)) -> -0.010943796 | AI17: =SUM(IF(BM17="keep",BW17,0),IF(CH17="keep",CR17,0),IF(DC17="keep",DM17,0),IF(DX17="keep",EH17,0),IF(ES17="keep",FC17,0),IF(FN17="keep",FX17,0),IF(GI17="keep",GS17,0),IF(HD17="keep",HN17,0),IF(HY17="keep",II17,0),IF(IT17="keep",JD17,0)) -> 0 | AJ17: =SUM(IF(BM17="lease",BX17,0),IF(CH17="lease",CS17,0),IF(DC17="lease",DN17,0),IF(DX17="lease",EI17,0),IF(ES17="lease",FD17,0),IF(FN17="lease",FY17,0),IF(GI17="lease",GT17,0),IF(HD17="lease",HO17,0),IF(HY17="lease",IJ17,0),IF(IT17="lease",JE17,0)) -> 0 | AK17: =SUM(IF(BM17="keep",BX17,0),IF(CH17="keep",CS17,0),IF(DC17="keep",DN17,0),IF(DX17="keep",EI17,0),IF(ES17="keep",FD17,0),IF(FN17="keep",FY17,0),IF(GI17="keep",GT17,0),IF(HD17="keep",HO17,0),IF(HY17="keep",IJ17,0),IF(IT17="keep",JE17,0)) -> 0 | AL17: =R17-S16 -> -2.220446e-16 | AM17: =T17-U16 -> 0 | AN17: =AN16 -> 1 | AO17: =AO16+AH17 -> 0.057078183 | AP17: =AP16+AL17 -> -2.220446e-16 | AQ17: =AN17+AO17+AP17 -> 1.0570782 | AR17: =S17-AQ17 -> 0 | AS17: =AS16 -> 0 | AT17: =AT16+AI17 -> 0 | AU17: =AU16+AM17 -> 0 | AV17: =AS17+AT17+AU17 -> 0 | AW17: =U17-AV17 -> 0 | AX17: 1.068022 | AY17: 1.0570782 | AZ17: =S17-AY17 -> 0 | BA17: 0 | BB17: 0 | BC17: =U17-BB17 -> 0 | BD17: =SUM(IF(BL17="direct",CE17,0),IF(CG17="direct",CZ17,0),IF(DB17="direct",DU17,0),IF(DW17="direct",EP17,0),IF(ER17="direct",FK17,0),IF(FM17="direct",GF17,0),IF(GH17="direct",HA17,0),IF(HC17="direct",HV17,0),IF(HX17="direct",IQ17,0),IF(IS17="direct",JL17,0)) -> -0.0068607492 | BE17: =SUM(IF(BL17="treasury",CE17,0),IF(CG17="treasury",CZ17,0),IF(DB17="treasury",DU17,0),IF(DW17="treasury",EP17,0),IF(ER17="treasury",FK17,0),IF(FM17="treasury",GF17,0),IF(GH17="treasury",HA17,0),IF(HC17="treasury",HV17,0),IF(HX17="treasury",IQ17,0),IF(IS17="treasury",JL17,0)) -> 5.2686013e-05 | BF17: =SUM(IF(BL17="future",CE17,0),IF(CG17="future",CZ17,0),IF(DB17="future",DU17,0),IF(DW17="future",EP17,0),IF(ER17="future",FK17,0),IF(FM17="future",GF17,0),IF(GH17="future",HA17,0),IF(HC17="future",HV17,0),IF(HX17="future",IQ17,0),IF(IS17="future",JL17,0)) -> -0.0034387259 | BG17: =SUM(IF(BL17="cash",CE17,0),IF(CG17="cash",CZ17,0),IF(DB17="cash",DU17,0),IF(DW17="cash",EP17,0),IF(ER17="cash",FK17,0),IF(FM17="cash",GF17,0),IF(GH17="cash",HA17,0),IF(HC17="cash",HV17,0),IF(HX17="cash",IQ17,0),IF(IS17="cash",JL17,0)) -> 0 | BH17: =SUM(BD17:BG17) -> -0.010246789 | BI17: =G17-BH17 -> 1.7347235e-18 | BJ17: =COUNTA(BK17,CF17,DA17,DV17,EQ17,FL17,GG17,HB17,HW17,IR17) -> 6 | BK17: Direct commodity holding | BL17: direct | BM17: lease | BN17: long | BP17: 2.002 | BQ17: 1.982 | BR17: 0.36612053 | BS17: 0.68629046 | BT17: 0.73297329 | BU17: 0.73297329 | BV17: 0.72565088 | BW17: -0.0073274309 | BX17: 5.020365e-06 | BY17: 2.002 | BZ17: 1.982 | CE17: =IFERROR(BW17/F17,0) -> -0.0068607492 | CF17: Treasury collateral | CG17: treasury | CH17: lease | CI17: long | CK17: 100.33593 | CL17: 100.35279 | CM17: 0.0033392691 | CN17: 0.31370954 | CO17: 0.33504868 | CP17: 0.33504868 | CQ17: 0.33510495 | CR17: 5.626982e-05 | CS17: 4.5109587e-17 | CT17: 2.002 | CU17: 1.982 | CY17: 64 | CZ17: =IFERROR(CR17/F17,0) -> 5.2686013e-05 | DA17: SI69H | DB17: future | DC17: lease | DD17: long | DE17: regular | DF17: 2.007 | DG17: 1.985 | DH17: 0.16690626 | DI17: 0.31364604 | DJ17: 0.33498087 | DK17: 0 | DL17: 0 | DM17: -0.0036719378 | DN17: 0.0036719378 | DO17: 2.002 | DP17: 1.982 | DQ17: 0.0024975025 | DR17: 0.0613 | DS17: 0.047056431 | DT17: 64 | DU17: =IFERROR(DM17/F17,0) -> -0.0034380732 | DV17: SI69K | DW17: future | DX17: lease | DY17: long | DZ17: regular | EA17: 2.043 | EB17: 2.022 | EC17: 3.3194619e-05 | ED17: 6.3497389e-05 | EE17: 6.7816607e-05 | EF17: 0 | EG17: 0 | EH17: -6.9708701e-07 | EI17: 6.9708701e-07 | EJ17: 2.002 | EK17: 1.982 | EL17: 0.02047952 | EM17: 0.061761538 | EN17: 0.0024359434 | EO17: 126 | EP17: =IFERROR(EH17/F17,0) -> -6.5268976e-07 | EQ17: Lease cash / margin / financing | ER17: cash | ES17: lease | ET17: cash | EV17: 1 | EW17: 1 | EX17: -2.220446e-16 | EZ17: -2.220446e-16 | FA17: -2.220446e-16 | FB17: -0.0036776552 | FC17: 0 | FD17: -0.0036776552 | FE17: 2.002 | FF17: 1.982 | FK17: =IFERROR(FC17/F17,0) -> 0 | FL17: Keep cash / margin / financing | FM17: cash | FN17: keep | FO17: cash | FQ17: 1 | FR17: 1 | FS17: 0 | FU17: 0 | FV17: 0 | FW17: 0 | FX17: 0 | FY17: 0 | FZ17: 2.002 | GA17: 1.982 | GF17: =IFERROR(FX17/F17,0) -> 0
A18: 25226 | B18: 25227 | C18: =B18-A18 -> 1 | D18: 25226 | E18: positive | F18: 1.0570782 | G18: 0.0062744164 | H18: =SUM(CE18,CZ18,DU18,EP18,FK18,GF18,HA18,HV18,IQ18,JL18) -> 0.0062744164 | I18: =G18-H18 -> 8.6736174e-19 | J18: =F18*(1+H18) -> 1.0637107 | K18: 1.0637107 | L18: =K18-J18 -> 0 | M18: 1.982 | N18: 1.988 | O18: =M18/$M$3 -> 1.0122574 | P18: =N18/$M$3 -> 1.0153218 | Q18: =IFERROR(N18/M18-1,0) -> 0.0030272452 | R18: =SUM(IF(BM18="lease",BU18,0),IF(CH18="lease",CP18,0),IF(DC18="lease",DK18,0),IF(DX18="lease",EF18,0),IF(ES18="lease",FA18,0),IF(FN18="lease",FV18,0),IF(GI18="lease",GQ18,0),IF(HD18="lease",HL18,0),IF(HY18="lease",IG18,0),IF(IT18="lease",JB18,0)) -> 1.0570782 | S18: =SUM(IF(BM18="lease",BV18,0),IF(CH18="lease",CQ18,0),IF(DC18="lease",DL18,0),IF(DX18="lease",EG18,0),IF(ES18="lease",FB18,0),IF(FN18="lease",FW18,0),IF(GI18="lease",GR18,0),IF(HD18="lease",HM18,0),IF(HY18="lease",IH18,0),IF(IT18="lease",JC18,0)) -> 1.0637107 | T18: =SUM(IF(BM18="keep",BU18,0),IF(CH18="keep",CP18,0),IF(DC18="keep",DK18,0),IF(DX18="keep",EF18,0),IF(ES18="keep",FA18,0),IF(FN18="keep",FV18,0),IF(GI18="keep",GQ18,0),IF(HD18="keep",HL18,0),IF(HY18="keep",IG18,0),IF(IT18="keep",JB18,0)) -> 0 | U18: =SUM(IF(BM18="keep",BV18,0),IF(CH18="keep",CQ18,0),IF(DC18="keep",DL18,0),IF(DX18="keep",EG18,0),IF(ES18="keep",FB18,0),IF(FN18="keep",FW18,0),IF(GI18="keep",GR18,0),IF(HD18="keep",HM18,0),IF(HY18="keep",IH18,0),IF(IT18="keep",JC18,0)) -> 0 | V18: =R18/O18 -> 1.044278 | W18: =S18/P18 -> 1.0476588 | X18: =T18/O18 -> 0 | Y18: =U18/P18 -> 0 | Z18: =V18+X18 -> 1.044278 | AA18: =IFERROR(W18/V18-1,0) -> 0.0032373709 | AB18: =IFERROR((W18-V18)/Z18,0) -> 0.0032373709 | AC18: =IFERROR(Y18/X18-1,0) -> 0 | AD18: =IFERROR((Y18-X18)/Z18,0) -> 0 | AE18: =AB18+AD18 -> 0.0032373709 | AF18: =(1+Q18)*(1+AE18)-1 -> 0.0062744164 | AG18: =G18-AF18 -> -2.4633073e-16 | AH18: =SUM(IF(BM18="lease",BW18,0),IF(CH18="lease",CR18,0),IF(DC18="lease",DM18,0),IF(DX18="lease",EH18,0),IF(ES18="lease",FC18,0),IF(FN18="lease",FX18,0),IF(GI18="lease",GS18,0),IF(HD18="lease",HN18,0),IF(HY18="lease",II18,0),IF(IT18="lease",JD18,0)) -> 0.0066325487 | AI18: =SUM(IF(BM18="keep",BW18,0),IF(CH18="keep",CR18,0),IF(DC18="keep",DM18,0),IF(DX18="keep",EH18,0),IF(ES18="keep",FC18,0),IF(FN18="keep",FX18,0),IF(GI18="keep",GS18,0),IF(HD18="keep",HN18,0),IF(HY18="keep",II18,0),IF(IT18="keep",JD18,0)) -> 0 | AJ18: =SUM(IF(BM18="lease",BX18,0),IF(CH18="lease",CS18,0),IF(DC18="lease",DN18,0),IF(DX18="lease",EI18,0),IF(ES18="lease",FD18,0),IF(FN18="lease",FY18,0),IF(GI18="lease",GT18,0),IF(HD18="lease",HO18,0),IF(HY18="lease",IJ18,0),IF(IT18="lease",JE18,0)) -> 0 | AK18: =SUM(IF(BM18="keep",BX18,0),IF(CH18="keep",CS18,0),IF(DC18="keep",DN18,0),IF(DX18="keep",EI18,0),IF(ES18="keep",FD18,0),IF(FN18="keep",FY18,0),IF(GI18="keep",GT18,0),IF(HD18="keep",HO18,0),IF(HY18="keep",IJ18,0),IF(IT18="keep",JE18,0)) -> 0 | AL18: =R18-S17 -> 0 | AM18: =T18-U17 -> 0 | AN18: =AN17 -> 1 | AO18: =AO17+AH18 -> 0.063710732 | AP18: =AP17+AL18 -> -2.220446e-16 | AQ18: =AN18+AO18+AP18 -> 1.0637107 | AR18: =S18-AQ18 -> 2.220446e-16 | AS18: =AS17 -> 0 | AT18: =AT17+AI18 -> 0 | AU18: =AU17+AM18 -> 0 | AV18: =AS18+AT18+AU18 -> 0 | AW18: =U18-AV18 -> 0 | AX18: 1.0570782 | AY18: 1.0637107 | AZ18: =S18-AY18 -> 2.220446e-16 | BA18: 0 | BB18: 0 | BC18: =U18-BB18 -> 0 | BD18: =SUM(IF(BL18="direct",CE18,0),IF(CG18="direct",CZ18,0),IF(DB18="direct",DU18,0),IF(DW18="direct",EP18,0),IF(ER18="direct",FK18,0),IF(FM18="direct",GF18,0),IF(GH18="direct",HA18,0),IF(HC18="direct",HV18,0),IF(HX18="direct",IQ18,0),IF(IS18="direct",JL18,0)) -> 0.0019566004 | BE18: =SUM(IF(BL18="treasury",CE18,0),IF(CG18="treasury",CZ18,0),IF(DB18="treasury",DU18,0),IF(DW18="treasury",EP18,0),IF(ER18="treasury",FK18,0),IF(FM18="treasury",GF18,0),IF(GH18="treasury",HA18,0),IF(HC18="treasury",HV18,0),IF(HX18="treasury",IQ18,0),IF(IS18="treasury",JL18,0)) -> 5.9440455e-05 | BF18: =SUM(IF(BL18="future",CE18,0),IF(CG18="future",CZ18,0),IF(DB18="future",DU18,0),IF(DW18="future",EP18,0),IF(ER18="future",FK18,0),IF(FM18="future",GF18,0),IF(GH18="future",HA18,0),IF(HC18="future",HV18,0),IF(HX18="future",IQ18,0),IF(IS18="future",JL18,0)) -> 0.0042583756 | BG18: =SUM(IF(BL18="cash",CE18,0),IF(CG18="cash",CZ18,0),IF(DB18="cash",DU18,0),IF(DW18="cash",EP18,0),IF(ER18="cash",FK18,0),IF(FM18="cash",GF18,0),IF(GH18="cash",HA18,0),IF(HC18="cash",HV18,0),IF(HX18="cash",IQ18,0),IF(IS18="cash",JL18,0)) -> 0 | BH18: =SUM(BD18:BG18) -> 0.0062744164 | BI18: =G18-BH18 -> 0 | BJ18: =COUNTA(BK18,CF18,DA18,DV18,EQ18,FL18,GG18,HB18,HW18,IR18) -> 6 | BK18: Direct commodity holding | BL18: direct | BM18: lease | BN18: long | BP18: 1.982 | BQ18: 1.988 | BR18: 0.34549497 | BS18: 0.64779601 | BT18: 0.68477102 | BU18: 0.68477102 | BV18: 0.68684399 | BW18: 0.0020682796 | BX18: 4.6902125e-06 | BY18: 1.982 | BZ18: 1.988 | CE18: =IFERROR(BW18/F18,0) -> 0.0019566004 | CF18: Treasury collateral | CG18: treasury | CH18: lease | CI18: long | CK18: 100.35279 | CL18: 100.36972 | CM18: 0.0037099833 | CN18: 0.35220399 | CO18: 0.37230716 | CP18: 0.37230716 | CQ18: 0.37236999 | CR18: 6.2833208e-05 | CS18: 3.4084606e-17 | CT18: 1.982 | CU18: 1.988 | CY18: 63 | CZ18: =IFERROR(CR18/F18,0) -> 5.9440455e-05 | DA18: SI69H | DB18: future | DC18: lease | DD18: long | DE18: regular | DF18: 1.985 | DG18: 2.009 | DH18: 0.1875356 | DI18: 0.35215764 | DJ18: 0.37225816 | DK18: 0 | DL18: 0 | DM18: 0.0045008543 | DN18: -0.0045008543 | DO18: 1.982 | DP18: 1.988 | DQ18: 0.0015136226 | DR18: 0.0616 | DS18: 0.052830599 | DT18: 63 | DU18: =IFERROR(DM18/F18,0) -> 0.0042578254 | DV18: SI69K | DW18: future | DX18: lease | DY18: long | DZ18: regular | EA18: 2.022 | EB18: 2.046 | EC18: 2.423219e-05 | ED18: 4.6351812e-05 | EE18: 4.8997489e-05 | EF18: 0 | EG18: 0 | EH18: 5.8157257e-07 | EI18: -5.8157257e-07 | EJ18: 1.982 | EK18: 1.988 | EL18: 0.020181635 | EM18: 0.062085714 | EN18: 0.0031553409 | EO18: 125 | EP18: =IFERROR(EH18/F18,0) -> 5.5016987e-07 | EQ18: Lease cash / margin / financing | ER18: cash | ES18: lease | ET18: cash | EV18: 1 | EW18: 1 | EX18: -2.220446e-16 | EZ18: -2.220446e-16 | FA18: -2.220446e-16 | FB18: 0.0044967457 | FC18: 0 | FD18: 0.0044967457 | FE18: 1.982 | FF18: 1.988 | FK18: =IFERROR(FC18/F18,0) -> 0 | FL18: Keep cash / margin / financing | FM18: cash | FN18: keep | FO18: cash | FQ18: 1 | FR18: 1 | FS18: 0 | FU18: 0 | FV18: 0 | FW18: 0 | FX18: 0 | FY18: 0 | FZ18: 1.982 | GA18: 1.988 | GF18: =IFERROR(FX18/F18,0) -> 0
A19: 25227 | B19: 25230 | C19: =B19-A19 -> 3 | D19: 25227 | E19: neutral | F19: 1.0637107 | G19: 0.0055126512 | H19: =SUM(CE19,CZ19,DU19,EP19,FK19,GF19,HA19,HV19,IQ19,JL19) -> 0.0055126512 | I19: =G19-H19 -> 0 | J19: =F19*(1+H19) -> 1.0695746 | K19: 1.0695746 | L19: =K19-J19 -> 0 | M19: 1.988 | N19: 1.999 | O19: =M19/$M$3 -> 1.0153218 | P19: =N19/$M$3 -> 1.0209397 | Q19: =IFERROR(N19/M19-1,0) -> 0.0055331992 | R19: =SUM(IF(BM19="lease",BU19,0),IF(CH19="lease",CP19,0),IF(DC19="lease",DK19,0),IF(DX19="lease",EF19,0),IF(ES19="lease",FA19,0),IF(FN19="lease",FV19,0),IF(GI19="lease",GQ19,0),IF(HD19="lease",HL19,0),IF(HY19="lease",IG19,0),IF(IT19="lease",JB19,0)) -> 1.0637107 | S19: =SUM(IF(BM19="lease",BV19,0),IF(CH19="lease",CQ19,0),IF(DC19="lease",DL19,0),IF(DX19="lease",EG19,0),IF(ES19="lease",FB19,0),IF(FN19="lease",FW19,0),IF(GI19="lease",GR19,0),IF(HD19="lease",HM19,0),IF(HY19="lease",IH19,0),IF(IT19="lease",JC19,0)) -> 1.0695746 | T19: =SUM(IF(BM19="keep",BU19,0),IF(CH19="keep",CP19,0),IF(DC19="keep",DK19,0),IF(DX19="keep",EF19,0),IF(ES19="keep",FA19,0),IF(FN19="keep",FV19,0),IF(GI19="keep",GQ19,0),IF(HD19="keep",HL19,0),IF(HY19="keep",IG19,0),IF(IT19="keep",JB19,0)) -> 0 | U19: =SUM(IF(BM19="keep",BV19,0),IF(CH19="keep",CQ19,0),IF(DC19="keep",DL19,0),IF(DX19="keep",EG19,0),IF(ES19="keep",FB19,0),IF(FN19="keep",FW19,0),IF(GI19="keep",GR19,0),IF(HD19="keep",HM19,0),IF(HY19="keep",IH19,0),IF(IT19="keep",JC19,0)) -> 0 | V19: =R19/O19 -> 1.0476588 | W19: =S19/P19 -> 1.0476374 | X19: =T19/O19 -> 0 | Y19: =U19/P19 -> 0 | Z19: =V19+X19 -> 1.0476588 | AA19: =IFERROR(W19/V19-1,0) -> -2.0434875e-05 | AB19: =IFERROR((W19-V19)/Z19,0) -> -2.0434875e-05 | AC19: =IFERROR(Y19/X19-1,0) -> 0 | AD19: =IFERROR((Y19-X19)/Z19,0) -> 0 | AE19: =AB19+AD19 -> -2.0434875e-05 | AF19: =(1+Q19)*(1+AE19)-1 -> 0.0055126512 | AG19: =G19-AF19 -> 8.3266727e-17 | AH19: =SUM(IF(BM19="lease",BW19,0),IF(CH19="lease",CR19,0),IF(DC19="lease",DM19,0),IF(DX19="lease",EH19,0),IF(ES19="lease",FC19,0),IF(FN19="lease",FX19,0),IF(GI19="lease",GS19,0),IF(HD19="lease",HN19,0),IF(HY19="lease",II19,0),IF(IT19="lease",JD19,0)) -> 0.0058638663 | AI19: =SUM(IF(BM19="keep",BW19,0),IF(CH19="keep",CR19,0),IF(DC19="keep",DM19,0),IF(DX19="keep",EH19,0),IF(ES19="keep",FC19,0),IF(FN19="keep",FX19,0),IF(GI19="keep",GS19,0),IF(HD19="keep",HN19,0),IF(HY19="keep",II19,0),IF(IT19="keep",JD19,0)) -> 0 | AJ19: =SUM(IF(BM19="lease",BX19,0),IF(CH19="lease",CS19,0),IF(DC19="lease",DN19,0),IF(DX19="lease",EI19,0),IF(ES19="lease",FD19,0),IF(FN19="lease",FY19,0),IF(GI19="lease",GT19,0),IF(HD19="lease",HO19,0),IF(HY19="lease",IJ19,0),IF(IT19="lease",JE19,0)) -> 0 | AK19: =SUM(IF(BM19="keep",BX19,0),IF(CH19="keep",CS19,0),IF(DC19="keep",DN19,0),IF(DX19="keep",EI19,0),IF(ES19="keep",FD19,0),IF(FN19="keep",FY19,0),IF(GI19="keep",GT19,0),IF(HD19="keep",HO19,0),IF(HY19="keep",IJ19,0),IF(IT19="keep",JE19,0)) -> 0 | AL19: =R19-S18 -> -2.220446e-16 | AM19: =T19-U18 -> 0 | AN19: =AN18 -> 1 | AO19: =AO18+AH19 -> 0.069574598 | AP19: =AP18+AL19 -> -4.4408921e-16 | AQ19: =AN19+AO19+AP19 -> 1.0695746 | AR19: =S19-AQ19 -> 2.220446e-16 | AS19: =AS18 -> 0 | AT19: =AT18+AI19 -> 0 | AU19: =AU18+AM19 -> 0 | AV19: =AS19+AT19+AU19 -> 0 | AW19: =U19-AV19 -> 0 | AX19: 1.0637107 | AY19: 1.0695746 | AZ19: =S19-AY19 -> 0 | BA19: 0 | BB19: 0 | BC19: =U19-BB19 -> 0 | BD19: =SUM(IF(BL19="direct",CE19,0),IF(CG19="direct",CZ19,0),IF(DB19="direct",DU19,0),IF(DW19="direct",EP19,0),IF(ER19="direct",FK19,0),IF(FM19="direct",GF19,0),IF(GH19="direct",HA19,0),IF(HC19="direct",HV19,0),IF(HX19="direct",IQ19,0),IF(IS19="direct",JL19,0)) -> 0.0055126512 | BE19: =SUM(IF(BL19="treasury",CE19,0),IF(CG19="treasury",CZ19,0),IF(DB19="treasury",DU19,0),IF(DW19="treasury",EP19,0),IF(ER19="treasury",FK19,0),IF(FM19="treasury",GF19,0),IF(GH19="treasury",HA19,0),IF(HC19="treasury",HV19,0),IF(HX19="treasury",IQ19,0),IF(IS19="treasury",JL19,0)) -> 0 | BF19: =SUM(IF(BL19="future",CE19,0),IF(CG19="future",CZ19,0),IF(DB19="future",DU19,0),IF(DW19="future",EP19,0),IF(ER19="future",FK19,0),IF(FM19="future",GF19,0),IF(GH19="future",HA19,0),IF(HC19="future",HV19,0),IF(HX19="future",IQ19,0),IF(IS19="future",JL19,0)) -> 0 | BG19: =SUM(IF(BL19="cash",CE19,0),IF(CG19="cash",CZ19,0),IF(DB19="cash",DU19,0),IF(DW19="cash",EP19,0),IF(ER19="cash",FK19,0),IF(FM19="cash",GF19,0),IF(GH19="cash",HA19,0),IF(HC19="cash",HV19,0),IF(HX19="cash",IQ19,0),IF(IS19="cash",JL19,0)) -> 0 | BH19: =SUM(BD19:BG19) -> 0.0055126512 | BI19: =G19-BH19 -> 0 | BJ19: =COUNTA(BK19,CF19,DA19,DV19,EQ19,FL19,GG19,HB19,HW19,IR19) -> 3 | BK19: Direct commodity holding | BL19: direct | BM19: lease | BN19: long | BP19: 1.988 | BQ19: 1.999 | BR19: 0.53506576 | BS19: 1 | BT19: 1.0637107 | BU19: 1.0637107 | BV19: 1.0695965 | BW19: 0.0058638663 | BX19: 2.185707e-05 | BY19: 1.988 | BZ19: 1.999 | CE19: =IFERROR(BW19/F19,0) -> 0.0055126512 | CF19: Lease cash / margin / financing | CG19: cash | CH19: lease | CI19: cash | CK19: 1 | CL19: 1 | CM19: -2.220446e-16 | CO19: -2.220446e-16 | CP19: -2.220446e-16 | CQ19: -2.185707e-05 | CR19: 0 | CS19: -2.185707e-05 | CT19: 1.988 | CU19: 1.999 | CZ19: =IFERROR(CR19/F19,0) -> 0 | DA19: Keep cash / margin / financing | DB19: cash | DC19: keep | DD19: cash | DF19: 1 | DG19: 1 | DH19: 0 | DJ19: 0 | DK19: 0 | DL19: 0 | DM19: 0 | DN19: 0 | DO19: 1.988 | DP19: 1.999 | DU19: =IFERROR(DM19/F19,0) -> 0
A20: 25230 | B20: 25231 | C20: =B20-A20 -> 1 | D20: 25230 | E20: positive | F20: 1.0695746 | G20: -0.005759813 | H20: =SUM(CE20,CZ20,DU20,EP20,FK20,GF20,HA20,HV20,IQ20,JL20) -> -0.005759813 | I20: =G20-H20 -> 0 | J20: =F20*(1+H20) -> 1.063414 | K20: 1.063414 | L20: =K20-J20 -> 0 | M20: 1.999 | N20: 1.987 | O20: =M20/$M$3 -> 1.0209397 | P20: =N20/$M$3 -> 1.014811 | Q20: =IFERROR(N20/M20-1,0) -> -0.0060030015 | R20: =SUM(IF(BM20="lease",BU20,0),IF(CH20="lease",CP20,0),IF(DC20="lease",DK20,0),IF(DX20="lease",EF20,0),IF(ES20="lease",FA20,0),IF(FN20="lease",FV20,0),IF(GI20="lease",GQ20,0),IF(HD20="lease",HL20,0),IF(HY20="lease",IG20,0),IF(IT20="lease",JB20,0)) -> 1.0695746 | S20: =SUM(IF(BM20="lease",BV20,0),IF(CH20="lease",CQ20,0),IF(DC20="lease",DL20,0),IF(DX20="lease",EG20,0),IF(ES20="lease",FB20,0),IF(FN20="lease",FW20,0),IF(GI20="lease",GR20,0),IF(HD20="lease",HM20,0),IF(HY20="lease",IH20,0),IF(IT20="lease",JC20,0)) -> 1.063414 | T20: =SUM(IF(BM20="keep",BU20,0),IF(CH20="keep",CP20,0),IF(DC20="keep",DK20,0),IF(DX20="keep",EF20,0),IF(ES20="keep",FA20,0),IF(FN20="keep",FV20,0),IF(GI20="keep",GQ20,0),IF(HD20="keep",HL20,0),IF(HY20="keep",IG20,0),IF(IT20="keep",JB20,0)) -> 0 | U20: =SUM(IF(BM20="keep",BV20,0),IF(CH20="keep",CQ20,0),IF(DC20="keep",DL20,0),IF(DX20="keep",EG20,0),IF(ES20="keep",FB20,0),IF(FN20="keep",FW20,0),IF(GI20="keep",GR20,0),IF(HD20="keep",HM20,0),IF(HY20="keep",IH20,0),IF(IT20="keep",JC20,0)) -> 0 | V20: =R20/O20 -> 1.0476374 | W20: =S20/P20 -> 1.0478937 | X20: =T20/O20 -> 0 | Y20: =U20/P20 -> 0 | Z20: =V20+X20 -> 1.0476374 | AA20: =IFERROR(W20/V20-1,0) -> 0.0002446572 | AB20: =IFERROR((W20-V20)/Z20,0) -> 0.0002446572 | AC20: =IFERROR(Y20/X20-1,0) -> 0 | AD20: =IFERROR((Y20-X20)/Z20,0) -> 0 | AE20: =AB20+AD20 -> 0.0002446572 | AF20: =(1+Q20)*(1+AE20)-1 -> -0.005759813 | AG20: =G20-AF20 -> -1.9081958e-17 | AH20: =SUM(IF(BM20="lease",BW20,0),IF(CH20="lease",CR20,0),IF(DC20="lease",DM20,0),IF(DX20="lease",EH20,0),IF(ES20="lease",FC20,0),IF(FN20="lease",FX20,0),IF(GI20="lease",GS20,0),IF(HD20="lease",HN20,0),IF(HY20="lease",II20,0),IF(IT20="lease",JD20,0)) -> -0.0061605496 | AI20: =SUM(IF(BM20="keep",BW20,0),IF(CH20="keep",CR20,0),IF(DC20="keep",DM20,0),IF(DX20="keep",EH20,0),IF(ES20="keep",FC20,0),IF(FN20="keep",FX20,0),IF(GI20="keep",GS20,0),IF(HD20="keep",HN20,0),IF(HY20="keep",II20,0),IF(IT20="keep",JD20,0)) -> 0 | AJ20: =SUM(IF(BM20="lease",BX20,0),IF(CH20="lease",CS20,0),IF(DC20="lease",DN20,0),IF(DX20="lease",EI20,0),IF(ES20="lease",FD20,0),IF(FN20="lease",FY20,0),IF(GI20="lease",GT20,0),IF(HD20="lease",HO20,0),IF(HY20="lease",IJ20,0),IF(IT20="lease",JE20,0)) -> 0 | AK20: =SUM(IF(BM20="keep",BX20,0),IF(CH20="keep",CS20,0),IF(DC20="keep",DN20,0),IF(DX20="keep",EI20,0),IF(ES20="keep",FD20,0),IF(FN20="keep",FY20,0),IF(GI20="keep",GT20,0),IF(HD20="keep",HO20,0),IF(HY20="keep",IJ20,0),IF(IT20="keep",JE20,0)) -> 0 | AL20: =R20-S19 -> 0 | AM20: =T20-U19 -> 0 | AN20: =AN19 -> 1 | AO20: =AO19+AH20 -> 0.063414048 | AP20: =AP19+AL20 -> -4.4408921e-16 | AQ20: =AN20+AO20+AP20 -> 1.063414 | AR20: =S20-AQ20 -> 2.220446e-16 | AS20: =AS19 -> 0 | AT20: =AT19+AI20 -> 0 | AU20: =AU19+AM20 -> 0 | AV20: =AS20+AT20+AU20 -> 0 | AW20: =U20-AV20 -> 0 | AX20: 1.0695746 | AY20: 1.063414 | AZ20: =S20-AY20 -> 0 | BA20: 0 | BB20: 0 | BC20: =U20-BB20 -> 0 | BD20: =SUM(IF(BL20="direct",CE20,0),IF(CG20="direct",CZ20,0),IF(DB20="direct",DU20,0),IF(DW20="direct",EP20,0),IF(ER20="direct",FK20,0),IF(FM20="direct",GF20,0),IF(GH20="direct",HA20,0),IF(HC20="direct",HV20,0),IF(HX20="direct",IQ20,0),IF(IS20="direct",JL20,0)) -> -0.003801813 | BE20: =SUM(IF(BL20="treasury",CE20,0),IF(CG20="treasury",CZ20,0),IF(DB20="treasury",DU20,0),IF(DW20="treasury",EP20,0),IF(ER20="treasury",FK20,0),IF(FM20="treasury",GF20,0),IF(GH20="treasury",HA20,0),IF(HC20="treasury",HV20,0),IF(HX20="treasury",IQ20,0),IF(IS20="treasury",JL20,0)) -> 6.1703589e-05 | BF20: =SUM(IF(BL20="future",CE20,0),IF(CG20="future",CZ20,0),IF(DB20="future",DU20,0),IF(DW20="future",EP20,0),IF(ER20="future",FK20,0),IF(FM20="future",GF20,0),IF(GH20="future",HA20,0),IF(HC20="future",HV20,0),IF(HX20="future",IQ20,0),IF(IS20="future",JL20,0)) -> -0.0020197036 | BG20: =SUM(IF(BL20="cash",CE20,0),IF(CG20="cash",CZ20,0),IF(DB20="cash",DU20,0),IF(DW20="cash",EP20,0),IF(ER20="cash",FK20,0),IF(FM20="cash",GF20,0),IF(GH20="cash",HA20,0),IF(HC20="cash",HV20,0),IF(HX20="cash",IQ20,0),IF(IS20="cash",JL20,0)) -> 0 | BH20: =SUM(BD20:BG20) -> -0.005759813 | BI20: =G20-BH20 -> 0 | BJ20: =COUNTA(BK20,CF20,DA20,DV20,EQ20,FL20,GG20,HB20,HW20,IR20) -> 6 | BK20: Direct commodity holding | BL20: direct | BM20: lease | BN20: long | BP20: 1.999 | BQ20: 1.987 | BR20: 0.33847403 | BS20: 0.6325969 | BT20: 0.67660958 | BU20: 0.67660958 | BV20: 0.67254789 | BW20: -0.0040663226 | BX20: 4.6343122e-06 | BY20: 1.999 | BZ20: 1.987 | CE20: =IFERROR(BW20/F20,0) -> -0.003801813 | CF20: Treasury collateral | CG20: treasury | CH20: lease | CI20: long | CK20: 100.42062 | CL20: 100.43749 | CM20: 0.0039131905 | CN20: 0.3674031 | CO20: 0.39296502 | CP20: 0.39296502 | CQ20: 0.39303102 | CR20: 6.5996591e-05 | CS20: -2.2036409e-17 | CT20: 1.999 | CU20: 1.987 | CY20: 59 | CZ20: =IFERROR(CR20/F20,0) -> 6.1703589e-05 | DA20: SI69H | DB20: future | DC20: lease | DD20: long | DE20: regular | DF20: 2.001 | DG20: 1.99 | DH20: 0.19636488 | DI20: 0.36736673 | DJ20: 0.39292612 | DK20: 0 | DL20: 0 | DM20: -0.0021600137 | DN20: 0.0021600137 | DO20: 1.999 | DP20: 1.987 | DQ20: 0.0010005003 | DR20: 0.0613 | DS20: 0.055110465 | DT20: 59 | DU20: =IFERROR(DM20/F20,0) -> -0.0020195073 | DV20: SI69K | DW20: future | DX20: lease | DY20: long | DZ20: regular | EA20: 2.038 | EB20: 2.027 | EC20: 1.9084934e-05 | ED20: 3.6365013e-05 | EE20: 3.8895095e-05 | EF20: 0 | EG20: 0 | EH20: -2.0993427e-07 | EI20: 2.0993427e-07 | EJ20: 1.999 | EK20: 1.987 | EL20: 0.019509755 | EM20: 0.061662637 | EN20: 0.0028108974 | EO20: 121 | EP20: =IFERROR(EH20/F20,0) -> -1.9627829e-07 | EQ20: Lease cash / margin / financing | ER20: cash | ES20: lease | ET20: cash | EV20: 1 | EW20: 1 | EX20: 0 | EZ20: 0 | FA20: 0 | FB20: -0.0021648579 | FC20: 0 | FD20: -0.0021648579 | FE20: 1.999 | FF20: 1.987 | FK20: =IFERROR(FC20/F20,0) -> 0 | FL20: Keep cash / margin / financing | FM20: cash | FN20: keep | FO20: cash | FQ20: 1 | FR20: 1 | FS20: 0 | FU20: 0 | FV20: 0 | FW20: 0 | FX20: 0 | FY20: 0 | FZ20: 1.999 | GA20: 1.987 | GF20: =IFERROR(FX20/F20,0) -> 0
A21: 25231 | B21: 25232 | C21: =B21-A21 -> 1 | D21: 25231 | E21: positive | F21: 1.063414 | G21: -0.0015676384 | H21: =SUM(CE21,CZ21,DU21,EP21,FK21,GF21,HA21,HV21,IQ21,JL21) -> -0.0015676384 | I21: =G21-H21 -> 0 | J21: =F21*(1+H21) -> 1.061747 | K21: 1.061747 | L21: =K21-J21 -> 0 | M21: 1.987 | N21: 1.981 | O21: =M21/$M$3 -> 1.014811 | P21: =N21/$M$3 -> 1.0117467 | Q21: =IFERROR(N21/M21-1,0) -> -0.0030196276 | R21: =SUM(IF(BM21="lease",BU21,0),IF(CH21="lease",CP21,0),IF(DC21="lease",DK21,0),IF(DX21="lease",EF21,0),IF(ES21="lease",FA21,0),IF(FN21="lease",FV21,0),IF(GI21="lease",GQ21,0),IF(HD21="lease",HL21,0),IF(HY21="lease",IG21,0),IF(IT21="lease",JB21,0)) -> 1.063414 | S21: =SUM(IF(BM21="lease",BV21,0),IF(CH21="lease",CQ21,0),IF(DC21="lease",DL21,0),IF(DX21="lease",EG21,0),IF(ES21="lease",FB21,0),IF(FN21="lease",FW21,0),IF(GI21="lease",GR21,0),IF(HD21="lease",HM21,0),IF(HY21="lease",IH21,0),IF(IT21="lease",JC21,0)) -> 1.061747 | T21: =SUM(IF(BM21="keep",BU21,0),IF(CH21="keep",CP21,0),IF(DC21="keep",DK21,0),IF(DX21="keep",EF21,0),IF(ES21="keep",FA21,0),IF(FN21="keep",FV21,0),IF(GI21="keep",GQ21,0),IF(HD21="keep",HL21,0),IF(HY21="keep",IG21,0),IF(IT21="keep",JB21,0)) -> 0 | U21: =SUM(IF(BM21="keep",BV21,0),IF(CH21="keep",CQ21,0),IF(DC21="keep",DL21,0),IF(DX21="keep",EG21,0),IF(ES21="keep",FB21,0),IF(FN21="keep",FW21,0),IF(GI21="keep",GR21,0),IF(HD21="keep",HM21,0),IF(HY21="keep",IH21,0),IF(IT21="keep",JC21,0)) -> 0 | V21: =R21/O21 -> 1.0478937 | W21: =S21/P21 -> 1.0494198 | X21: =T21/O21 -> 0 | Y21: =U21/P21 -> 0 | Z21: =V21+X21 -> 1.0478937 | AA21: =IFERROR(W21/V21-1,0) -> 0.0014563869 | AB21: =IFERROR((W21-V21)/Z21,0) -> 0.0014563869 | AC21: =IFERROR(Y21/X21-1,0) -> 0 | AD21: =IFERROR((Y21-X21)/Z21,0) -> 0 | AE21: =AB21+AD21 -> 0.0014563869 | AF21: =(1+Q21)*(1+AE21)-1 -> -0.0015676384 | AG21: =G21-AF21 -> 1.3010426e-17 | AH21: =SUM(IF(BM21="lease",BW21,0),IF(CH21="lease",CR21,0),IF(DC21="lease",DM21,0),IF(DX21="lease",EH21,0),IF(ES21="lease",FC21,0),IF(FN21="lease",FX21,0),IF(GI21="lease",GS21,0),IF(HD21="lease",HN21,0),IF(HY21="lease",II21,0),IF(IT21="lease",JD21,0)) -> -0.0016670487 | AI21: =SUM(IF(BM21="keep",BW21,0),IF(CH21="keep",CR21,0),IF(DC21="keep",DM21,0),IF(DX21="keep",EH21,0),IF(ES21="keep",FC21,0),IF(FN21="keep",FX21,0),IF(GI21="keep",GS21,0),IF(HD21="keep",HN21,0),IF(HY21="keep",II21,0),IF(IT21="keep",JD21,0)) -> 0 | AJ21: =SUM(IF(BM21="lease",BX21,0),IF(CH21="lease",CS21,0),IF(DC21="lease",DN21,0),IF(DX21="lease",EI21,0),IF(ES21="lease",FD21,0),IF(FN21="lease",FY21,0),IF(GI21="lease",GT21,0),IF(HD21="lease",HO21,0),IF(HY21="lease",IJ21,0),IF(IT21="lease",JE21,0)) -> 0 | AK21: =SUM(IF(BM21="keep",BX21,0),IF(CH21="keep",CS21,0),IF(DC21="keep",DN21,0),IF(DX21="keep",EI21,0),IF(ES21="keep",FD21,0),IF(FN21="keep",FY21,0),IF(GI21="keep",GT21,0),IF(HD21="keep",HO21,0),IF(HY21="keep",IJ21,0),IF(IT21="keep",JE21,0)) -> 0 | AL21: =R21-S20 -> 0 | AM21: =T21-U20 -> 0 | AN21: =AN20 -> 1 | AO21: =AO20+AH21 -> 0.061747 | AP21: =AP20+AL21 -> -4.4408921e-16 | AQ21: =AN21+AO21+AP21 -> 1.061747 | AR21: =S21-AQ21 -> 2.220446e-16 | AS21: =AS20 -> 0 | AT21: =AT20+AI21 -> 0 | AU21: =AU20+AM21 -> 0 | AV21: =AS21+AT21+AU21 -> 0 | AW21: =U21-AV21 -> 0 | AX21: 1.063414 | AY21: 1.061747 | AZ21: =S21-AY21 -> 0 | BA21: 0 | BB21: 0 | BC21: =U21-BB21 -> 0 | BD21: =SUM(IF(BL21="direct",CE21,0),IF(CG21="direct",CZ21,0),IF(DB21="direct",DU21,0),IF(DW21="direct",EP21,0),IF(ER21="direct",FK21,0),IF(FM21="direct",GF21,0),IF(GH21="direct",HA21,0),IF(HC21="direct",HV21,0),IF(HX21="direct",IQ21,0),IF(IS21="direct",JL21,0)) -> -0.0019753091 | BE21: =SUM(IF(BL21="treasury",CE21,0),IF(CG21="treasury",CZ21,0),IF(DB21="treasury",DU21,0),IF(DW21="treasury",EP21,0),IF(ER21="treasury",FK21,0),IF(FM21="treasury",GF21,0),IF(GH21="treasury",HA21,0),IF(HC21="treasury",HV21,0),IF(HX21="treasury",IQ21,0),IF(IS21="treasury",JL21,0)) -> 5.8616856e-05 | BF21: =SUM(IF(BL21="future",CE21,0),IF(CG21="future",CZ21,0),IF(DB21="future",DU21,0),IF(DW21="future",EP21,0),IF(ER21="future",FK21,0),IF(FM21="future",GF21,0),IF(GH21="future",HA21,0),IF(HC21="future",HV21,0),IF(HX21="future",IQ21,0),IF(IS21="future",JL21,0)) -> 0.00034905385 | BG21: =SUM(IF(BL21="cash",CE21,0),IF(CG21="cash",CZ21,0),IF(DB21="cash",DU21,0),IF(DW21="cash",EP21,0),IF(ER21="cash",FK21,0),IF(FM21="cash",GF21,0),IF(GH21="cash",HA21,0),IF(HC21="cash",HV21,0),IF(HX21="cash",IQ21,0),IF(IS21="cash",JL21,0)) -> 0 | BH21: =SUM(BD21:BG21) -> -0.0015676384 | BI21: =G21-BH21 -> 4.3368087e-19 | BJ21: =COUNTA(BK21,CF21,DA21,DV21,EQ21,FL21,GG21,HB21,HW21,IR21) -> 6 | BK21: Direct commodity holding | BL21: direct | BM21: lease | BN21: long | BP21: 1.987 | BQ21: 1.981 | BR21: 0.34930293 | BS21: 0.6526761 | BT21: 0.69406493 | BU21: 0.69406493 | BV21: 0.69196911 | BW21: -0.0021005715 | BX21: 4.7538694e-06 | BY21: 1.987 | BZ21: 1.981 | CE21: =IFERROR(BW21/F21,0) -> -0.0019753091 | CF21: Treasury collateral | CG21: treasury | CH21: lease | CI21: long | CK21: 100.43749 | CL21: 100.45444 | CM21: 0.003677403 | CN21: 0.3473239 | CO21: 0.36934912 | CP21: 0.36934912 | CQ21: 0.36941145 | CR21: 6.2333988e-05 | CS21: -5.9766645e-18 | CT21: 1.987 | CU21: 1.981 | CY21: 58 | CZ21: =IFERROR(CR21/F21,0) -> 5.8616856e-05 | DA21: SI69H | DB21: future | DC21: lease | DD21: long | DE21: regular | DF21: 1.99 | DG21: 1.992 | DH21: 0.18558649 | DI21: 0.34729382 | DJ21: 0.36931712 | DK21: 0 | DL21: 0 | DM21: 0.00037117299 | DN21: -0.00037117299 | DO21: 1.987 | DP21: 1.981 | DQ21: 0.0015098138 | DR21: 0.0616 | DS21: 0.052098586 | DT21: 58 | DU21: =IFERROR(DM21/F21,0) -> 0.00034903901 | DV21: SI69K | DW21: future | DX21: lease | DY21: long | DZ21: regular | EA21: 2.027 | EB21: 2.028 | EC21: 1.5785005e-05 | ED21: 3.0088191e-05 | EE21: 3.1996205e-05 | EF21: 0 | EG21: 0 | EH21: 1.5785005e-08 | EI21: -1.5785005e-08 | EJ21: 1.987 | EK21: 1.981 | EL21: 0.020130851 | EM21: 0.061854945 | EN21: 0.00062360803 | EO21: 120 | EP21: =IFERROR(EH21/F21,0) -> 1.4843705e-08 | EQ21: Lease cash / margin / financing | ER21: cash | ES21: lease | ET21: cash | EV21: 1 | EW21: 1 | EX21: 0 | EZ21: 0 | FA21: 0 | FB21: 0.0003664349 | FC21: 0 | FD21: 0.0003664349 | FE21: 1.987 | FF21: 1.981 | FK21: =IFERROR(FC21/F21,0) -> 0 | FL21: Keep cash / margin / financing | FM21: cash | FN21: keep | FO21: cash | FQ21: 1 | FR21: 1 | FS21: 0 | FU21: 0 | FV21: 0 | FW21: 0 | FX21: 0 | FY21: 0 | FZ21: 1.987 | GA21: 1.981 | GF21: =IFERROR(FX21/F21,0) -> 0
A22: 25232 | B22: 25233 | C22: =B22-A22 -> 1 | D22: 25232 | E22: positive | F22: 1.061747 | G22: 0.0094997646 | H22: =SUM(CE22,CZ22,DU22,EP22,FK22,GF22,HA22,HV22,IQ22,JL22) -> 0.0094997646 | I22: =G22-H22 -> 1.7347235e-18 | J22: =F22*(1+H22) -> 1.0718333 | K22: 1.0718333 | L22: =K22-J22 -> 0 | M22: 1.981 | N22: 2.001 | O22: =M22/$M$3 -> 1.0117467 | P22: =N22/$M$3 -> 1.0219612 | Q22: =IFERROR(N22/M22-1,0) -> 0.010095911 | R22: =SUM(IF(BM22="lease",BU22,0),IF(CH22="lease",CP22,0),IF(DC22="lease",DK22,0),IF(DX22="lease",EF22,0),IF(ES22="lease",FA22,0),IF(FN22="lease",FV22,0),IF(GI22="lease",GQ22,0),IF(HD22="lease",HL22,0),IF(HY22="lease",IG22,0),IF(IT22="lease",JB22,0)) -> 1.061747 | S22: =SUM(IF(BM22="lease",BV22,0),IF(CH22="lease",CQ22,0),IF(DC22="lease",DL22,0),IF(DX22="lease",EG22,0),IF(ES22="lease",FB22,0),IF(FN22="lease",FW22,0),IF(GI22="lease",GR22,0),IF(HD22="lease",HM22,0),IF(HY22="lease",IH22,0),IF(IT22="lease",JC22,0)) -> 1.0718333 | T22: =SUM(IF(BM22="keep",BU22,0),IF(CH22="keep",CP22,0),IF(DC22="keep",DK22,0),IF(DX22="keep",EF22,0),IF(ES22="keep",FA22,0),IF(FN22="keep",FV22,0),IF(GI22="keep",GQ22,0),IF(HD22="keep",HL22,0),IF(HY22="keep",IG22,0),IF(IT22="keep",JB22,0)) -> 0 | U22: =SUM(IF(BM22="keep",BV22,0),IF(CH22="keep",CQ22,0),IF(DC22="keep",DL22,0),IF(DX22="keep",EG22,0),IF(ES22="keep",FB22,0),IF(FN22="keep",FW22,0),IF(GI22="keep",GR22,0),IF(HD22="keep",HM22,0),IF(HY22="keep",IH22,0),IF(IT22="keep",JC22,0)) -> 0 | V22: =R22/O22 -> 1.0494198 | W22: =S22/P22 -> 1.0488004 | X22: =T22/O22 -> 0 | Y22: =U22/P22 -> 0 | Z22: =V22+X22 -> 1.0494198 | AA22: =IFERROR(W22/V22-1,0) -> -0.0005901881 | AB22: =IFERROR((W22-V22)/Z22,0) -> -0.0005901881 | AC22: =IFERROR(Y22/X22-1,0) -> 0 | AD22: =IFERROR((Y22-X22)/Z22,0) -> 0 | AE22: =AB22+AD22 -> -0.0005901881 | AF22: =(1+Q22)*(1+AE22)-1 -> 0.0094997646 | AG22: =G22-AF22 -> -2.0122792e-16 | AH22: =SUM(IF(BM22="lease",BW22,0),IF(CH22="lease",CR22,0),IF(DC22="lease",DM22,0),IF(DX22="lease",EH22,0),IF(ES22="lease",FC22,0),IF(FN22="lease",FX22,0),IF(GI22="lease",GS22,0),IF(HD22="lease",HN22,0),IF(HY22="lease",II22,0),IF(IT22="lease",JD22,0)) -> 0.010086347 | AI22: =SUM(IF(BM22="keep",BW22,0),IF(CH22="keep",CR22,0),IF(DC22="keep",DM22,0),IF(DX22="keep",EH22,0),IF(ES22="keep",FC22,0),IF(FN22="keep",FX22,0),IF(GI22="keep",GS22,0),IF(HD22="keep",HN22,0),IF(HY22="keep",II22,0),IF(IT22="keep",JD22,0)) -> 0 | AJ22: =SUM(IF(BM22="lease",BX22,0),IF(CH22="lease",CS22,0),IF(DC22="lease",DN22,0),IF(DX22="lease",EI22,0),IF(ES22="lease",FD22,0),IF(FN22="lease",FY22,0),IF(GI22="lease",GT22,0),IF(HD22="lease",HO22,0),IF(HY22="lease",IJ22,0),IF(IT22="lease",JE22,0)) -> 0 | AK22: =SUM(IF(BM22="keep",BX22,0),IF(CH22="keep",CS22,0),IF(DC22="keep",DN22,0),IF(DX22="keep",EI22,0),IF(ES22="keep",FD22,0),IF(FN22="keep",FY22,0),IF(GI22="keep",GT22,0),IF(HD22="keep",HO22,0),IF(HY22="keep",IJ22,0),IF(IT22="keep",JE22,0)) -> 0 | AL22: =R22-S21 -> 0 | AM22: =T22-U21 -> 0 | AN22: =AN21 -> 1 | AO22: =AO21+AH22 -> 0.071833346 | AP22: =AP21+AL22 -> -4.4408921e-16 | AQ22: =AN22+AO22+AP22 -> 1.0718333 | AR22: =S22-AQ22 -> 2.220446e-16 | AS22: =AS21 -> 0 | AT22: =AT21+AI22 -> 0 | AU22: =AU21+AM22 -> 0 | AV22: =AS22+AT22+AU22 -> 0 | AW22: =U22-AV22 -> 0 | AX22: 1.061747 | AY22: 1.0718333 | AZ22: =S22-AY22 -> 2.220446e-16 | BA22: 0 | BB22: 0 | BC22: =U22-BB22 -> 0 | BD22: =SUM(IF(BL22="direct",CE22,0),IF(CG22="direct",CZ22,0),IF(DB22="direct",DU22,0),IF(DW22="direct",EP22,0),IF(ER22="direct",FK22,0),IF(FM22="direct",GF22,0),IF(GH22="direct",HA22,0),IF(HC22="direct",HV22,0),IF(HX22="direct",IQ22,0),IF(IS22="direct",JL22,0)) -> 0.008337405 | BE22: =SUM(IF(BL22="treasury",CE22,0),IF(CG22="treasury",CZ22,0),IF(DB22="treasury",DU22,0),IF(DW22="treasury",EP22,0),IF(ER22="treasury",FK22,0),IF(FM22="treasury",GF22,0),IF(GH22="treasury",HA22,0),IF(HC22="treasury",HV22,0),IF(HX22="treasury",IQ22,0),IF(IS22="treasury",JL22,0)) -> 2.9301246e-05 | BF22: =SUM(IF(BL22="future",CE22,0),IF(CG22="future",CZ22,0),IF(DB22="future",DU22,0),IF(DW22="future",EP22,0),IF(ER22="future",FK22,0),IF(FM22="future",GF22,0),IF(GH22="future",HA22,0),IF(HC22="future",HV22,0),IF(HX22="future",IQ22,0),IF(IS22="future",JL22,0)) -> 0.0011330583 | BG22: =SUM(IF(BL22="cash",CE22,0),IF(CG22="cash",CZ22,0),IF(DB22="cash",DU22,0),IF(DW22="cash",EP22,0),IF(ER22="cash",FK22,0),IF(FM22="cash",GF22,0),IF(GH22="cash",HA22,0),IF(HC22="cash",HV22,0),IF(HX22="cash",IQ22,0),IF(IS22="cash",JL22,0)) -> 0 | BH22: =SUM(BD22:BG22) -> 0.0094997646 | BI22: =G22-BH22 -> 0 | BJ22: =COUNTA(BK22,CF22,DA22,DV22,EQ22,FL22,GG22,HB22,HW22,IR22) -> 5 | BK22: Direct commodity holding | BL22: direct | BM22: lease | BN22: long | BP22: 1.981 | BQ22: 2.001 | BR22: 0.44291122 | BS22: 0.8263806 | BT22: 0.87740713 | BU22: 0.87740713 | BV22: 0.88626535 | BW22: 0.0088522148 | BX22: 6.0096379e-06 | BY22: 1.981 | BZ22: 2.001 | CE22: =IFERROR(BW22/F22,0) -> 0.008337405 | CF22: Treasury collateral | CG22: treasury | CH22: lease | CI22: long | CK22: 100.45444 | CL22: 100.47139 | CM22: 0.0018350595 | CN22: 0.1736194 | CO22: 0.18433987 | CP22: 0.18433987 | CQ22: 0.18437098 | CR22: 3.111051e-05 | CS22: 1.3010426e-17 | CT22: 1.981 | CU22: 2.001 | CY22: 57 | CZ22: =IFERROR(CR22/F22,0) -> 2.9301246e-05 | DA22: SI69H | DB22: future | DC22: lease | DD22: long | DE22: regular | DF22: 1.992 | DG22: 2.005 | DH22: 0.092540097 | DI22: 0.1736194 | DJ22: 0.18433987 | DK22: 0 | DL22: 0 | DM22: 0.0012030213 | DN22: -0.0012030213 | DO22: 1.981 | DP22: 2.001 | DQ22: 0.0055527511 | DR22: 0.0616 | DS22: 0.026042909 | DT22: 57 | DU22: =IFERROR(DM22/F22,0) -> 0.0011330583 | DV22: Lease cash / margin / financing | DW22: cash | DX22: lease | DY22: cash | EA22: 1 | EB22: 1 | EC22: 0 | EE22: 0 | EF22: 0 | EG22: 0.0011970116 | EH22: 0 | EI22: 0.0011970116 | EJ22: 1.981 | EK22: 2.001 | EP22: =IFERROR(EH22/F22,0) -> 0 | EQ22: Keep cash / margin / financing | ER22: cash | ES22: keep | ET22: cash | EV22: 1 | EW22: 1 | EX22: 0 | EZ22: 0 | FA22: 0 | FB22: 0 | FC22: 0 | FD22: 0 | FE22: 1.981 | FF22: 2.001 | FK22: =IFERROR(FC22/F22,0) -> 0
A23: 25233 | B23: 25234 | C23: =B23-A23 -> 1 | D23: 25233 | E23: positive | F23: 1.0718333 | G23: -0.00059710349 | H23: =SUM(CE23,CZ23,DU23,EP23,FK23,GF23,HA23,HV23,IQ23,JL23) -> -0.00059710349 | I23: =G23-H23 -> 0 | J23: =F23*(1+H23) -> 1.0711934 | K23: 1.0711934 | L23: =K23-J23 -> 0 | M23: 2.001 | N23: 2.001 | O23: =M23/$M$3 -> 1.0219612 | P23: =N23/$M$3 -> 1.0219612 | Q23: =IFERROR(N23/M23-1,0) -> 0 | R23: =SUM(IF(BM23="lease",BU23,0),IF(CH23="lease",CP23,0),IF(DC23="lease",DK23,0),IF(DX23="lease",EF23,0),IF(ES23="lease",FA23,0),IF(FN23="lease",FV23,0),IF(GI23="lease",GQ23,0),IF(HD23="lease",HL23,0),IF(HY23="lease",IG23,0),IF(IT23="lease",JB23,0)) -> 1.0718333 | S23: =SUM(IF(BM23="lease",BV23,0),IF(CH23="lease",CQ23,0),IF(DC23="lease",DL23,0),IF(DX23="lease",EG23,0),IF(ES23="lease",FB23,0),IF(FN23="lease",FW23,0),IF(GI23="lease",GR23,0),IF(HD23="lease",HM23,0),IF(HY23="lease",IH23,0),IF(IT23="lease",JC23,0)) -> 1.0711934 | T23: =SUM(IF(BM23="keep",BU23,0),IF(CH23="keep",CP23,0),IF(DC23="keep",DK23,0),IF(DX23="keep",EF23,0),IF(ES23="keep",FA23,0),IF(FN23="keep",FV23,0),IF(GI23="keep",GQ23,0),IF(HD23="keep",HL23,0),IF(HY23="keep",IG23,0),IF(IT23="keep",JB23,0)) -> 0 | U23: =SUM(IF(BM23="keep",BV23,0),IF(CH23="keep",CQ23,0),IF(DC23="keep",DL23,0),IF(DX23="keep",EG23,0),IF(ES23="keep",FB23,0),IF(FN23="keep",FW23,0),IF(GI23="keep",GR23,0),IF(HD23="keep",HM23,0),IF(HY23="keep",IH23,0),IF(IT23="keep",JC23,0)) -> 0 | V23: =R23/O23 -> 1.0488004 | W23: =S23/P23 -> 1.0481742 | X23: =T23/O23 -> 0 | Y23: =U23/P23 -> 0 | Z23: =V23+X23 -> 1.0488004 | AA23: =IFERROR(W23/V23-1,0) -> -0.00059710349 | AB23: =IFERROR((W23-V23)/Z23,0) -> -0.00059710349 | AC23: =IFERROR(Y23/X23-1,0) -> 0 | AD23: =IFERROR((Y23-X23)/Z23,0) -> 0 | AE23: =AB23+AD23 -> -0.00059710349 | AF23: =(1+Q23)*(1+AE23)-1 -> -0.00059710349 | AG23: =G23-AF23 -> 1.2717691e-16 | AH23: =SUM(IF(BM23="lease",BW23,0),IF(CH23="lease",CR23,0),IF(DC23="lease",DM23,0),IF(DX23="lease",EH23,0),IF(ES23="lease",FC23,0),IF(FN23="lease",FX23,0),IF(GI23="lease",GS23,0),IF(HD23="lease",HN23,0),IF(HY23="lease",II23,0),IF(IT23="lease",JD23,0)) -> -0.00063999543 | AI23: =SUM(IF(BM23="keep",BW23,0),IF(CH23="keep",CR23,0),IF(DC23="keep",DM23,0),IF(DX23="keep",EH23,0),IF(ES23="keep",FC23,0),IF(FN23="keep",FX23,0),IF(GI23="keep",GS23,0),IF(HD23="keep",HN23,0),IF(HY23="keep",II23,0),IF(IT23="keep",JD23,0)) -> 0 | AJ23: =SUM(IF(BM23="lease",BX23,0),IF(CH23="lease",CS23,0),IF(DC23="lease",DN23,0),IF(DX23="lease",EI23,0),IF(ES23="lease",FD23,0),IF(FN23="lease",FY23,0),IF(GI23="lease",GT23,0),IF(HD23="lease",HO23,0),IF(HY23="lease",IJ23,0),IF(IT23="lease",JE23,0)) -> 0 | AK23: =SUM(IF(BM23="keep",BX23,0),IF(CH23="keep",CS23,0),IF(DC23="keep",DN23,0),IF(DX23="keep",EI23,0),IF(ES23="keep",FD23,0),IF(FN23="keep",FY23,0),IF(GI23="keep",GT23,0),IF(HD23="keep",HO23,0),IF(HY23="keep",IJ23,0),IF(IT23="keep",JE23,0)) -> 0 | AL23: =R23-S22 -> -2.220446e-16 | AM23: =T23-U22 -> 0 | AN23: =AN22 -> 1 | AO23: =AO22+AH23 -> 0.071193351 | AP23: =AP22+AL23 -> -6.6613381e-16 | AQ23: =AN23+AO23+AP23 -> 1.0711934 | AR23: =S23-AQ23 -> 2.220446e-16 | AS23: =AS22 -> 0 | AT23: =AT22+AI23 -> 0 | AU23: =AU22+AM23 -> 0 | AV23: =AS23+AT23+AU23 -> 0 | AW23: =U23-AV23 -> 0 | AX23: 1.0718333 | AY23: 1.0711934 | AZ23: =S23-AY23 -> -2.220446e-16 | BA23: 0 | BB23: 0 | BC23: =U23-BB23 -> 0 | BD23: =SUM(IF(BL23="direct",CE23,0),IF(CG23="direct",CZ23,0),IF(DB23="direct",DU23,0),IF(DW23="direct",EP23,0),IF(ER23="direct",FK23,0),IF(FM23="direct",GF23,0),IF(GH23="direct",HA23,0),IF(HC23="direct",HV23,0),IF(HX23="direct",IQ23,0),IF(IS23="direct",JL23,0)) -> -4.6269041e-06 | BE23: =SUM(IF(BL23="treasury",CE23,0),IF(CG23="treasury",CZ23,0),IF(DB23="treasury",DU23,0),IF(DW23="treasury",EP23,0),IF(ER23="treasury",FK23,0),IF(FM23="treasury",GF23,0),IF(GH23="treasury",HA23,0),IF(HC23="treasury",HV23,0),IF(HX23="treasury",IQ23,0),IF(IS23="treasury",JL23,0)) -> 5.4849103e-05 | BF23: =SUM(IF(BL23="future",CE23,0),IF(CG23="future",CZ23,0),IF(DB23="future",DU23,0),IF(DW23="future",EP23,0),IF(ER23="future",FK23,0),IF(FM23="future",GF23,0),IF(GH23="future",HA23,0),IF(HC23="future",HV23,0),IF(HX23="future",IQ23,0),IF(IS23="future",JL23,0)) -> -0.00064732569 | BG23: =SUM(IF(BL23="cash",CE23,0),IF(CG23="cash",CZ23,0),IF(DB23="cash",DU23,0),IF(DW23="cash",EP23,0),IF(ER23="cash",FK23,0),IF(FM23="cash",GF23,0),IF(GH23="cash",HA23,0),IF(HC23="cash",HV23,0),IF(HX23="cash",IQ23,0),IF(IS23="cash",JL23,0)) -> 0 | BH23: =SUM(BD23:BG23) -> -0.00059710349 | BI23: =G23-BH23 -> 0 | BJ23: =COUNTA(BK23,CF23,DA23,DV23,EQ23,FL23,GG23,HB23,HW23,IR23) -> 5 | BK23: Direct commodity holding | BL23: direct | BM23: lease | BN23: long | BP23: 2.001 | BQ23: 2.001 | BR23: 0.36184579 | BS23: 0.675528 | BT23: 0.72405343 | BU23: 0.72405343 | BV23: 0.72405343 | BW23: -4.9592701e-06 | BX23: 4.9592701e-06 | BY23: 2.001 | BZ23: 2.001 | CE23: =IFERROR(BW23/F23,0) -> -4.6269041e-06 | CF23: Treasury collateral | CG23: treasury | CH23: lease | CI23: long | CK23: 100.47139 | CL23: 100.48837 | CM23: 0.003461482 | CN23: 0.324472 | CO23: 0.34777991 | CP23: 0.34777991 | CQ23: 0.3478387 | CR23: 5.8789097e-05 | CS23: -4.499439e-17 | CT23: 2.001 | CU23: 2.001 | CY23: 56 | CZ23: =IFERROR(CR23/F23,0) -> 5.4849103e-05 | DA23: SI69H | DB23: future | DC23: lease | DD23: long | DE23: regular | DF23: 2.005 | DG23: 2.001 | DH23: 0.17345632 | DI23: 0.324472 | DJ23: 0.34777991 | DK23: 0 | DL23: 0 | DM23: -0.00069382526 | DN23: 0.00069382526 | DO23: 2.001 | DP23: 2.001 | DQ23: 0.0019990005 | DR23: 0.0617 | DS23: 0.0486708 | DT23: 56 | DU23: =IFERROR(DM23/F23,0) -> -0.00064732569 | DV23: Lease cash / margin / financing | DW23: cash | DX23: lease | DY23: cash | EA23: 1 | EB23: 1 | EC23: 0 | EE23: 0 | EF23: 0 | EG23: -0.00069878453 | EH23: 0 | EI23: -0.00069878453 | EJ23: 2.001 | EK23: 2.001 | EP23: =IFERROR(EH23/F23,0) -> 0 | EQ23: Keep cash / margin / financing | ER23: cash | ES23: keep | ET23: cash | EV23: 1 | EW23: 1 | EX23: 0 | EZ23: 0 | FA23: 0 | FB23: 0 | FC23: 0 | FD23: 0 | FE23: 2.001 | FF23: 2.001 | FK23: =IFERROR(FC23/F23,0) -> 0
A24: 25234 | B24: 25237 | C24: =B24-A24 -> 3 | D24: 25234 | E24: positive | F24: 1.0711934 | G24: -0.0053550075 | H24: =SUM(CE24,CZ24,DU24,EP24,FK24,GF24,HA24,HV24,IQ24,JL24) -> -0.0053550075 | I24: =G24-H24 -> 0 | J24: =F24*(1+H24) -> 1.0654571 | K24: 1.0654571 | L24: =K24-J24 -> 0 | M24: 2.001 | N24: 1.987 | O24: =M24/$M$3 -> 1.0219612 | P24: =N24/$M$3 -> 1.014811 | Q24: =IFERROR(N24/M24-1,0) -> -0.0069965017 | R24: =SUM(IF(BM24="lease",BU24,0),IF(CH24="lease",CP24,0),IF(DC24="lease",DK24,0),IF(DX24="lease",EF24,0),IF(ES24="lease",FA24,0),IF(FN24="lease",FV24,0),IF(GI24="lease",GQ24,0),IF(HD24="lease",HL24,0),IF(HY24="lease",IG24,0),IF(IT24="lease",JB24,0)) -> 1.0711934 | S24: =SUM(IF(BM24="lease",BV24,0),IF(CH24="lease",CQ24,0),IF(DC24="lease",DL24,0),IF(DX24="lease",EG24,0),IF(ES24="lease",FB24,0),IF(FN24="lease",FW24,0),IF(GI24="lease",GR24,0),IF(HD24="lease",HM24,0),IF(HY24="lease",IH24,0),IF(IT24="lease",JC24,0)) -> 1.0654571 | T24: =SUM(IF(BM24="keep",BU24,0),IF(CH24="keep",CP24,0),IF(DC24="keep",DK24,0),IF(DX24="keep",EF24,0),IF(ES24="keep",FA24,0),IF(FN24="keep",FV24,0),IF(GI24="keep",GQ24,0),IF(HD24="keep",HL24,0),IF(HY24="keep",IG24,0),IF(IT24="keep",JB24,0)) -> 0 | U24: =SUM(IF(BM24="keep",BV24,0),IF(CH24="keep",CQ24,0),IF(DC24="keep",DL24,0),IF(DX24="keep",EG24,0),IF(ES24="keep",FB24,0),IF(FN24="keep",FW24,0),IF(GI24="keep",GR24,0),IF(HD24="keep",HM24,0),IF(HY24="keep",IH24,0),IF(IT24="keep",JC24,0)) -> 0 | V24: =R24/O24 -> 1.0481742 | W24: =S24/P24 -> 1.0499069 | X24: =T24/O24 -> 0 | Y24: =U24/P24 -> 0 | Z24: =V24+X24 -> 1.0481742 | AA24: =IFERROR(W24/V24-1,0) -> 0.0016530599 | AB24: =IFERROR((W24-V24)/Z24,0) -> 0.0016530599 | AC24: =IFERROR(Y24/X24-1,0) -> 0 | AD24: =IFERROR((Y24-X24)/Z24,0) -> 0 | AE24: =AB24+AD24 -> 0.0016530599 | AF24: =(1+Q24)*(1+AE24)-1 -> -0.0053550075 | AG24: =G24-AF24 -> 1.3183898e-16 | AH24: =SUM(IF(BM24="lease",BW24,0),IF(CH24="lease",CR24,0),IF(DC24="lease",DM24,0),IF(DX24="lease",EH24,0),IF(ES24="lease",FC24,0),IF(FN24="lease",FX24,0),IF(GI24="lease",GS24,0),IF(HD24="lease",HN24,0),IF(HY24="lease",II24,0),IF(IT24="lease",JD24,0)) -> -0.0057362484 | AI24: =SUM(IF(BM24="keep",BW24,0),IF(CH24="keep",CR24,0),IF(DC24="keep",DM24,0),IF(DX24="keep",EH24,0),IF(ES24="keep",FC24,0),IF(FN24="keep",FX24,0),IF(GI24="keep",GS24,0),IF(HD24="keep",HN24,0),IF(HY24="keep",II24,0),IF(IT24="keep",JD24,0)) -> 0 | AJ24: =SUM(IF(BM24="lease",BX24,0),IF(CH24="lease",CS24,0),IF(DC24="lease",DN24,0),IF(DX24="lease",EI24,0),IF(ES24="lease",FD24,0),IF(FN24="lease",FY24,0),IF(GI24="lease",GT24,0),IF(HD24="lease",HO24,0),IF(HY24="lease",IJ24,0),IF(IT24="lease",JE24,0)) -> 0 | AK24: =SUM(IF(BM24="keep",BX24,0),IF(CH24="keep",CS24,0),IF(DC24="keep",DN24,0),IF(DX24="keep",EI24,0),IF(ES24="keep",FD24,0),IF(FN24="keep",FY24,0),IF(GI24="keep",GT24,0),IF(HD24="keep",HO24,0),IF(HY24="keep",IJ24,0),IF(IT24="keep",JE24,0)) -> 0 | AL24: =R24-S23 -> 2.220446e-16 | AM24: =T24-U23 -> 0 | AN24: =AN23 -> 1 | AO24: =AO23+AH24 -> 0.065457102 | AP24: =AP23+AL24 -> -4.4408921e-16 | AQ24: =AN24+AO24+AP24 -> 1.0654571 | AR24: =S24-AQ24 -> 2.220446e-16 | AS24: =AS23 -> 0 | AT24: =AT23+AI24 -> 0 | AU24: =AU23+AM24 -> 0 | AV24: =AS24+AT24+AU24 -> 0 | AW24: =U24-AV24 -> 0 | AX24: 1.0711934 | AY24: 1.0654571 | AZ24: =S24-AY24 -> 0 | BA24: 0 | BB24: 0 | BC24: =U24-BB24 -> 0 | BD24: =SUM(IF(BL24="direct",CE24,0),IF(CG24="direct",CZ24,0),IF(DB24="direct",DU24,0),IF(DW24="direct",EP24,0),IF(ER24="direct",FK24,0),IF(FM24="direct",GF24,0),IF(GH24="direct",HA24,0),IF(HC24="direct",HV24,0),IF(HX24="direct",IQ24,0),IF(IS24="direct",JL24,0)) -> -0.0041213472 | BE24: =SUM(IF(BL24="treasury",CE24,0),IF(CG24="treasury",CZ24,0),IF(DB24="treasury",DU24,0),IF(DW24="treasury",EP24,0),IF(ER24="treasury",FK24,0),IF(FM24="treasury",GF24,0),IF(GH24="treasury",HA24,0),IF(HC24="treasury",HV24,0),IF(HX24="treasury",IQ24,0),IF(IS24="treasury",JL24,0)) -> 0.00020995123 | BF24: =SUM(IF(BL24="future",CE24,0),IF(CG24="future",CZ24,0),IF(DB24="future",DU24,0),IF(DW24="future",EP24,0),IF(ER24="future",FK24,0),IF(FM24="future",GF24,0),IF(GH24="future",HA24,0),IF(HC24="future",HV24,0),IF(HX24="future",IQ24,0),IF(IS24="future",JL24,0)) -> -0.0014436115 | BG24: =SUM(IF(BL24="cash",CE24,0),IF(CG24="cash",CZ24,0),IF(DB24="cash",DU24,0),IF(DW24="cash",EP24,0),IF(ER24="cash",FK24,0),IF(FM24="cash",GF24,0),IF(GH24="cash",HA24,0),IF(HC24="cash",HV24,0),IF(HX24="cash",IQ24,0),IF(IS24="cash",JL24,0)) -> 0 | BH24: =SUM(BD24:BG24) -> -0.0053550075 | BI24: =G24-BH24 -> 0 | BJ24: =COUNTA(BK24,CF24,DA24,DV24,EQ24,FL24,GG24,HB24,HW24,IR24) -> 5 | BK24: Direct commodity holding | BL24: direct | BM24: lease | BN24: long | BP24: 2.001 | BQ24: 1.987 | BR24: 0.31441657 | BS24: 0.58733333 | BT24: 0.62914756 | BU24: 0.62914756 | BV24: 0.62474573 | BW24: -0.0044147597 | BX24: 1.292769e-05 | BY24: 2.001 | BZ24: 1.987 | CE24: =IFERROR(BW24/F24,0) -> -0.0041213472 | CF24: Treasury collateral | CG24: treasury | CH24: lease | CI24: long | CK24: 100.48837 | CL24: 100.5395 | CM24: 0.0043989744 | CN24: 0.41266667 | CO24: 0.44204579 | CP24: 0.44204579 | CQ24: 0.44227069 | CR24: 0.00022489836 | CS24: -9.0801932e-18 | CT24: 2.001 | CU24: 1.987 | CY24: 55 | CZ24: =IFERROR(CR24/F24,0) -> 0.00020995123 | DA24: SI69H | DB24: future | DC24: lease | DD24: long | DE24: regular | DF24: 2.001 | DG24: 1.994 | DH24: 0.22091244 | DI24: 0.41266667 | DJ24: 0.44204579 | DK24: 0 | DL24: 0 | DM24: -0.0015463871 | DN24: 0.0015463871 | DO24: 2.001 | DP24: 1.987 | DQ24: 0 | DR24: 0.0619 | DS24: 0.0619 | DT24: 55 | DU24: =IFERROR(DM24/F24,0) -> -0.0014436115 | DV24: Lease cash / margin / financing | DW24: cash | DX24: lease | DY24: cash | EA24: 1 | EB24: 1 | EC24: 0 | EE24: 0 | EF24: 0 | EG24: -0.0015593148 | EH24: 0 | EI24: -0.0015593148 | EJ24: 2.001 | EK24: 1.987 | EP24: =IFERROR(EH24/F24,0) -> 0 | EQ24: Keep cash / margin / financing | ER24: cash | ES24: keep | ET24: cash | EV24: 1 | EW24: 1 | EX24: 0 | EZ24: 0 | FA24: 0 | FB24: 0 | FC24: 0 | FD24: 0 | FE24: 2.001 | FF24: 1.987 | FK24: =IFERROR(FC24/F24,0) -> 0
A25: 25237 | B25: 25238 | C25: =B25-A25 -> 1 | D25: 25237 | E25: positive | F25: 1.0654571 | G25: 0.0001840176 | H25: =SUM(CE25,CZ25,DU25,EP25,FK25,GF25,HA25,HV25,IQ25,JL25) -> 0.0001840176 | I25: =G25-H25 -> -1.6263033e-19 | J25: =F25*(1+H25) -> 1.0656532 | K25: 1.0656532 | L25: =K25-J25 -> 0 | M25: 1.987 | N25: 1.991 | O25: =M25/$M$3 -> 1.014811 | P25: =N25/$M$3 -> 1.0168539 | Q25: =IFERROR(N25/M25-1,0) -> 0.0020130851 | R25: =SUM(IF(BM25="lease",BU25,0),IF(CH25="lease",CP25,0),IF(DC25="lease",DK25,0),IF(DX25="lease",EF25,0),IF(ES25="lease",FA25,0),IF(FN25="lease",FV25,0),IF(GI25="lease",GQ25,0),IF(HD25="lease",HL25,0),IF(HY25="lease",IG25,0),IF(IT25="lease",JB25,0)) -> 1.0654571 | S25: =SUM(IF(BM25="lease",BV25,0),IF(CH25="lease",CQ25,0),IF(DC25="lease",DL25,0),IF(DX25="lease",EG25,0),IF(ES25="lease",FB25,0),IF(FN25="lease",FW25,0),IF(GI25="lease",GR25,0),IF(HD25="lease",HM25,0),IF(HY25="lease",IH25,0),IF(IT25="lease",JC25,0)) -> 1.0656532 | T25: =SUM(IF(BM25="keep",BU25,0),IF(CH25="keep",CP25,0),IF(DC25="keep",DK25,0),IF(DX25="keep",EF25,0),IF(ES25="keep",FA25,0),IF(FN25="keep",FV25,0),IF(GI25="keep",GQ25,0),IF(HD25="keep",HL25,0),IF(HY25="keep",IG25,0),IF(IT25="keep",JB25,0)) -> 0 | U25: =SUM(IF(BM25="keep",BV25,0),IF(CH25="keep",CQ25,0),IF(DC25="keep",DL25,0),IF(DX25="keep",EG25,0),IF(ES25="keep",FB25,0),IF(FN25="keep",FW25,0),IF(GI25="keep",GR25,0),IF(HD25="keep",HM25,0),IF(HY25="keep",IH25,0),IF(IT25="keep",JC25,0)) -> 0 | V25: =R25/O25 -> 1.0499069 | W25: =S25/P25 -> 1.0479904 | X25: =T25/O25 -> 0 | Y25: =U25/P25 -> 0 | Z25: =V25+X25 -> 1.0499069 | AA25: =IFERROR(W25/V25-1,0) -> -0.0018253928 | AB25: =IFERROR((W25-V25)/Z25,0) -> -0.0018253928 | AC25: =IFERROR(Y25/X25-1,0) -> 0 | AD25: =IFERROR((Y25-X25)/Z25,0) -> 0 | AE25: =AB25+AD25 -> -0.0018253928 | AF25: =(1+Q25)*(1+AE25)-1 -> 0.0001840176 | AG25: =G25-AF25 -> 2.2573089e-16 | AH25: =SUM(IF(BM25="lease",BW25,0),IF(CH25="lease",CR25,0),IF(DC25="lease",DM25,0),IF(DX25="lease",EH25,0),IF(ES25="lease",FC25,0),IF(FN25="lease",FX25,0),IF(GI25="lease",GS25,0),IF(HD25="lease",HN25,0),IF(HY25="lease",II25,0),IF(IT25="lease",JD25,0)) -> 0.00019606286 | AI25: =SUM(IF(BM25="keep",BW25,0),IF(CH25="keep",CR25,0),IF(DC25="keep",DM25,0),IF(DX25="keep",EH25,0),IF(ES25="keep",FC25,0),IF(FN25="keep",FX25,0),IF(GI25="keep",GS25,0),IF(HD25="keep",HN25,0),IF(HY25="keep",II25,0),IF(IT25="keep",JD25,0)) -> 0 | AJ25: =SUM(IF(BM25="lease",BX25,0),IF(CH25="lease",CS25,0),IF(DC25="lease",DN25,0),IF(DX25="lease",EI25,0),IF(ES25="lease",FD25,0),IF(FN25="lease",FY25,0),IF(GI25="lease",GT25,0),IF(HD25="lease",HO25,0),IF(HY25="lease",IJ25,0),IF(IT25="lease",JE25,0)) -> 0 | AK25: =SUM(IF(BM25="keep",BX25,0),IF(CH25="keep",CS25,0),IF(DC25="keep",DN25,0),IF(DX25="keep",EI25,0),IF(ES25="keep",FD25,0),IF(FN25="keep",FY25,0),IF(GI25="keep",GT25,0),IF(HD25="keep",HO25,0),IF(HY25="keep",IJ25,0),IF(IT25="keep",JE25,0)) -> 0 | AL25: =R25-S24 -> 0 | AM25: =T25-U24 -> 0 | AN25: =AN24 -> 1 | AO25: =AO24+AH25 -> 0.065653165 | AP25: =AP24+AL25 -> -4.4408921e-16 | AQ25: =AN25+AO25+AP25 -> 1.0656532 | AR25: =S25-AQ25 -> 0 | AS25: =AS24 -> 0 | AT25: =AT24+AI25 -> 0 | AU25: =AU24+AM25 -> 0 | AV25: =AS25+AT25+AU25 -> 0 | AW25: =U25-AV25 -> 0 | AX25: 1.0654571 | AY25: 1.0656532 | AZ25: =S25-AY25 -> -2.220446e-16 | BA25: 0 | BB25: 0 | BC25: =U25-BB25 -> 0 | BD25: =SUM(IF(BL25="direct",CE25,0),IF(CG25="direct",CZ25,0),IF(DB25="direct",DU25,0),IF(DW25="direct",EP25,0),IF(ER25="direct",FK25,0),IF(FM25="direct",GF25,0),IF(GH25="direct",HA25,0),IF(HC25="direct",HV25,0),IF(HX25="direct",IQ25,0),IF(IS25="direct",JL25,0)) -> 0.0015090643 | BE25: =SUM(IF(BL25="treasury",CE25,0),IF(CG25="treasury",CZ25,0),IF(DB25="treasury",DU25,0),IF(DW25="treasury",EP25,0),IF(ER25="treasury",FK25,0),IF(FM25="treasury",GF25,0),IF(GH25="treasury",HA25,0),IF(HC25="treasury",HV25,0),IF(HX25="treasury",IQ25,0),IF(IS25="treasury",JL25,0)) -> 4.202638e-05 | BF25: =SUM(IF(BL25="future",CE25,0),IF(CG25="future",CZ25,0),IF(DB25="future",DU25,0),IF(DW25="future",EP25,0),IF(ER25="future",FK25,0),IF(FM25="future",GF25,0),IF(GH25="future",HA25,0),IF(HC25="future",HV25,0),IF(HX25="future",IQ25,0),IF(IS25="future",JL25,0)) -> -0.0013670731 | BG25: =SUM(IF(BL25="cash",CE25,0),IF(CG25="cash",CZ25,0),IF(DB25="cash",DU25,0),IF(DW25="cash",EP25,0),IF(ER25="cash",FK25,0),IF(FM25="cash",GF25,0),IF(GH25="cash",HA25,0),IF(HC25="cash",HV25,0),IF(HX25="cash",IQ25,0),IF(IS25="cash",JL25,0)) -> 0 | BH25: =SUM(BD25:BG25) -> 0.0001840176 | BI25: =G25-BH25 -> 0 | BJ25: =COUNTA(BK25,CF25,DA25,DV25,EQ25,FL25,GG25,HB25,HW25,IR25) -> 5 | BK25: Direct commodity holding | BL25: direct | BM25: lease | BN25: long | BP25: 1.987 | BQ25: 1.991 | BR25: 0.40333312 | BS25: 0.75218693 | BT25: 0.80142291 | BU25: 0.80142291 | BV25: 0.80303624 | BW25: 0.0016078433 | BX25: 5.489198e-06 | BY25: 1.987 | BZ25: 1.991 | CE25: =IFERROR(BW25/F25,0) -> 0.0015090643 | CF25: Treasury collateral | CG25: treasury | CH25: lease | CI25: long | CK25: 100.5395 | CL25: 100.55655 | CM25: 0.0026261737 | CN25: 0.24781307 | CO25: 0.26403419 | CP25: 0.26403419 | CQ25: 0.26407897 | CR25: 4.4777305e-05 | CS25: 1.0225382e-17 | CT25: 1.987 | CU25: 1.991 | CY25: 52 | CZ25: =IFERROR(CR25/F25,0) -> 4.202638e-05 | DA25: SI69H | DB25: future | DC25: lease | DD25: long | DE25: regular | DF25: 1.994 | DG25: 1.983 | DH25: 0.13241434 | DI25: 0.24781307 | DJ25: 0.26403419 | DK25: 0 | DL25: 0 | DM25: -0.0014565577 | DN25: 0.0014565577 | DO25: 1.987 | DP25: 1.991 | DQ25: 0.0035228988 | DR25: 0.0619 | DS25: 0.03717196 | DT25: 52 | DU25: =IFERROR(DM25/F25,0) -> -0.0013670731 | DV25: Lease cash / margin / financing | DW25: cash | DX25: lease | DY25: cash | EA25: 1 | EB25: 1 | EC25: 0 | EE25: 0 | EF25: 0 | EG25: -0.0014620469 | EH25: 0 | EI25: -0.0014620469 | EJ25: 1.987 | EK25: 1.991 | EP25: =IFERROR(EH25/F25,0) -> 0 | EQ25: Keep cash / margin / financing | ER25: cash | ES25: keep | ET25: cash | EV25: 1 | EW25: 1 | EX25: 0 | EZ25: 0 | FA25: 0 | FB25: 0 | FC25: 0 | FD25: 0 | FE25: 1.987 | FF25: 1.991 | FK25: =IFERROR(FC25/F25,0) -> 0
A26: 25238 | B26: 25239 | C26: =B26-A26 -> 1 | D26: 25238 | E26: positive | F26: 1.0656532 | G26: -0.032608756 | H26: =SUM(CE26,CZ26,DU26,EP26,FK26,GF26,HA26,HV26,IQ26,JL26) -> -0.032608756 | I26: =G26-H26 -> 0 | J26: =F26*(1+H26) -> 1.0309035 | K26: 1.0309035 | L26: =K26-J26 -> 0 | M26: 1.991 | N26: 1.983 | O26: =M26/$M$3 -> 1.0168539 | P26: =N26/$M$3 -> 1.0127681 | Q26: =IFERROR(N26/M26-1,0) -> -0.0040180814 | R26: =SUM(IF(BM26="lease",BU26,0),IF(CH26="lease",CP26,0),IF(DC26="lease",DK26,0),IF(DX26="lease",EF26,0),IF(ES26="lease",FA26,0),IF(FN26="lease",FV26,0),IF(GI26="lease",GQ26,0),IF(HD26="lease",HL26,0),IF(HY26="lease",IG26,0),IF(IT26="lease",JB26,0)) -> 1.0656532 | S26: =SUM(IF(BM26="lease",BV26,0),IF(CH26="lease",CQ26,0),IF(DC26="lease",DL26,0),IF(DX26="lease",EG26,0),IF(ES26="lease",FB26,0),IF(FN26="lease",FW26,0),IF(GI26="lease",GR26,0),IF(HD26="lease",HM26,0),IF(HY26="lease",IH26,0),IF(IT26="lease",JC26,0)) -> 1.0309035 | T26: =SUM(IF(BM26="keep",BU26,0),IF(CH26="keep",CP26,0),IF(DC26="keep",DK26,0),IF(DX26="keep",EF26,0),IF(ES26="keep",FA26,0),IF(FN26="keep",FV26,0),IF(GI26="keep",GQ26,0),IF(HD26="keep",HL26,0),IF(HY26="keep",IG26,0),IF(IT26="keep",JB26,0)) -> 0 | U26: =SUM(IF(BM26="keep",BV26,0),IF(CH26="keep",CQ26,0),IF(DC26="keep",DL26,0),IF(DX26="keep",EG26,0),IF(ES26="keep",FB26,0),IF(FN26="keep",FW26,0),IF(GI26="keep",GR26,0),IF(HD26="keep",HM26,0),IF(HY26="keep",IH26,0),IF(IT26="keep",JC26,0)) -> 0 | V26: =R26/O26 -> 1.0479904 | W26: =S26/P26 -> 1.0179068 | X26: =T26/O26 -> 0 | Y26: =U26/P26 -> 0 | Z26: =V26+X26 -> 1.0479904 | AA26: =IFERROR(W26/V26-1,0) -> -0.028706018 | AB26: =IFERROR((W26-V26)/Z26,0) -> -0.028706018 | AC26: =IFERROR(Y26/X26-1,0) -> 0 | AD26: =IFERROR((Y26-X26)/Z26,0) -> 0 | AE26: =AB26+AD26 -> -0.028706018 | AF26: =(1+Q26)*(1+AE26)-1 -> -0.032608756 | AG26: =G26-AF26 -> -1.3877788e-17 | AH26: =SUM(IF(BM26="lease",BW26,0),IF(CH26="lease",CR26,0),IF(DC26="lease",DM26,0),IF(DX26="lease",EH26,0),IF(ES26="lease",FC26,0),IF(FN26="lease",FX26,0),IF(GI26="lease",GS26,0),IF(HD26="lease",HN26,0),IF(HY26="lease",II26,0),IF(IT26="lease",JD26,0)) -> -0.034749624 | AI26: =SUM(IF(BM26="keep",BW26,0),IF(CH26="keep",CR26,0),IF(DC26="keep",DM26,0),IF(DX26="keep",EH26,0),IF(ES26="keep",FC26,0),IF(FN26="keep",FX26,0),IF(GI26="keep",GS26,0),IF(HD26="keep",HN26,0),IF(HY26="keep",II26,0),IF(IT26="keep",JD26,0)) -> 0 | AJ26: =SUM(IF(BM26="lease",BX26,0),IF(CH26="lease",CS26,0),IF(DC26="lease",DN26,0),IF(DX26="lease",EI26,0),IF(ES26="lease",FD26,0),IF(FN26="lease",FY26,0),IF(GI26="lease",GT26,0),IF(HD26="lease",HO26,0),IF(HY26="lease",IJ26,0),IF(IT26="lease",JE26,0)) -> 0 | AK26: =SUM(IF(BM26="keep",BX26,0),IF(CH26="keep",CS26,0),IF(DC26="keep",DN26,0),IF(DX26="keep",EI26,0),IF(ES26="keep",FD26,0),IF(FN26="keep",FY26,0),IF(GI26="keep",GT26,0),IF(HD26="keep",HO26,0),IF(HY26="keep",IJ26,0),IF(IT26="keep",JE26,0)) -> 0 | AL26: =R26-S25 -> 2.220446e-16 | AM26: =T26-U25 -> 0 | AN26: =AN25 -> 1 | AO26: =AO25+AH26 -> 0.030903541 | AP26: =AP25+AL26 -> -2.220446e-16 | AQ26: =AN26+AO26+AP26 -> 1.0309035 | AR26: =S26-AQ26 -> 0 | AS26: =AS25 -> 0 | AT26: =AT25+AI26 -> 0 | AU26: =AU25+AM26 -> 0 | AV26: =AS26+AT26+AU26 -> 0 | AW26: =U26-AV26 -> 0 | AX26: 1.0656532 | AY26: 1.0309035 | AZ26: =S26-AY26 -> 0 | BA26: 0 | BB26: 0 | BC26: =U26-BB26 -> 0 | BD26: =SUM(IF(BL26="direct",CE26,0),IF(CG26="direct",CZ26,0),IF(DB26="direct",DU26,0),IF(DW26="direct",EP26,0),IF(ER26="direct",FK26,0),IF(FM26="direct",GF26,0),IF(GH26="direct",HA26,0),IF(HC26="direct",HV26,0),IF(HX26="direct",IQ26,0),IF(IS26="direct",JL26,0)) -> -0.0015896636 | BE26: =SUM(IF(BL26="treasury",CE26,0),IF(CG26="treasury",CZ26,0),IF(DB26="treasury",DU26,0),IF(DW26="treasury",EP26,0),IF(ER26="treasury",FK26,0),IF(FM26="treasury",GF26,0),IF(GH26="treasury",HA26,0),IF(HC26="treasury",HV26,0),IF(HX26="treasury",IQ26,0),IF(IS26="treasury",JL26,0)) -> 0.00010277489 | BF26: =SUM(IF(BL26="future",CE26,0),IF(CG26="future",CZ26,0),IF(DB26="future",DU26,0),IF(DW26="future",EP26,0),IF(ER26="future",FK26,0),IF(FM26="future",GF26,0),IF(GH26="future",HA26,0),IF(HC26="future",HV26,0),IF(HX26="future",IQ26,0),IF(IS26="future",JL26,0)) -> -0.031121867 | BG26: =SUM(IF(BL26="cash",CE26,0),IF(CG26="cash",CZ26,0),IF(DB26="cash",DU26,0),IF(DW26="cash",EP26,0),IF(ER26="cash",FK26,0),IF(FM26="cash",GF26,0),IF(GH26="cash",HA26,0),IF(HC26="cash",HV26,0),IF(HX26="cash",IQ26,0),IF(IS26="cash",JL26,0)) -> 0 | BH26: =SUM(BD26:BG26) -> -0.032608756 | BI26: =G26-BH26 -> 0 | BJ26: =COUNTA(BK26,CF26,DA26,DV26,EQ26,FL26,GG26,HB26,HW26,IR26) -> 5 | BK26: Direct commodity holding | BL26: direct | BM26: lease | BN26: long | BP26: 1.991 | BQ26: 1.983 | BR26: 0.21139341 | BS26: 0.39495429 | BT26: 0.42088429 | BU26: 0.42088429 | BV26: 0.41919314 | BW26: -0.0016940301 | BX26: 2.8827691e-06 | BY26: 1.991 | BZ26: 1.983 | CE26: =IFERROR(BW26/F26,0) -> -0.0015896636 | CF26: Treasury collateral | CG26: treasury | CH26: lease | CI26: long | CK26: 100.55655 | CL26: 100.57363 | CM26: 0.0064120028 | CN26: 0.60504571 | CO26: 0.64476888 | CP26: 0.64476888 | CQ26: 0.6448784 | CR26: 0.00010952238 | CS26: 1.871604e-17 | CT26: 1.991 | CU26: 1.983 | CY26: 51 | CZ26: =IFERROR(CR26/F26,0) -> 0.00010277489 | DA26: SI69H | DB26: future | DC26: lease | DD26: long | DE26: regular | DF26: 1.983 | DG26: 1.881 | DH26: 0.3251482 | DI26: 0.60504571 | DJ26: 0.64476888 | DK26: 0 | DL26: 0 | DM26: -0.033165116 | DN26: 0.033165116 | DO26: 1.991 | DP26: 1.983 | DQ26: -0.0040180814 | DR26: 0.062 | DS26: 0.090756857 | DT26: 51 | DU26: =IFERROR(DM26/F26,0) -> -0.031121867 | DV26: Lease cash / margin / financing | DW26: cash | DX26: lease | DY26: cash | EA26: 1 | EB26: 1 | EC26: 0 | EE26: 0 | EF26: 0 | EG26: -0.033167999 | EH26: 0 | EI26: -0.033167999 | EJ26: 1.991 | EK26: 1.983 | EP26: =IFERROR(EH26/F26,0) -> 0 | EQ26: Keep cash / margin / financing | ER26: cash | ES26: keep | ET26: cash | EV26: 1 | EW26: 1 | EX26: 0 | EZ26: 0 | FA26: 0 | FB26: 0 | FC26: 0 | FD26: 0 | FE26: 1.991 | FF26: 1.983 | FK26: =IFERROR(FC26/F26,0) -> 0
A27: 25239 | B27: 25240 | C27: =B27-A27 -> 1 | D27: 25239 | E27: positive | F27: 1.0309035 | G27: -0.024285214 | H27: =SUM(CE27,CZ27,DU27,EP27,FK27,GF27,HA27,HV27,IQ27,JL27) -> -0.024285214 | I27: =G27-H27 -> 0 | J27: =F27*(1+H27) -> 1.0058678 | K27: 1.0058678 | L27: =K27-J27 -> 0 | M27: 1.983 | N27: 1.922 | O27: =M27/$M$3 -> 1.0127681 | P27: =N27/$M$3 -> 0.98161389 | Q27: =IFERROR(N27/M27-1,0) -> -0.030761473 | R27: =SUM(IF(BM27="lease",BU27,0),IF(CH27="lease",CP27,0),IF(DC27="lease",DK27,0),IF(DX27="lease",EF27,0),IF(ES27="lease",FA27,0),IF(FN27="lease",FV27,0),IF(GI27="lease",GQ27,0),IF(HD27="lease",HL27,0),IF(HY27="lease",IG27,0),IF(IT27="lease",JB27,0)) -> 1.0309035 | S27: =SUM(IF(BM27="lease",BV27,0),IF(CH27="lease",CQ27,0),IF(DC27="lease",DL27,0),IF(DX27="lease",EG27,0),IF(ES27="lease",FB27,0),IF(FN27="lease",FW27,0),IF(GI27="lease",GR27,0),IF(HD27="lease",HM27,0),IF(HY27="lease",IH27,0),IF(IT27="lease",JC27,0)) -> 1.0058678 | T27: =SUM(IF(BM27="keep",BU27,0),IF(CH27="keep",CP27,0),IF(DC27="keep",DK27,0),IF(DX27="keep",EF27,0),IF(ES27="keep",FA27,0),IF(FN27="keep",FV27,0),IF(GI27="keep",GQ27,0),IF(HD27="keep",HL27,0),IF(HY27="keep",IG27,0),IF(IT27="keep",JB27,0)) -> 0 | U27: =SUM(IF(BM27="keep",BV27,0),IF(CH27="keep",CQ27,0),IF(DC27="keep",DL27,0),IF(DX27="keep",EG27,0),IF(ES27="keep",FB27,0),IF(FN27="keep",FW27,0),IF(GI27="keep",GR27,0),IF(HD27="keep",HM27,0),IF(HY27="keep",IH27,0),IF(IT27="keep",JC27,0)) -> 0 | V27: =R27/O27 -> 1.0179068 | W27: =S27/P27 -> 1.0247082 | X27: =T27/O27 -> 0 | Y27: =U27/P27 -> 0 | Z27: =V27+X27 -> 1.0179068 | AA27: =IFERROR(W27/V27-1,0) -> 0.0066818005 | AB27: =IFERROR((W27-V27)/Z27,0) -> 0.0066818005 | AC27: =IFERROR(Y27/X27-1,0) -> 0 | AD27: =IFERROR((Y27-X27)/Z27,0) -> 0 | AE27: =AB27+AD27 -> 0.0066818005 | AF27: =(1+Q27)*(1+AE27)-1 -> -0.024285214 | AG27: =G27-AF27 -> -1.8041124e-16 | AH27: =SUM(IF(BM27="lease",BW27,0),IF(CH27="lease",CR27,0),IF(DC27="lease",DM27,0),IF(DX27="lease",EH27,0),IF(ES27="lease",FC27,0),IF(FN27="lease",FX27,0),IF(GI27="lease",GS27,0),IF(HD27="lease",HN27,0),IF(HY27="lease",II27,0),IF(IT27="lease",JD27,0)) -> -0.025035713 | AI27: =SUM(IF(BM27="keep",BW27,0),IF(CH27="keep",CR27,0),IF(DC27="keep",DM27,0),IF(DX27="keep",EH27,0),IF(ES27="keep",FC27,0),IF(FN27="keep",FX27,0),IF(GI27="keep",GS27,0),IF(HD27="keep",HN27,0),IF(HY27="keep",II27,0),IF(IT27="keep",JD27,0)) -> 0 | AJ27: =SUM(IF(BM27="lease",BX27,0),IF(CH27="lease",CS27,0),IF(DC27="lease",DN27,0),IF(DX27="lease",EI27,0),IF(ES27="lease",FD27,0),IF(FN27="lease",FY27,0),IF(GI27="lease",GT27,0),IF(HD27="lease",HO27,0),IF(HY27="lease",IJ27,0),IF(IT27="lease",JE27,0)) -> 0 | AK27: =SUM(IF(BM27="keep",BX27,0),IF(CH27="keep",CS27,0),IF(DC27="keep",DN27,0),IF(DX27="keep",EI27,0),IF(ES27="keep",FD27,0),IF(FN27="keep",FY27,0),IF(GI27="keep",GT27,0),IF(HD27="keep",HO27,0),IF(HY27="keep",IJ27,0),IF(IT27="keep",JE27,0)) -> 0 | AL27: =R27-S26 -> 0 | AM27: =T27-U26 -> 0 | AN27: =AN26 -> 1 | AO27: =AO26+AH27 -> 0.005867828 | AP27: =AP26+AL27 -> -2.220446e-16 | AQ27: =AN27+AO27+AP27 -> 1.0058678 | AR27: =S27-AQ27 -> 0 | AS27: =AS26 -> 0 | AT27: =AT26+AI27 -> 0 | AU27: =AU26+AM27 -> 0 | AV27: =AS27+AT27+AU27 -> 0 | AW27: =U27-AV27 -> 0 | AX27: 1.0309035 | AY27: 1.0058678 | AZ27: =S27-AY27 -> 0 | BA27: 0 | BB27: 0 | BC27: =U27-BB27 -> 0 | BD27: =SUM(IF(BL27="direct",CE27,0),IF(CG27="direct",CZ27,0),IF(DB27="direct",DU27,0),IF(DW27="direct",EP27,0),IF(ER27="direct",FK27,0),IF(FM27="direct",GF27,0),IF(GH27="direct",HA27,0),IF(HC27="direct",HV27,0),IF(HX27="direct",IQ27,0),IF(IS27="direct",JL27,0)) -> 0 | BE27: =SUM(IF(BL27="treasury",CE27,0),IF(CG27="treasury",CZ27,0),IF(DB27="treasury",DU27,0),IF(DW27="treasury",EP27,0),IF(ER27="treasury",FK27,0),IF(FM27="treasury",GF27,0),IF(GH27="treasury",HA27,0),IF(HC27="treasury",HV27,0),IF(HX27="treasury",IQ27,0),IF(IS27="treasury",JL27,0)) -> 0.00016986301 | BF27: =SUM(IF(BL27="future",CE27,0),IF(CG27="future",CZ27,0),IF(DB27="future",DU27,0),IF(DW27="future",EP27,0),IF(ER27="future",FK27,0),IF(FM27="future",GF27,0),IF(GH27="future",HA27,0),IF(HC27="future",HV27,0),IF(HX27="future",IQ27,0),IF(IS27="future",JL27,0)) -> -0.024455077 | BG27: =SUM(IF(BL27="cash",CE27,0),IF(CG27="cash",CZ27,0),IF(DB27="cash",DU27,0),IF(DW27="cash",EP27,0),IF(ER27="cash",FK27,0),IF(FM27="cash",GF27,0),IF(GH27="cash",HA27,0),IF(HC27="cash",HV27,0),IF(HX27="cash",IQ27,0),IF(IS27="cash",JL27,0)) -> 0 | BH27: =SUM(BD27:BG27) -> -0.024285214 | BI27: =G27-BH27 -> 0 | BJ27: =COUNTA(BK27,CF27,DA27,DV27,EQ27,FL27,GG27,HB27,HW27,IR27) -> 4 | BK27: Treasury collateral | BL27: treasury | BM27: lease | BN27: long | BP27: 100.57363 | BQ27: 100.59071 | BR27: 0.010250237 | BS27: 1 | BT27: 1.0309035 | BU27: 1.0309035 | BV27: 1.0310787 | BW27: 0.00017511238 | BX27: 4.2853091e-17 | BY27: 1.983 | BZ27: 1.922 | CD27: 50 | CE27: =IFERROR(BW27/F27,0) -> 0.00016986301 | CF27: SI69H | CG27: future | CH27: lease | CI27: long | CJ27: regular | CK27: 1.881 | CL27: 1.835 | CM27: 0.54806143 | CN27: 1 | CO27: 1.0309035 | CP27: 0 | CQ27: 0 | CR27: -0.025210826 | CS27: 0.025210826 | CT27: 1.983 | CU27: 1.922 | CV27: -0.051437216 | CW27: 0.062 | CX27: 0.43749168 | CY27: 50 | CZ27: =IFERROR(CR27/F27,0) -> -0.024455077 | DA27: Lease cash / margin / financing | DB27: cash | DC27: lease | DD27: cash | DF27: 1 | DG27: 1 | DH27: 0 | DJ27: 0 | DK27: 0 | DL27: -0.025210826 | DM27: 0 | DN27: -0.025210826 | DO27: 1.983 | DP27: 1.922 | DU27: =IFERROR(DM27/F27,0) -> 0 | DV27: Keep cash / margin / financing | DW27: cash | DX27: keep | DY27: cash | EA27: 1 | EB27: 1 | EC27: 0 | EE27: 0 | EF27: 0 | EG27: 0 | EH27: 0 | EI27: 0 | EJ27: 1.983 | EK27: 1.922 | EP27: =IFERROR(EH27/F27,0) -> 0
A28: 25240 | B28: 25241 | C28: =B28-A28 -> 1 | D28: 25240 | E28: positive | F28: 1.0058678 | G28: 0.00016986301 | H28: =SUM(CE28,CZ28,DU28,EP28,FK28,GF28,HA28,HV28,IQ28,JL28) -> 0.00016986301 | I28: =G28-H28 -> 0 | J28: =F28*(1+H28) -> 1.0060387 | K28: 1.0060387 | L28: =K28-J28 -> 0 | M28: 1.922 | N28: 1.885 | O28: =M28/$M$3 -> 0.98161389 | P28: =N28/$M$3 -> 0.96271706 | Q28: =IFERROR(N28/M28-1,0) -> -0.01925078 | R28: =SUM(IF(BM28="lease",BU28,0),IF(CH28="lease",CP28,0),IF(DC28="lease",DK28,0),IF(DX28="lease",EF28,0),IF(ES28="lease",FA28,0),IF(FN28="lease",FV28,0),IF(GI28="lease",GQ28,0),IF(HD28="lease",HL28,0),IF(HY28="lease",IG28,0),IF(IT28="lease",JB28,0)) -> 1.0058678 | S28: =SUM(IF(BM28="lease",BV28,0),IF(CH28="lease",CQ28,0),IF(DC28="lease",DL28,0),IF(DX28="lease",EG28,0),IF(ES28="lease",FB28,0),IF(FN28="lease",FW28,0),IF(GI28="lease",GR28,0),IF(HD28="lease",HM28,0),IF(HY28="lease",IH28,0),IF(IT28="lease",JC28,0)) -> 1.0060387 | T28: =SUM(IF(BM28="keep",BU28,0),IF(CH28="keep",CP28,0),IF(DC28="keep",DK28,0),IF(DX28="keep",EF28,0),IF(ES28="keep",FA28,0),IF(FN28="keep",FV28,0),IF(GI28="keep",GQ28,0),IF(HD28="keep",HL28,0),IF(HY28="keep",IG28,0),IF(IT28="keep",JB28,0)) -> 0 | U28: =SUM(IF(BM28="keep",BV28,0),IF(CH28="keep",CQ28,0),IF(DC28="keep",DL28,0),IF(DX28="keep",EG28,0),IF(ES28="keep",FB28,0),IF(FN28="keep",FW28,0),IF(GI28="keep",GR28,0),IF(HD28="keep",HM28,0),IF(HY28="keep",IH28,0),IF(IT28="keep",JC28,0)) -> 0 | V28: =R28/O28 -> 1.0247082 | W28: =S28/P28 -> 1.0449993 | X28: =T28/O28 -> 0 | Y28: =U28/P28 -> 0 | Z28: =V28+X28 -> 1.0247082 | AA28: =IFERROR(W28/V28-1,0) -> 0.019801844 | AB28: =IFERROR((W28-V28)/Z28,0) -> 0.019801844 | AC28: =IFERROR(Y28/X28-1,0) -> 0 | AD28: =IFERROR((Y28-X28)/Z28,0) -> 0 | AE28: =AB28+AD28 -> 0.019801844 | AF28: =(1+Q28)*(1+AE28)-1 -> 0.00016986301 | AG28: =G28-AF28 -> 2.6205167e-16 | AH28: =SUM(IF(BM28="lease",BW28,0),IF(CH28="lease",CR28,0),IF(DC28="lease",DM28,0),IF(DX28="lease",EH28,0),IF(ES28="lease",FC28,0),IF(FN28="lease",FX28,0),IF(GI28="lease",GS28,0),IF(HD28="lease",HN28,0),IF(HY28="lease",II28,0),IF(IT28="lease",JD28,0)) -> 0.00017085974 | AI28: =SUM(IF(BM28="keep",BW28,0),IF(CH28="keep",CR28,0),IF(DC28="keep",DM28,0),IF(DX28="keep",EH28,0),IF(ES28="keep",FC28,0),IF(FN28="keep",FX28,0),IF(GI28="keep",GS28,0),IF(HD28="keep",HN28,0),IF(HY28="keep",II28,0),IF(IT28="keep",JD28,0)) -> 0 | AJ28: =SUM(IF(BM28="lease",BX28,0),IF(CH28="lease",CS28,0),IF(DC28="lease",DN28,0),IF(DX28="lease",EI28,0),IF(ES28="lease",FD28,0),IF(FN28="lease",FY28,0),IF(GI28="lease",GT28,0),IF(HD28="lease",HO28,0),IF(HY28="lease",IJ28,0),IF(IT28="lease",JE28,0)) -> 0 | AK28: =SUM(IF(BM28="keep",BX28,0),IF(CH28="keep",CS28,0),IF(DC28="keep",DN28,0),IF(DX28="keep",EI28,0),IF(ES28="keep",FD28,0),IF(FN28="keep",FY28,0),IF(GI28="keep",GT28,0),IF(HD28="keep",HO28,0),IF(HY28="keep",IJ28,0),IF(IT28="keep",JE28,0)) -> 0 | AL28: =R28-S27 -> 0 | AM28: =T28-U27 -> 0 | AN28: =AN27 -> 1 | AO28: =AO27+AH28 -> 0.0060386877 | AP28: =AP27+AL28 -> -2.220446e-16 | AQ28: =AN28+AO28+AP28 -> 1.0060387 | AR28: =S28-AQ28 -> 0 | AS28: =AS27 -> 0 | AT28: =AT27+AI28 -> 0 | AU28: =AU27+AM28 -> 0 | AV28: =AS28+AT28+AU28 -> 0 | AW28: =U28-AV28 -> 0 | AX28: 1.0058678 | AY28: 1.0060387 | AZ28: =S28-AY28 -> 0 | BA28: 0 | BB28: 0 | BC28: =U28-BB28 -> 0 | BD28: =SUM(IF(BL28="direct",CE28,0),IF(CG28="direct",CZ28,0),IF(DB28="direct",DU28,0),IF(DW28="direct",EP28,0),IF(ER28="direct",FK28,0),IF(FM28="direct",GF28,0),IF(GH28="direct",HA28,0),IF(HC28="direct",HV28,0),IF(HX28="direct",IQ28,0),IF(IS28="direct",JL28,0)) -> 0 | BE28: =SUM(IF(BL28="treasury",CE28,0),IF(CG28="treasury",CZ28,0),IF(DB28="treasury",DU28,0),IF(DW28="treasury",EP28,0),IF(ER28="treasury",FK28,0),IF(FM28="treasury",GF28,0),IF(GH28="treasury",HA28,0),IF(HC28="treasury",HV28,0),IF(HX28="treasury",IQ28,0),IF(IS28="treasury",JL28,0)) -> 0.00016986301 | BF28: =SUM(IF(BL28="future",CE28,0),IF(CG28="future",CZ28,0),IF(DB28="future",DU28,0),IF(DW28="future",EP28,0),IF(ER28="future",FK28,0),IF(FM28="future",GF28,0),IF(GH28="future",HA28,0),IF(HC28="future",HV28,0),IF(HX28="future",IQ28,0),IF(IS28="future",JL28,0)) -> 0 | BG28: =SUM(IF(BL28="cash",CE28,0),IF(CG28="cash",CZ28,0),IF(DB28="cash",DU28,0),IF(DW28="cash",EP28,0),IF(ER28="cash",FK28,0),IF(FM28="cash",GF28,0),IF(GH28="cash",HA28,0),IF(HC28="cash",HV28,0),IF(HX28="cash",IQ28,0),IF(IS28="cash",JL28,0)) -> 0 | BH28: =SUM(BD28:BG28) -> 0.00016986301 | BI28: =G28-BH28 -> 0 | BJ28: =COUNTA(BK28,CF28,DA28,DV28,EQ28,FL28,GG28,HB28,HW28,IR28) -> 4 | BK28: Treasury collateral | BL28: treasury | BM28: lease | BN28: long | BP28: 100.59071 | BQ28: 100.6078 | BR28: 0.0099996091 | BS28: 1 | BT28: 1.0058678 | BU28: 1.0058678 | BV28: 1.0060387 | BW28: 0.00017085974 | BX28: -1.0608918e-16 | BY28: 1.922 | BZ28: 1.885 | CD28: 49 | CE28: =IFERROR(BW28/F28,0) -> 0.00016986301 | CF28: SI69H | CG28: future | CH28: lease | CI28: long | CJ28: regular | CK28: 1.835 | CL28: 1.835 | CM28: 0.54815685 | CN28: 1 | CO28: 1.0058678 | CP28: 0 | CQ28: 0 | CR28: 0 | CS28: 0 | CT28: 1.922 | CU28: 1.885 | CV28: -0.045265349 | CW28: 0.062 | CX28: 0.39918066 | CY28: 49 | CZ28: =IFERROR(CR28/F28,0) -> 0 | DA28: Lease cash / margin / financing | DB28: cash | DC28: lease | DD28: cash | DF28: 1 | DG28: 1 | DH28: 2.220446e-16 | DJ28: 2.220446e-16 | DK28: 2.220446e-16 | DL28: 3.2813379e-16 | DM28: 0 | DN28: 1.0608918e-16 | DO28: 1.922 | DP28: 1.885 | DU28: =IFERROR(DM28/F28,0) -> 0 | DV28: Keep cash / margin / financing | DW28: cash | DX28: keep | DY28: cash | EA28: 1 | EB28: 1 | EC28: 0 | EE28: 0 | EF28: 0 | EG28: 0 | EH28: 0 | EI28: 0 | EJ28: 1.922 | EK28: 1.885 | EP28: =IFERROR(EH28/F28,0) -> 0
A29: 25241 | B29: 25245 | C29: =B29-A29 -> 4 | D29: 25241 | E29: positive | F29: 1.0060387 | G29: 0.0017638909 | H29: =SUM(CE29,CZ29,DU29,EP29,FK29,GF29,HA29,HV29,IQ29,JL29) -> 0.0017638909 | I29: =G29-H29 -> 0 | J29: =F29*(1+H29) -> 1.0078132 | K29: 1.0078132 | L29: =K29-J29 -> 0 | M29: 1.885 | N29: 1.883 | O29: =M29/$M$3 -> 0.96271706 | P29: =N29/$M$3 -> 0.96169561 | Q29: =IFERROR(N29/M29-1,0) -> -0.001061008 | R29: =SUM(IF(BM29="lease",BU29,0),IF(CH29="lease",CP29,0),IF(DC29="lease",DK29,0),IF(DX29="lease",EF29,0),IF(ES29="lease",FA29,0),IF(FN29="lease",FV29,0),IF(GI29="lease",GQ29,0),IF(HD29="lease",HL29,0),IF(HY29="lease",IG29,0),IF(IT29="lease",JB29,0)) -> 1.0060387 | S29: =SUM(IF(BM29="lease",BV29,0),IF(CH29="lease",CQ29,0),IF(DC29="lease",DL29,0),IF(DX29="lease",EG29,0),IF(ES29="lease",FB29,0),IF(FN29="lease",FW29,0),IF(GI29="lease",GR29,0),IF(HD29="lease",HM29,0),IF(HY29="lease",IH29,0),IF(IT29="lease",JC29,0)) -> 1.0078132 | T29: =SUM(IF(BM29="keep",BU29,0),IF(CH29="keep",CP29,0),IF(DC29="keep",DK29,0),IF(DX29="keep",EF29,0),IF(ES29="keep",FA29,0),IF(FN29="keep",FV29,0),IF(GI29="keep",GQ29,0),IF(HD29="keep",HL29,0),IF(HY29="keep",IG29,0),IF(IT29="keep",JB29,0)) -> 0 | U29: =SUM(IF(BM29="keep",BV29,0),IF(CH29="keep",CQ29,0),IF(DC29="keep",DL29,0),IF(DX29="keep",EG29,0),IF(ES29="keep",FB29,0),IF(FN29="keep",FW29,0),IF(GI29="keep",GR29,0),IF(HD29="keep",HM29,0),IF(HY29="keep",IH29,0),IF(IT29="keep",JC29,0)) -> 0 | V29: =R29/O29 -> 1.0449993 | W29: =S29/P29 -> 1.0479545 | X29: =T29/O29 -> 0 | Y29: =U29/P29 -> 0 | Z29: =V29+X29 -> 1.0449993 | AA29: =IFERROR(W29/V29-1,0) -> 0.0028278992 | AB29: =IFERROR((W29-V29)/Z29,0) -> 0.0028278992 | AC29: =IFERROR(Y29/X29-1,0) -> 0 | AD29: =IFERROR((Y29-X29)/Z29,0) -> 0 | AE29: =AB29+AD29 -> 0.0028278992 | AF29: =(1+Q29)*(1+AE29)-1 -> 0.0017638909 | AG29: =G29-AF29 -> 1.2294853e-16 | AH29: =SUM(IF(BM29="lease",BW29,0),IF(CH29="lease",CR29,0),IF(DC29="lease",DM29,0),IF(DX29="lease",EH29,0),IF(ES29="lease",FC29,0),IF(FN29="lease",FX29,0),IF(GI29="lease",GS29,0),IF(HD29="lease",HN29,0),IF(HY29="lease",II29,0),IF(IT29="lease",JD29,0)) -> 0.0017745424 | AI29: =SUM(IF(BM29="keep",BW29,0),IF(CH29="keep",CR29,0),IF(DC29="keep",DM29,0),IF(DX29="keep",EH29,0),IF(ES29="keep",FC29,0),IF(FN29="keep",FX29,0),IF(GI29="keep",GS29,0),IF(HD29="keep",HN29,0),IF(HY29="keep",II29,0),IF(IT29="keep",JD29,0)) -> 0 | AJ29: =SUM(IF(BM29="lease",BX29,0),IF(CH29="lease",CS29,0),IF(DC29="lease",DN29,0),IF(DX29="lease",EI29,0),IF(ES29="lease",FD29,0),IF(FN29="lease",FY29,0),IF(GI29="lease",GT29,0),IF(HD29="lease",HO29,0),IF(HY29="lease",IJ29,0),IF(IT29="lease",JE29,0)) -> 0 | AK29: =SUM(IF(BM29="keep",BX29,0),IF(CH29="keep",CS29,0),IF(DC29="keep",DN29,0),IF(DX29="keep",EI29,0),IF(ES29="keep",FD29,0),IF(FN29="keep",FY29,0),IF(GI29="keep",GT29,0),IF(HD29="keep",HO29,0),IF(HY29="keep",IJ29,0),IF(IT29="keep",JE29,0)) -> 0 | AL29: =R29-S28 -> 0 | AM29: =T29-U28 -> 0 | AN29: =AN28 -> 1 | AO29: =AO28+AH29 -> 0.0078132301 | AP29: =AP28+AL29 -> -2.220446e-16 | AQ29: =AN29+AO29+AP29 -> 1.0078132 | AR29: =S29-AQ29 -> -2.220446e-16 | AS29: =AS28 -> 0 | AT29: =AT28+AI29 -> 0 | AU29: =AU28+AM29 -> 0 | AV29: =AS29+AT29+AU29 -> 0 | AW29: =U29-AV29 -> 0 | AX29: 1.0060387 | AY29: 1.0078132 | AZ29: =S29-AY29 -> 0 | BA29: 0 | BB29: 0 | BC29: =U29-BB29 -> 0 | BD29: =SUM(IF(BL29="direct",CE29,0),IF(CG29="direct",CZ29,0),IF(DB29="direct",DU29,0),IF(DW29="direct",EP29,0),IF(ER29="direct",FK29,0),IF(FM29="direct",GF29,0),IF(GH29="direct",HA29,0),IF(HC29="direct",HV29,0),IF(HX29="direct",IQ29,0),IF(IS29="direct",JL29,0)) -> 0 | BE29: =SUM(IF(BL29="treasury",CE29,0),IF(CG29="treasury",CZ29,0),IF(DB29="treasury",DU29,0),IF(DW29="treasury",EP29,0),IF(ER29="treasury",FK29,0),IF(FM29="treasury",GF29,0),IF(GH29="treasury",HA29,0),IF(HC29="treasury",HV29,0),IF(HX29="treasury",IQ29,0),IF(IS29="treasury",JL29,0)) -> 0.0006739726 | BF29: =SUM(IF(BL29="future",CE29,0),IF(CG29="future",CZ29,0),IF(DB29="future",DU29,0),IF(DW29="future",EP29,0),IF(ER29="future",FK29,0),IF(FM29="future",GF29,0),IF(GH29="future",HA29,0),IF(HC29="future",HV29,0),IF(HX29="future",IQ29,0),IF(IS29="future",JL29,0)) -> 0.0010899183 | BG29: =SUM(IF(BL29="cash",CE29,0),IF(CG29="cash",CZ29,0),IF(DB29="cash",DU29,0),IF(DW29="cash",EP29,0),IF(ER29="cash",FK29,0),IF(FM29="cash",GF29,0),IF(GH29="cash",HA29,0),IF(HC29="cash",HV29,0),IF(HX29="cash",IQ29,0),IF(IS29="cash",JL29,0)) -> 0 | BH29: =SUM(BD29:BG29) -> 0.0017638909 | BI29: =G29-BH29 -> 0 | BJ29: =COUNTA(BK29,CF29,DA29,DV29,EQ29,FL29,GG29,HB29,HW29,IR29) -> 4 | BK29: Treasury collateral | BL29: treasury | BM29: lease | BN29: long | BP29: 100.6078 | BQ29: 100.67561 | BR29: 0.0099996091 | BS29: 1 | BT29: 1.0060387 | BU29: 1.0060387 | BV29: 1.0067167 | BW29: 0.00067804251 | BX29: 3.0238399e-16 | BY29: 1.885 | BZ29: 1.883 | CD29: 48 | CE29: =IFERROR(BW29/F29,0) -> 0.0006739726 | CF29: SI69H | CG29: future | CH29: lease | CI29: long | CJ29: regular | CK29: 1.835 | CL29: 1.837 | CM29: 0.54824997 | CN29: 1 | CO29: 1.0060387 | CP29: 0 | CQ29: 0 | CR29: 0.0010964999 | CS29: -0.0010964999 | CT29: 1.885 | CU29: 1.883 | CV29: -0.026525199 | CW29: 0.0615 | CX29: 0.26320203 | CY29: 48 | CZ29: =IFERROR(CR29/F29,0) -> 0.0010899183 | DA29: Lease cash / margin / financing | DB29: cash | DC29: lease | DD29: cash | DF29: 1 | DG29: 1 | DH29: 2.220446e-16 | DJ29: 2.220446e-16 | DK29: 2.220446e-16 | DL29: 0.0010964999 | DM29: 0 | DN29: 0.0010964999 | DO29: 1.885 | DP29: 1.883 | DU29: =IFERROR(DM29/F29,0) -> 0 | DV29: Keep cash / margin / financing | DW29: cash | DX29: keep | DY29: cash | EA29: 1 | EB29: 1 | EC29: 0 | EE29: 0 | EF29: 0 | EG29: 0 | EH29: 0 | EI29: 0 | EJ29: 1.885 | EK29: 1.883 | EP29: =IFERROR(EH29/F29,0) -> 0
A30: 25245 | B30: 25247 | C30: =B30-A30 -> 2 | D30: 25245 | E30: positive | F30: 1.0078132 | G30: -0.054103431 | H30: =SUM(CE30,CZ30,DU30,EP30,FK30,GF30,HA30,HV30,IQ30,JL30) -> -0.054103431 | I30: =G30-H30 -> 0 | J30: =F30*(1+H30) -> 0.95328708 | K30: 0.95328708 | L30: =K30-J30 -> 0 | M30: 1.883 | N30: 1.833 | O30: =M30/$M$3 -> 0.96169561 | P30: =N30/$M$3 -> 0.93615935 | Q30: =IFERROR(N30/M30-1,0) -> -0.026553372 | R30: =SUM(IF(BM30="lease",BU30,0),IF(CH30="lease",CP30,0),IF(DC30="lease",DK30,0),IF(DX30="lease",EF30,0),IF(ES30="lease",FA30,0),IF(FN30="lease",FV30,0),IF(GI30="lease",GQ30,0),IF(HD30="lease",HL30,0),IF(HY30="lease",IG30,0),IF(IT30="lease",JB30,0)) -> 1.0078132 | S30: =SUM(IF(BM30="lease",BV30,0),IF(CH30="lease",CQ30,0),IF(DC30="lease",DL30,0),IF(DX30="lease",EG30,0),IF(ES30="lease",FB30,0),IF(FN30="lease",FW30,0),IF(GI30="lease",GR30,0),IF(HD30="lease",HM30,0),IF(HY30="lease",IH30,0),IF(IT30="lease",JC30,0)) -> 0.95328708 | T30: =SUM(IF(BM30="keep",BU30,0),IF(CH30="keep",CP30,0),IF(DC30="keep",DK30,0),IF(DX30="keep",EF30,0),IF(ES30="keep",FA30,0),IF(FN30="keep",FV30,0),IF(GI30="keep",GQ30,0),IF(HD30="keep",HL30,0),IF(HY30="keep",IG30,0),IF(IT30="keep",JB30,0)) -> 0 | U30: =SUM(IF(BM30="keep",BV30,0),IF(CH30="keep",CQ30,0),IF(DC30="keep",DL30,0),IF(DX30="keep",EG30,0),IF(ES30="keep",FB30,0),IF(FN30="keep",FW30,0),IF(GI30="keep",GR30,0),IF(HD30="keep",HM30,0),IF(HY30="keep",IH30,0),IF(IT30="keep",JC30,0)) -> 0 | V30: =R30/O30 -> 1.0479545 | W30: =S30/P30 -> 1.0182957 | X30: =T30/O30 -> 0 | Y30: =U30/P30 -> 0 | Z30: =V30+X30 -> 1.0479545 | AA30: =IFERROR(W30/V30-1,0) -> -0.02830156 | AB30: =IFERROR((W30-V30)/Z30,0) -> -0.02830156 | AC30: =IFERROR(Y30/X30-1,0) -> 0 | AD30: =IFERROR((Y30-X30)/Z30,0) -> 0 | AE30: =AB30+AD30 -> -0.02830156 | AF30: =(1+Q30)*(1+AE30)-1 -> -0.054103431 | AG30: =G30-AF30 -> -5.5511151e-17 | AH30: =SUM(IF(BM30="lease",BW30,0),IF(CH30="lease",CR30,0),IF(DC30="lease",DM30,0),IF(DX30="lease",EH30,0),IF(ES30="lease",FC30,0),IF(FN30="lease",FX30,0),IF(GI30="lease",GS30,0),IF(HD30="lease",HN30,0),IF(HY30="lease",II30,0),IF(IT30="lease",JD30,0)) -> -0.054526153 | AI30: =SUM(IF(BM30="keep",BW30,0),IF(CH30="keep",CR30,0),IF(DC30="keep",DM30,0),IF(DX30="keep",EH30,0),IF(ES30="keep",FC30,0),IF(FN30="keep",FX30,0),IF(GI30="keep",GS30,0),IF(HD30="keep",HN30,0),IF(HY30="keep",II30,0),IF(IT30="keep",JD30,0)) -> 0 | AJ30: =SUM(IF(BM30="lease",BX30,0),IF(CH30="lease",CS30,0),IF(DC30="lease",DN30,0),IF(DX30="lease",EI30,0),IF(ES30="lease",FD30,0),IF(FN30="lease",FY30,0),IF(GI30="lease",GT30,0),IF(HD30="lease",HO30,0),IF(HY30="lease",IJ30,0),IF(IT30="lease",JE30,0)) -> 0 | AK30: =SUM(IF(BM30="keep",BX30,0),IF(CH30="keep",CS30,0),IF(DC30="keep",DN30,0),IF(DX30="keep",EI30,0),IF(ES30="keep",FD30,0),IF(FN30="keep",FY30,0),IF(GI30="keep",GT30,0),IF(HD30="keep",HO30,0),IF(HY30="keep",IJ30,0),IF(IT30="keep",JE30,0)) -> 0 | AL30: =R30-S29 -> 0 | AM30: =T30-U29 -> 0 | AN30: =AN29 -> 1 | AO30: =AO29+AH30 -> -0.046712923 | AP30: =AP29+AL30 -> -2.220446e-16 | AQ30: =AN30+AO30+AP30 -> 0.95328708 | AR30: =S30-AQ30 -> -2.220446e-16 | AS30: =AS29 -> 0 | AT30: =AT29+AI30 -> 0 | AU30: =AU29+AM30 -> 0 | AV30: =AS30+AT30+AU30 -> 0 | AW30: =U30-AV30 -> 0 | AX30: 1.0078132 | AY30: 0.95328708 | AZ30: =S30-AY30 -> 0 | BA30: 0 | BB30: 0 | BC30: =U30-BB30 -> 0 | BD30: =SUM(IF(BL30="direct",CE30,0),IF(CG30="direct",CZ30,0),IF(DB30="direct",DU30,0),IF(DW30="direct",EP30,0),IF(ER30="direct",FK30,0),IF(FM30="direct",GF30,0),IF(GH30="direct",HA30,0),IF(HC30="direct",HV30,0),IF(HX30="direct",IQ30,0),IF(IS30="direct",JL30,0)) -> 0 | BE30: =SUM(IF(BL30="treasury",CE30,0),IF(CG30="treasury",CZ30,0),IF(DB30="treasury",DU30,0),IF(DW30="treasury",EP30,0),IF(ER30="treasury",FK30,0),IF(FM30="treasury",GF30,0),IF(GH30="treasury",HA30,0),IF(HC30="treasury",HV30,0),IF(HX30="treasury",IQ30,0),IF(IS30="treasury",JL30,0)) -> 0.00033315068 | BF30: =SUM(IF(BL30="future",CE30,0),IF(CG30="future",CZ30,0),IF(DB30="future",DU30,0),IF(DW30="future",EP30,0),IF(ER30="future",FK30,0),IF(FM30="future",GF30,0),IF(GH30="future",HA30,0),IF(HC30="future",HV30,0),IF(HX30="future",IQ30,0),IF(IS30="future",JL30,0)) -> -0.054436581 | BG30: =SUM(IF(BL30="cash",CE30,0),IF(CG30="cash",CZ30,0),IF(DB30="cash",DU30,0),IF(DW30="cash",EP30,0),IF(ER30="cash",FK30,0),IF(FM30="cash",GF30,0),IF(GH30="cash",HA30,0),IF(HC30="cash",HV30,0),IF(HX30="cash",IQ30,0),IF(IS30="cash",JL30,0)) -> 0 | BH30: =SUM(BD30:BG30) -> -0.054103431 | BI30: =G30-BH30 -> 0 | BJ30: =COUNTA(BK30,CF30,DA30,DV30,EQ30,FL30,GG30,HB30,HW30,IR30) -> 4 | BK30: Treasury collateral | BL30: treasury | BM30: lease | BN30: long | BP30: 100.67561 | BQ30: 100.70915 | BR30: 0.010010501 | BS30: 1 | BT30: 1.0078132 | BU30: 1.0078132 | BV30: 1.008149 | BW30: 0.00033575367 | BX30: 2.8893988e-17 | BY30: 1.883 | BZ30: 1.833 | CD30: 44 | CE30: =IFERROR(BW30/F30,0) -> 0.00033315068 | CF30: SI69H | CG30: future | CH30: lease | CI30: long | CJ30: regular | CK30: 1.837 | CL30: 1.737 | CM30: 0.54861907 | CN30: 1 | CO30: 1.0078132 | CP30: 0 | CQ30: 0 | CR30: -0.054861907 | CS30: 0.054861907 | CT30: 1.883 | CU30: 1.833 | CV30: -0.024429102 | CW30: 0.0608 | CX30: 0.26345051 | CY30: 44 | CZ30: =IFERROR(CR30/F30,0) -> -0.054436581 | DA30: Lease cash / margin / financing | DB30: cash | DC30: lease | DD30: cash | DF30: 1 | DG30: 1 | DH30: 0 | DJ30: 0 | DK30: 0 | DL30: -0.054861907 | DM30: 0 | DN30: -0.054861907 | DO30: 1.883 | DP30: 1.833 | DU30: =IFERROR(DM30/F30,0) -> 0 | DV30: Keep cash / margin / financing | DW30: cash | DX30: keep | DY30: cash | EA30: 1 | EB30: 1 | EC30: 0 | EE30: 0 | EF30: 0 | EG30: 0 | EH30: 0 | EI30: 0 | EJ30: 1.883 | EK30: 1.833 | EP30: =IFERROR(EH30/F30,0) -> 0
A31: 25247 | B31: 25248 | C31: =B31-A31 -> 1 | D31: 25247 | E31: positive | F31: 0.95328708 | G31: 0.030678953 | H31: =SUM(CE31,CZ31,DU31,EP31,FK31,GF31,HA31,HV31,IQ31,JL31) -> 0.030678953 | I31: =G31-H31 -> -3.469447e-18 | J31: =F31*(1+H31) -> 0.98253293 | K31: 0.98253293 | L31: =K31-J31 -> 0 | M31: 1.833 | N31: 1.77 | O31: =M31/$M$3 -> 0.93615935 | P31: =N31/$M$3 -> 0.90398366 | Q31: =IFERROR(N31/M31-1,0) -> -0.034369885 | R31: =SUM(IF(BM31="lease",BU31,0),IF(CH31="lease",CP31,0),IF(DC31="lease",DK31,0),IF(DX31="lease",EF31,0),IF(ES31="lease",FA31,0),IF(FN31="lease",FV31,0),IF(GI31="lease",GQ31,0),IF(HD31="lease",HL31,0),IF(HY31="lease",IG31,0),IF(IT31="lease",JB31,0)) -> 0.95328708 | S31: =SUM(IF(BM31="lease",BV31,0),IF(CH31="lease",CQ31,0),IF(DC31="lease",DL31,0),IF(DX31="lease",EG31,0),IF(ES31="lease",FB31,0),IF(FN31="lease",FW31,0),IF(GI31="lease",GR31,0),IF(HD31="lease",HM31,0),IF(HY31="lease",IH31,0),IF(IT31="lease",JC31,0)) -> 0.98253293 | T31: =SUM(IF(BM31="keep",BU31,0),IF(CH31="keep",CP31,0),IF(DC31="keep",DK31,0),IF(DX31="keep",EF31,0),IF(ES31="keep",FA31,0),IF(FN31="keep",FV31,0),IF(GI31="keep",GQ31,0),IF(HD31="keep",HL31,0),IF(HY31="keep",IG31,0),IF(IT31="keep",JB31,0)) -> 0 | U31: =SUM(IF(BM31="keep",BV31,0),IF(CH31="keep",CQ31,0),IF(DC31="keep",DL31,0),IF(DX31="keep",EG31,0),IF(ES31="keep",FB31,0),IF(FN31="keep",FW31,0),IF(GI31="keep",GR31,0),IF(HD31="keep",HM31,0),IF(HY31="keep",IH31,0),IF(IT31="keep",JC31,0)) -> 0 | V31: =R31/O31 -> 1.0182957 | W31: =S31/P31 -> 1.0868924 | X31: =T31/O31 -> 0 | Y31: =U31/P31 -> 0 | Z31: =V31+X31 -> 1.0182957 | AA31: =IFERROR(W31/V31-1,0) -> 0.067364136 | AB31: =IFERROR((W31-V31)/Z31,0) -> 0.067364136 | AC31: =IFERROR(Y31/X31-1,0) -> 0 | AD31: =IFERROR((Y31-X31)/Z31,0) -> 0 | AE31: =AB31+AD31 -> 0.067364136 | AF31: =(1+Q31)*(1+AE31)-1 -> 0.030678953 | AG31: =G31-AF31 -> 1.9428903e-16 | AH31: =SUM(IF(BM31="lease",BW31,0),IF(CH31="lease",CR31,0),IF(DC31="lease",DM31,0),IF(DX31="lease",EH31,0),IF(ES31="lease",FC31,0),IF(FN31="lease",FX31,0),IF(GI31="lease",GS31,0),IF(HD31="lease",HN31,0),IF(HY31="lease",II31,0),IF(IT31="lease",JD31,0)) -> 0.029245849 | AI31: =SUM(IF(BM31="keep",BW31,0),IF(CH31="keep",CR31,0),IF(DC31="keep",DM31,0),IF(DX31="keep",EH31,0),IF(ES31="keep",FC31,0),IF(FN31="keep",FX31,0),IF(GI31="keep",GS31,0),IF(HD31="keep",HN31,0),IF(HY31="keep",II31,0),IF(IT31="keep",JD31,0)) -> 0 | AJ31: =SUM(IF(BM31="lease",BX31,0),IF(CH31="lease",CS31,0),IF(DC31="lease",DN31,0),IF(DX31="lease",EI31,0),IF(ES31="lease",FD31,0),IF(FN31="lease",FY31,0),IF(GI31="lease",GT31,0),IF(HD31="lease",HO31,0),IF(HY31="lease",IJ31,0),IF(IT31="lease",JE31,0)) -> 0 | AK31: =SUM(IF(BM31="keep",BX31,0),IF(CH31="keep",CS31,0),IF(DC31="keep",DN31,0),IF(DX31="keep",EI31,0),IF(ES31="keep",FD31,0),IF(FN31="keep",FY31,0),IF(GI31="keep",GT31,0),IF(HD31="keep",HO31,0),IF(HY31="keep",IJ31,0),IF(IT31="keep",JE31,0)) -> 0 | AL31: =R31-S30 -> 0 | AM31: =T31-U30 -> 0 | AN31: =AN30 -> 1 | AO31: =AO30+AH31 -> -0.017467074 | AP31: =AP30+AL31 -> -2.220446e-16 | AQ31: =AN31+AO31+AP31 -> 0.98253293 | AR31: =S31-AQ31 -> -2.220446e-16 | AS31: =AS30 -> 0 | AT31: =AT30+AI31 -> 0 | AU31: =AU30+AM31 -> 0 | AV31: =AS31+AT31+AU31 -> 0 | AW31: =U31-AV31 -> 0 | AX31: 0.95328708 | AY31: 0.98253293 | AZ31: =S31-AY31 -> 0 | BA31: 0 | BB31: 0 | BC31: =U31-BB31 -> 0 | BD31: =SUM(IF(BL31="direct",CE31,0),IF(CG31="direct",CZ31,0),IF(DB31="direct",DU31,0),IF(DW31="direct",EP31,0),IF(ER31="direct",FK31,0),IF(FM31="direct",GF31,0),IF(GH31="direct",HA31,0),IF(HC31="direct",HV31,0),IF(HX31="direct",IQ31,0),IF(IS31="direct",JL31,0)) -> 0 | BE31: =SUM(IF(BL31="treasury",CE31,0),IF(CG31="treasury",CZ31,0),IF(DB31="treasury",DU31,0),IF(DW31="treasury",EP31,0),IF(ER31="treasury",FK31,0),IF(FM31="treasury",GF31,0),IF(GH31="treasury",HA31,0),IF(HC31="treasury",HV31,0),IF(HX31="treasury",IQ31,0),IF(IS31="treasury",JL31,0)) -> 0.00016657534 | BF31: =SUM(IF(BL31="future",CE31,0),IF(CG31="future",CZ31,0),IF(DB31="future",DU31,0),IF(DW31="future",EP31,0),IF(ER31="future",FK31,0),IF(FM31="future",GF31,0),IF(GH31="future",HA31,0),IF(HC31="future",HV31,0),IF(HX31="future",IQ31,0),IF(IS31="future",JL31,0)) -> 0.030512378 | BG31: =SUM(IF(BL31="cash",CE31,0),IF(CG31="cash",CZ31,0),IF(DB31="cash",DU31,0),IF(DW31="cash",EP31,0),IF(ER31="cash",FK31,0),IF(FM31="cash",GF31,0),IF(GH31="cash",HA31,0),IF(HC31="cash",HV31,0),IF(HX31="cash",IQ31,0),IF(IS31="cash",JL31,0)) -> 0 | BH31: =SUM(BD31:BG31) -> 0.030678953 | BI31: =G31-BH31 -> 0 | BJ31: =COUNTA(BK31,CF31,DA31,DV31,EQ31,FL31,GG31,HB31,HW31,IR31) -> 4 | BK31: Treasury collateral | BL31: treasury | BM31: lease | BN31: long | BP31: 100.70915 | BQ31: 100.72592 | BR31: 0.0094657446 | BS31: 1 | BT31: 0.95328708 | BU31: 0.95328708 | BV31: 0.95344587 | BW31: 0.00015879412 | BX31: -1.9615928e-16 | BY31: 1.833 | BZ31: 1.77 | CD31: 42 | CE31: =IFERROR(BW31/F31,0) -> 0.00016657534 | CF31: SI69H | CG31: future | CH31: lease | CI31: long | CJ31: regular | CK31: 1.737 | CL31: 1.79 | CM31: 0.54881236 | CN31: 1 | CO31: 0.95328708 | CP31: 0 | CQ31: 0 | CR31: 0.029087055 | CS31: -0.029087055 | CT31: 1.833 | CU31: 1.77 | CV31: -0.052373159 | CW31: 0.0608 | CX31: 0.51594769 | CY31: 42 | CZ31: =IFERROR(CR31/F31,0) -> 0.030512378 | DA31: Lease cash / margin / financing | DB31: cash | DC31: lease | DD31: cash | DF31: 1 | DG31: 1 | DH31: -1.110223e-16 | DJ31: -1.110223e-16 | DK31: -1.110223e-16 | DL31: 0.029087055 | DM31: 0 | DN31: 0.029087055 | DO31: 1.833 | DP31: 1.77 | DU31: =IFERROR(DM31/F31,0) -> 0 | DV31: Keep cash / margin / financing | DW31: cash | DX31: keep | DY31: cash | EA31: 1 | EB31: 1 | EC31: 0 | EE31: 0 | EF31: 0 | EG31: 0 | EH31: 0 | EI31: 0 | EJ31: 1.833 | EK31: 1.77 | EP31: =IFERROR(EH31/F31,0) -> 0
A32: 25248 | B32: 25251 | C32: =B32-A32 -> 3 | D32: 25248 | E32: neutral | F32: 0.98253293 | G32: 0.048002051 | H32: =SUM(CE32,CZ32,DU32,EP32,FK32,GF32,HA32,HV32,IQ32,JL32) -> 0.048002051 | I32: =G32-H32 -> 0 | J32: =F32*(1+H32) -> 1.0296965 | K32: 1.0296965 | L32: =K32-J32 -> 0 | M32: 1.77 | N32: 1.855 | O32: =M32/$M$3 -> 0.90398366 | P32: =N32/$M$3 -> 0.9473953 | Q32: =IFERROR(N32/M32-1,0) -> 0.048022599 | R32: =SUM(IF(BM32="lease",BU32,0),IF(CH32="lease",CP32,0),IF(DC32="lease",DK32,0),IF(DX32="lease",EF32,0),IF(ES32="lease",FA32,0),IF(FN32="lease",FV32,0),IF(GI32="lease",GQ32,0),IF(HD32="lease",HL32,0),IF(HY32="lease",IG32,0),IF(IT32="lease",JB32,0)) -> 0.98253293 | S32: =SUM(IF(BM32="lease",BV32,0),IF(CH32="lease",CQ32,0),IF(DC32="lease",DL32,0),IF(DX32="lease",EG32,0),IF(ES32="lease",FB32,0),IF(FN32="lease",FW32,0),IF(GI32="lease",GR32,0),IF(HD32="lease",HM32,0),IF(HY32="lease",IH32,0),IF(IT32="lease",JC32,0)) -> 1.0296965 | T32: =SUM(IF(BM32="keep",BU32,0),IF(CH32="keep",CP32,0),IF(DC32="keep",DK32,0),IF(DX32="keep",EF32,0),IF(ES32="keep",FA32,0),IF(FN32="keep",FV32,0),IF(GI32="keep",GQ32,0),IF(HD32="keep",HL32,0),IF(HY32="keep",IG32,0),IF(IT32="keep",JB32,0)) -> 0 | U32: =SUM(IF(BM32="keep",BV32,0),IF(CH32="keep",CQ32,0),IF(DC32="keep",DL32,0),IF(DX32="keep",EG32,0),IF(ES32="keep",FB32,0),IF(FN32="keep",FW32,0),IF(GI32="keep",GR32,0),IF(HD32="keep",HM32,0),IF(HY32="keep",IH32,0),IF(IT32="keep",JC32,0)) -> 0 | V32: =R32/O32 -> 1.0868924 | W32: =S32/P32 -> 1.086871 | X32: =T32/O32 -> 0 | Y32: =U32/P32 -> 0 | Z32: =V32+X32 -> 1.0868924 | AA32: =IFERROR(W32/V32-1,0) -> -1.9606395e-05 | AB32: =IFERROR((W32-V32)/Z32,0) -> -1.9606395e-05 | AC32: =IFERROR(Y32/X32-1,0) -> 0 | AD32: =IFERROR((Y32-X32)/Z32,0) -> 0 | AE32: =AB32+AD32 -> -1.9606395e-05 | AF32: =(1+Q32)*(1+AE32)-1 -> 0.048002051 | AG32: =G32-AF32 -> 8.3266727e-17 | AH32: =SUM(IF(BM32="lease",BW32,0),IF(CH32="lease",CR32,0),IF(DC32="lease",DM32,0),IF(DX32="lease",EH32,0),IF(ES32="lease",FC32,0),IF(FN32="lease",FX32,0),IF(GI32="lease",GS32,0),IF(HD32="lease",HN32,0),IF(HY32="lease",II32,0),IF(IT32="lease",JD32,0)) -> 0.047163596 | AI32: =SUM(IF(BM32="keep",BW32,0),IF(CH32="keep",CR32,0),IF(DC32="keep",DM32,0),IF(DX32="keep",EH32,0),IF(ES32="keep",FC32,0),IF(FN32="keep",FX32,0),IF(GI32="keep",GS32,0),IF(HD32="keep",HN32,0),IF(HY32="keep",II32,0),IF(IT32="keep",JD32,0)) -> 0 | AJ32: =SUM(IF(BM32="lease",BX32,0),IF(CH32="lease",CS32,0),IF(DC32="lease",DN32,0),IF(DX32="lease",EI32,0),IF(ES32="lease",FD32,0),IF(FN32="lease",FY32,0),IF(GI32="lease",GT32,0),IF(HD32="lease",HO32,0),IF(HY32="lease",IJ32,0),IF(IT32="lease",JE32,0)) -> 0 | AK32: =SUM(IF(BM32="keep",BX32,0),IF(CH32="keep",CS32,0),IF(DC32="keep",DN32,0),IF(DX32="keep",EI32,0),IF(ES32="keep",FD32,0),IF(FN32="keep",FY32,0),IF(GI32="keep",GT32,0),IF(HD32="keep",HO32,0),IF(HY32="keep",IJ32,0),IF(IT32="keep",JE32,0)) -> 0 | AL32: =R32-S31 -> 0 | AM32: =T32-U31 -> 0 | AN32: =AN31 -> 1 | AO32: =AO31+AH32 -> 0.029696522 | AP32: =AP31+AL32 -> -2.220446e-16 | AQ32: =AN32+AO32+AP32 -> 1.0296965 | AR32: =S32-AQ32 -> -2.220446e-16 | AS32: =AS31 -> 0 | AT32: =AT31+AI32 -> 0 | AU32: =AU31+AM32 -> 0 | AV32: =AS32+AT32+AU32 -> 0 | AW32: =U32-AV32 -> 0 | AX32: 0.98253293 | AY32: 1.0296965 | AZ32: =S32-AY32 -> 0 | BA32: 0 | BB32: 0 | BC32: =U32-BB32 -> 0 | BD32: =SUM(IF(BL32="direct",CE32,0),IF(CG32="direct",CZ32,0),IF(DB32="direct",DU32,0),IF(DW32="direct",EP32,0),IF(ER32="direct",FK32,0),IF(FM32="direct",GF32,0),IF(GH32="direct",HA32,0),IF(HC32="direct",HV32,0),IF(HX32="direct",IQ32,0),IF(IS32="direct",JL32,0)) -> 0.048002051 | BE32: =SUM(IF(BL32="treasury",CE32,0),IF(CG32="treasury",CZ32,0),IF(DB32="treasury",DU32,0),IF(DW32="treasury",EP32,0),IF(ER32="treasury",FK32,0),IF(FM32="treasury",GF32,0),IF(GH32="treasury",HA32,0),IF(HC32="treasury",HV32,0),IF(HX32="treasury",IQ32,0),IF(IS32="treasury",JL32,0)) -> 0 | BF32: =SUM(IF(BL32="future",CE32,0),IF(CG32="future",CZ32,0),IF(DB32="future",DU32,0),IF(DW32="future",EP32,0),IF(ER32="future",FK32,0),IF(FM32="future",GF32,0),IF(GH32="future",HA32,0),IF(HC32="future",HV32,0),IF(HX32="future",IQ32,0),IF(IS32="future",JL32,0)) -> 0 | BG32: =SUM(IF(BL32="cash",CE32,0),IF(CG32="cash",CZ32,0),IF(DB32="cash",DU32,0),IF(DW32="cash",EP32,0),IF(ER32="cash",FK32,0),IF(FM32="cash",GF32,0),IF(GH32="cash",HA32,0),IF(HC32="cash",HV32,0),IF(HX32="cash",IQ32,0),IF(IS32="cash",JL32,0)) -> 0 | BH32: =SUM(BD32:BG32) -> 0.048002051 | BI32: =G32-BH32 -> 0 | BJ32: =COUNTA(BK32,CF32,DA32,DV32,EQ32,FL32,GG32,HB32,HW32,IR32) -> 3 | BK32: Direct commodity holding | BL32: direct | BM32: lease | BN32: long | BP32: 1.77 | BQ32: 1.855 | BR32: 0.55510335 | BS32: 1 | BT32: 0.98253293 | BU32: 0.98253293 | BV32: 1.0297167 | BW32: 0.047163596 | BX32: 2.0189033e-05 | BY32: 1.77 | BZ32: 1.855 | CE32: =IFERROR(BW32/F32,0) -> 0.048002051 | CF32: Lease cash / margin / financing | CG32: cash | CH32: lease | CI32: cash | CK32: 1 | CL32: 1 | CM32: -1.110223e-16 | CO32: -1.110223e-16 | CP32: -1.110223e-16 | CQ32: -2.0189033e-05 | CR32: 0 | CS32: -2.0189033e-05 | CT32: 1.77 | CU32: 1.855 | CZ32: =IFERROR(CR32/F32,0) -> 0 | DA32: Keep cash / margin / financing | DB32: cash | DC32: keep | DD32: cash | DF32: 1 | DG32: 1 | DH32: 0 | DJ32: 0 | DK32: 0 | DL32: 0 | DM32: 0 | DN32: 0 | DO32: 1.77 | DP32: 1.855 | DU32: =IFERROR(DM32/F32,0) -> 0
A33: 25251 | B33: 25252 | C33: =B33-A33 -> 1 | D33: 25251 | E33: positive | F33: 1.0296965 | G33: 0.021574478 | H33: =SUM(CE33,CZ33,DU33,EP33,FK33,GF33,HA33,HV33,IQ33,JL33) -> 0.021574478 | I33: =G33-H33 -> -3.469447e-18 | J33: =F33*(1+H33) -> 1.0519117 | K33: 1.0519117 | L33: =K33-J33 -> 0 | M33: 1.855 | N33: 1.804 | O33: =M33/$M$3 -> 0.9473953 | P33: =N33/$M$3 -> 0.92134831 | Q33: =IFERROR(N33/M33-1,0) -> -0.027493261 | R33: =SUM(IF(BM33="lease",BU33,0),IF(CH33="lease",CP33,0),IF(DC33="lease",DK33,0),IF(DX33="lease",EF33,0),IF(ES33="lease",FA33,0),IF(FN33="lease",FV33,0),IF(GI33="lease",GQ33,0),IF(HD33="lease",HL33,0),IF(HY33="lease",IG33,0),IF(IT33="lease",JB33,0)) -> 1.0296965 | S33: =SUM(IF(BM33="lease",BV33,0),IF(CH33="lease",CQ33,0),IF(DC33="lease",DL33,0),IF(DX33="lease",EG33,0),IF(ES33="lease",FB33,0),IF(FN33="lease",FW33,0),IF(GI33="lease",GR33,0),IF(HD33="lease",HM33,0),IF(HY33="lease",IH33,0),IF(IT33="lease",JC33,0)) -> 1.0519117 | T33: =SUM(IF(BM33="keep",BU33,0),IF(CH33="keep",CP33,0),IF(DC33="keep",DK33,0),IF(DX33="keep",EF33,0),IF(ES33="keep",FA33,0),IF(FN33="keep",FV33,0),IF(GI33="keep",GQ33,0),IF(HD33="keep",HL33,0),IF(HY33="keep",IG33,0),IF(IT33="keep",JB33,0)) -> 0 | U33: =SUM(IF(BM33="keep",BV33,0),IF(CH33="keep",CQ33,0),IF(DC33="keep",DL33,0),IF(DX33="keep",EG33,0),IF(ES33="keep",FB33,0),IF(FN33="keep",FW33,0),IF(GI33="keep",GR33,0),IF(HD33="keep",HM33,0),IF(HY33="keep",IH33,0),IF(IT33="keep",JC33,0)) -> 0 | V33: =R33/O33 -> 1.086871 | W33: =S33/P33 -> 1.141709 | X33: =T33/O33 -> 0 | Y33: =U33/P33 -> 0 | Z33: =V33+X33 -> 1.086871 | AA33: =IFERROR(W33/V33-1,0) -> 0.05045491 | AB33: =IFERROR((W33-V33)/Z33,0) -> 0.05045491 | AC33: =IFERROR(Y33/X33-1,0) -> 0 | AD33: =IFERROR((Y33-X33)/Z33,0) -> 0 | AE33: =AB33+AD33 -> 0.05045491 | AF33: =(1+Q33)*(1+AE33)-1 -> 0.021574478 | AG33: =G33-AF33 -> -7.6327833e-17 | AH33: =SUM(IF(BM33="lease",BW33,0),IF(CH33="lease",CR33,0),IF(DC33="lease",DM33,0),IF(DX33="lease",EH33,0),IF(ES33="lease",FC33,0),IF(FN33="lease",FX33,0),IF(GI33="lease",GS33,0),IF(HD33="lease",HN33,0),IF(HY33="lease",II33,0),IF(IT33="lease",JD33,0)) -> 0.022215165 | AI33: =SUM(IF(BM33="keep",BW33,0),IF(CH33="keep",CR33,0),IF(DC33="keep",DM33,0),IF(DX33="keep",EH33,0),IF(ES33="keep",FC33,0),IF(FN33="keep",FX33,0),IF(GI33="keep",GS33,0),IF(HD33="keep",HN33,0),IF(HY33="keep",II33,0),IF(IT33="keep",JD33,0)) -> 0 | AJ33: =SUM(IF(BM33="lease",BX33,0),IF(CH33="lease",CS33,0),IF(DC33="lease",DN33,0),IF(DX33="lease",EI33,0),IF(ES33="lease",FD33,0),IF(FN33="lease",FY33,0),IF(GI33="lease",GT33,0),IF(HD33="lease",HO33,0),IF(HY33="lease",IJ33,0),IF(IT33="lease",JE33,0)) -> 0 | AK33: =SUM(IF(BM33="keep",BX33,0),IF(CH33="keep",CS33,0),IF(DC33="keep",DN33,0),IF(DX33="keep",EI33,0),IF(ES33="keep",FD33,0),IF(FN33="keep",FY33,0),IF(GI33="keep",GT33,0),IF(HD33="keep",HO33,0),IF(HY33="keep",IJ33,0),IF(IT33="keep",JE33,0)) -> 0 | AL33: =R33-S32 -> 0 | AM33: =T33-U32 -> 0 | AN33: =AN32 -> 1 | AO33: =AO32+AH33 -> 0.051911687 | AP33: =AP32+AL33 -> -2.220446e-16 | AQ33: =AN33+AO33+AP33 -> 1.0519117 | AR33: =S33-AQ33 -> -2.220446e-16 | AS33: =AS32 -> 0 | AT33: =AT32+AI33 -> 0 | AU33: =AU32+AM33 -> 0 | AV33: =AS33+AT33+AU33 -> 0 | AW33: =U33-AV33 -> 0 | AX33: 1.0296965 | AY33: 1.0519117 | AZ33: =S33-AY33 -> 0 | BA33: 0 | BB33: 0 | BC33: =U33-BB33 -> 0 | BD33: =SUM(IF(BL33="direct",CE33,0),IF(CG33="direct",CZ33,0),IF(DB33="direct",DU33,0),IF(DW33="direct",EP33,0),IF(ER33="direct",FK33,0),IF(FM33="direct",GF33,0),IF(GH33="direct",HA33,0),IF(HC33="direct",HV33,0),IF(HX33="direct",IQ33,0),IF(IS33="direct",JL33,0)) -> 0 | BE33: =SUM(IF(BL33="treasury",CE33,0),IF(CG33="treasury",CZ33,0),IF(DB33="treasury",DU33,0),IF(DW33="treasury",EP33,0),IF(ER33="treasury",FK33,0),IF(FM33="treasury",GF33,0),IF(GH33="treasury",HA33,0),IF(HC33="treasury",HV33,0),IF(HX33="treasury",IQ33,0),IF(IS33="treasury",JL33,0)) -> 0.0001660274 | BF33: =SUM(IF(BL33="future",CE33,0),IF(CG33="future",CZ33,0),IF(DB33="future",DU33,0),IF(DW33="future",EP33,0),IF(ER33="future",FK33,0),IF(FM33="future",GF33,0),IF(GH33="future",HA33,0),IF(HC33="future",HV33,0),IF(HX33="future",IQ33,0),IF(IS33="future",JL33,0)) -> 0.021408451 | BG33: =SUM(IF(BL33="cash",CE33,0),IF(CG33="cash",CZ33,0),IF(DB33="cash",DU33,0),IF(DW33="cash",EP33,0),IF(ER33="cash",FK33,0),IF(FM33="cash",GF33,0),IF(GH33="cash",HA33,0),IF(HC33="cash",HV33,0),IF(HX33="cash",IQ33,0),IF(IS33="cash",JL33,0)) -> 0 | BH33: =SUM(BD33:BG33) -> 0.021574478 | BI33: =G33-BH33 -> 0 | BJ33: =COUNTA(BK33,CF33,DA33,DV33,EQ33,FL33,GG33,HB33,HW33,IR33) -> 5 | BK33: Treasury collateral | BL33: treasury | BM33: lease | BN33: long | BP33: 100.77601 | BQ33: 100.79274 | BR33: 0.010217675 | BS33: 1 | BT33: 1.0296965 | BU33: 1.0296965 | BV33: 1.0298675 | BW33: 0.00017095783 | BX33: -1.5265567e-16 | BY33: 1.855 | BZ33: 1.804 | CD33: 38 | CE33: =IFERROR(BW33/F33,0) -> 0.0001660274 | CF33: SI69H | CG33: future | CH33: lease | CI33: long | CJ33: regular | CK33: 1.775 | CL33: 1.813 | CM33: 0.58011072 | CN33: 1 | CO33: 1.0296965 | CP33: 0 | CQ33: 0 | CR33: 0.022044207 | CS33: -0.022044207 | CT33: 1.855 | CU33: 1.804 | CV33: -0.043126685 | CW33: 0.0606 | CX33: 0.47484316 | CY33: 38 | CZ33: =IFERROR(CR33/F33,0) -> 0.021408451 | DA33: SI69K | DB33: future | DC33: lease | DD33: long | DE33: regular | DF33: 1.808 | DG33: 1.847 | DH33: 6.1612113e-15 | DI33: 1.0818207e-14 | DJ33: 1.113947e-14 | DK33: 0 | DL33: 0 | DM33: 2.4028724e-16 | DN33: -2.4028724e-16 | DO33: 1.855 | DP33: 1.804 | DQ33: -0.025336927 | DR33: 0.060787912 | DS33: 0.1532677 | DT33: 100 | DU33: =IFERROR(DM33/F33,0) -> 2.3335734e-16 | DV33: Lease cash / margin / financing | DW33: cash | DX33: lease | DY33: cash | EA33: 1 | EB33: 1 | EC33: 0 | EE33: 0 | EF33: 0 | EG33: 0.022044207 | EH33: 0 | EI33: 0.022044207 | EJ33: 1.855 | EK33: 1.804 | EP33: =IFERROR(EH33/F33,0) -> 0 | EQ33: Keep cash / margin / financing | ER33: cash | ES33: keep | ET33: cash | EV33: 1 | EW33: 1 | EX33: 0 | EZ33: 0 | FA33: 0 | FB33: 0 | FC33: 0 | FD33: 0 | FE33: 1.855 | FF33: 1.804 | FK33: =IFERROR(FC33/F33,0) -> 0
A34: 25252 | B34: 25253 | C34: =B34-A34 -> 1 | D34: 25252 | E34: positive | F34: 1.0519117 | G34: 0.013272709 | H34: =SUM(CE34,CZ34,DU34,EP34,FK34,GF34,HA34,HV34,IQ34,JL34) -> 0.013272709 | I34: =G34-H34 -> 0 | J34: =F34*(1+H34) -> 1.0658734 | K34: 1.0658734 | L34: =K34-J34 -> 0 | M34: 1.804 | N34: 1.829 | O34: =M34/$M$3 -> 0.92134831 | P34: =N34/$M$3 -> 0.93411645 | Q34: =IFERROR(N34/M34-1,0) -> 0.013858093 | R34: =SUM(IF(BM34="lease",BU34,0),IF(CH34="lease",CP34,0),IF(DC34="lease",DK34,0),IF(DX34="lease",EF34,0),IF(ES34="lease",FA34,0),IF(FN34="lease",FV34,0),IF(GI34="lease",GQ34,0),IF(HD34="lease",HL34,0),IF(HY34="lease",IG34,0),IF(IT34="lease",JB34,0)) -> 1.0519117 | S34: =SUM(IF(BM34="lease",BV34,0),IF(CH34="lease",CQ34,0),IF(DC34="lease",DL34,0),IF(DX34="lease",EG34,0),IF(ES34="lease",FB34,0),IF(FN34="lease",FW34,0),IF(GI34="lease",GR34,0),IF(HD34="lease",HM34,0),IF(HY34="lease",IH34,0),IF(IT34="lease",JC34,0)) -> 1.0658734 | T34: =SUM(IF(BM34="keep",BU34,0),IF(CH34="keep",CP34,0),IF(DC34="keep",DK34,0),IF(DX34="keep",EF34,0),IF(ES34="keep",FA34,0),IF(FN34="keep",FV34,0),IF(GI34="keep",GQ34,0),IF(HD34="keep",HL34,0),IF(HY34="keep",IG34,0),IF(IT34="keep",JB34,0)) -> 0 | U34: =SUM(IF(BM34="keep",BV34,0),IF(CH34="keep",CQ34,0),IF(DC34="keep",DL34,0),IF(DX34="keep",EG34,0),IF(ES34="keep",FB34,0),IF(FN34="keep",FW34,0),IF(GI34="keep",GR34,0),IF(HD34="keep",HM34,0),IF(HY34="keep",IH34,0),IF(IT34="keep",JC34,0)) -> 0 | V34: =R34/O34 -> 1.141709 | W34: =S34/P34 -> 1.1410498 | X34: =T34/O34 -> 0 | Y34: =U34/P34 -> 0 | Z34: =V34+X34 -> 1.141709 | AA34: =IFERROR(W34/V34-1,0) -> -0.00057738223 | AB34: =IFERROR((W34-V34)/Z34,0) -> -0.00057738223 | AC34: =IFERROR(Y34/X34-1,0) -> 0 | AD34: =IFERROR((Y34-X34)/Z34,0) -> 0 | AE34: =AB34+AD34 -> -0.00057738223 | AF34: =(1+Q34)*(1+AE34)-1 -> 0.013272709 | AG34: =G34-AF34 -> -6.4184769e-17 | AH34: =SUM(IF(BM34="lease",BW34,0),IF(CH34="lease",CR34,0),IF(DC34="lease",DM34,0),IF(DX34="lease",EH34,0),IF(ES34="lease",FC34,0),IF(FN34="lease",FX34,0),IF(GI34="lease",GS34,0),IF(HD34="lease",HN34,0),IF(HY34="lease",II34,0),IF(IT34="lease",JD34,0)) -> 0.013961718 | AI34: =SUM(IF(BM34="keep",BW34,0),IF(CH34="keep",CR34,0),IF(DC34="keep",DM34,0),IF(DX34="keep",EH34,0),IF(ES34="keep",FC34,0),IF(FN34="keep",FX34,0),IF(GI34="keep",GS34,0),IF(HD34="keep",HN34,0),IF(HY34="keep",II34,0),IF(IT34="keep",JD34,0)) -> 0 | AJ34: =SUM(IF(BM34="lease",BX34,0),IF(CH34="lease",CS34,0),IF(DC34="lease",DN34,0),IF(DX34="lease",EI34,0),IF(ES34="lease",FD34,0),IF(FN34="lease",FY34,0),IF(GI34="lease",GT34,0),IF(HD34="lease",HO34,0),IF(HY34="lease",IJ34,0),IF(IT34="lease",JE34,0)) -> 0 | AK34: =SUM(IF(BM34="keep",BX34,0),IF(CH34="keep",CS34,0),IF(DC34="keep",DN34,0),IF(DX34="keep",EI34,0),IF(ES34="keep",FD34,0),IF(FN34="keep",FY34,0),IF(GI34="keep",GT34,0),IF(HD34="keep",HO34,0),IF(HY34="keep",IJ34,0),IF(IT34="keep",JE34,0)) -> 0 | AL34: =R34-S33 -> 0 | AM34: =T34-U33 -> 0 | AN34: =AN33 -> 1 | AO34: =AO33+AH34 -> 0.065873405 | AP34: =AP33+AL34 -> -2.220446e-16 | AQ34: =AN34+AO34+AP34 -> 1.0658734 | AR34: =S34-AQ34 -> 0 | AS34: =AS33 -> 0 | AT34: =AT33+AI34 -> 0 | AU34: =AU33+AM34 -> 0 | AV34: =AS34+AT34+AU34 -> 0 | AW34: =U34-AV34 -> 0 | AX34: 1.0519117 | AY34: 1.0658734 | AZ34: =S34-AY34 -> 2.220446e-16 | BA34: 0 | BB34: 0 | BC34: =U34-BB34 -> 0 | BD34: =SUM(IF(BL34="direct",CE34,0),IF(CG34="direct",CZ34,0),IF(DB34="direct",DU34,0),IF(DW34="direct",EP34,0),IF(ER34="direct",FK34,0),IF(FM34="direct",GF34,0),IF(GH34="direct",HA34,0),IF(HC34="direct",HV34,0),IF(HX34="direct",IQ34,0),IF(IS34="direct",JL34,0)) -> 0.012716823 | BE34: =SUM(IF(BL34="treasury",CE34,0),IF(CG34="treasury",CZ34,0),IF(DB34="treasury",DU34,0),IF(DW34="treasury",EP34,0),IF(ER34="treasury",FK34,0),IF(FM34="treasury",GF34,0),IF(GH34="treasury",HA34,0),IF(HC34="treasury",HV34,0),IF(HX34="treasury",IQ34,0),IF(IS34="treasury",JL34,0)) -> 1.3799636e-05 | BF34: =SUM(IF(BL34="future",CE34,0),IF(CG34="future",CZ34,0),IF(DB34="future",DU34,0),IF(DW34="future",EP34,0),IF(ER34="future",FK34,0),IF(FM34="future",GF34,0),IF(GH34="future",HA34,0),IF(HC34="future",HV34,0),IF(HX34="future",IQ34,0),IF(IS34="future",JL34,0)) -> 0.00054208681 | BG34: =SUM(IF(BL34="cash",CE34,0),IF(CG34="cash",CZ34,0),IF(DB34="cash",DU34,0),IF(DW34="cash",EP34,0),IF(ER34="cash",FK34,0),IF(FM34="cash",GF34,0),IF(GH34="cash",HA34,0),IF(HC34="cash",HV34,0),IF(HX34="cash",IQ34,0),IF(IS34="cash",JL34,0)) -> 0 | BH34: =SUM(BD34:BG34) -> 0.013272709 | BI34: =G34-BH34 -> 0 | BJ34: =COUNTA(BK34,CF34,DA34,DV34,EQ34,FL34,GG34,HB34,HW34,IR34) -> 5 | BK34: Direct commodity holding | BL34: direct | BM34: lease | BN34: long | BP34: 1.804 | BQ34: 1.829 | BR34: 0.53534358 | BS34: 0.91809972 | BT34: 0.96575982 | BU34: 0.96575982 | BV34: 0.97914341 | BW34: 0.013376975 | BX34: 6.6147933e-06 | BY34: 1.804 | BZ34: 1.829 | CE34: =IFERROR(BW34/F34,0) -> 0.012716823 | CF34: Treasury collateral | CG34: treasury | CH34: lease | CI34: long | CK34: 100.79274 | CL34: 100.80973 | CM34: 0.00085474273 | CN34: 0.081900282 | CO34: 0.086151863 | CP34: 0.086151863 | CQ34: 0.086166379 | CR34: 1.4515999e-05 | CS34: 1.254117e-17 | CT34: 1.804 | CU34: 1.829 | CY34: 37 | CZ34: =IFERROR(CR34/F34,0) -> 1.3799636e-05 | DA34: SI69H | DB34: future | DC34: lease | DD34: long | DE34: regular | DF34: 1.813 | DG34: 1.825 | DH34: 0.047518954 | DI34: 0.081900282 | DJ34: 0.086151863 | DK34: 0 | DL34: 0 | DM34: 0.00057022745 | DN34: -0.00057022745 | DO34: 1.804 | DP34: 1.829 | DQ34: 0.0049889135 | DR34: 0.0615 | DS34: 0.012285042 | DT34: 37 | DU34: =IFERROR(DM34/F34,0) -> 0.00054208681 | DV34: Lease cash / margin / financing | DW34: cash | DX34: lease | DY34: cash | EA34: 1 | EB34: 1 | EC34: 0 | EE34: 0 | EF34: 0 | EG34: 0.00056361265 | EH34: 0 | EI34: 0.00056361265 | EJ34: 1.804 | EK34: 1.829 | EP34: =IFERROR(EH34/F34,0) -> 0 | EQ34: Keep cash / margin / financing | ER34: cash | ES34: keep | ET34: cash | EV34: 1 | EW34: 1 | EX34: 0 | EZ34: 0 | FA34: 0 | FB34: 0 | FC34: 0 | FD34: 0 | FE34: 1.804 | FF34: 1.829 | FK34: =IFERROR(FC34/F34,0) -> 0
A35: 25253 | B35: 25254 | C35: =B35-A35 -> 1 | D35: 25253 | E35: positive | F35: 1.0658734 | G35: 0.0037857017 | H35: =SUM(CE35,CZ35,DU35,EP35,FK35,GF35,HA35,HV35,IQ35,JL35) -> 0.0037857017 | I35: =G35-H35 -> -8.6736174e-19 | J35: =F35*(1+H35) -> 1.0699085 | K35: 1.0699085 | L35: =K35-J35 -> 0 | M35: 1.829 | N35: 1.843 | O35: =M35/$M$3 -> 0.93411645 | P35: =N35/$M$3 -> 0.9412666 | Q35: =IFERROR(N35/M35-1,0) -> 0.007654456 | R35: =SUM(IF(BM35="lease",BU35,0),IF(CH35="lease",CP35,0),IF(DC35="lease",DK35,0),IF(DX35="lease",EF35,0),IF(ES35="lease",FA35,0),IF(FN35="lease",FV35,0),IF(GI35="lease",GQ35,0),IF(HD35="lease",HL35,0),IF(HY35="lease",IG35,0),IF(IT35="lease",JB35,0)) -> 1.0658734 | S35: =SUM(IF(BM35="lease",BV35,0),IF(CH35="lease",CQ35,0),IF(DC35="lease",DL35,0),IF(DX35="lease",EG35,0),IF(ES35="lease",FB35,0),IF(FN35="lease",FW35,0),IF(GI35="lease",GR35,0),IF(HD35="lease",HM35,0),IF(HY35="lease",IH35,0),IF(IT35="lease",JC35,0)) -> 1.0699085 | T35: =SUM(IF(BM35="keep",BU35,0),IF(CH35="keep",CP35,0),IF(DC35="keep",DK35,0),IF(DX35="keep",EF35,0),IF(ES35="keep",FA35,0),IF(FN35="keep",FV35,0),IF(GI35="keep",GQ35,0),IF(HD35="keep",HL35,0),IF(HY35="keep",IG35,0),IF(IT35="keep",JB35,0)) -> 0 | U35: =SUM(IF(BM35="keep",BV35,0),IF(CH35="keep",CQ35,0),IF(DC35="keep",DL35,0),IF(DX35="keep",EG35,0),IF(ES35="keep",FB35,0),IF(FN35="keep",FW35,0),IF(GI35="keep",GR35,0),IF(HD35="keep",HM35,0),IF(HY35="keep",IH35,0),IF(IT35="keep",JC35,0)) -> 0 | V35: =R35/O35 -> 1.1410498 | W35: =S35/P35 -> 1.1366689 | X35: =T35/O35 -> 0 | Y35: =U35/P35 -> 0 | Z35: =V35+X35 -> 1.1410498 | AA35: =IFERROR(W35/V35-1,0) -> -0.003839366 | AB35: =IFERROR((W35-V35)/Z35,0) -> -0.003839366 | AC35: =IFERROR(Y35/X35-1,0) -> 0 | AD35: =IFERROR((Y35-X35)/Z35,0) -> 0 | AE35: =AB35+AD35 -> -0.003839366 | AF35: =(1+Q35)*(1+AE35)-1 -> 0.0037857017 | AG35: =G35-AF35 -> -1.8778382e-16 | AH35: =SUM(IF(BM35="lease",BW35,0),IF(CH35="lease",CR35,0),IF(DC35="lease",DM35,0),IF(DX35="lease",EH35,0),IF(ES35="lease",FC35,0),IF(FN35="lease",FX35,0),IF(GI35="lease",GS35,0),IF(HD35="lease",HN35,0),IF(HY35="lease",II35,0),IF(IT35="lease",JD35,0)) -> 0.0040350788 | AI35: =SUM(IF(BM35="keep",BW35,0),IF(CH35="keep",CR35,0),IF(DC35="keep",DM35,0),IF(DX35="keep",EH35,0),IF(ES35="keep",FC35,0),IF(FN35="keep",FX35,0),IF(GI35="keep",GS35,0),IF(HD35="keep",HN35,0),IF(HY35="keep",II35,0),IF(IT35="keep",JD35,0)) -> 0 | AJ35: =SUM(IF(BM35="lease",BX35,0),IF(CH35="lease",CS35,0),IF(DC35="lease",DN35,0),IF(DX35="lease",EI35,0),IF(ES35="lease",FD35,0),IF(FN35="lease",FY35,0),IF(GI35="lease",GT35,0),IF(HD35="lease",HO35,0),IF(HY35="lease",IJ35,0),IF(IT35="lease",JE35,0)) -> 0 | AK35: =SUM(IF(BM35="keep",BX35,0),IF(CH35="keep",CS35,0),IF(DC35="keep",DN35,0),IF(DX35="keep",EI35,0),IF(ES35="keep",FD35,0),IF(FN35="keep",FY35,0),IF(GI35="keep",GT35,0),IF(HD35="keep",HO35,0),IF(HY35="keep",IJ35,0),IF(IT35="keep",JE35,0)) -> 0 | AL35: =R35-S34 -> -2.220446e-16 | AM35: =T35-U34 -> 0 | AN35: =AN34 -> 1 | AO35: =AO34+AH35 -> 0.069908484 | AP35: =AP34+AL35 -> -4.4408921e-16 | AQ35: =AN35+AO35+AP35 -> 1.0699085 | AR35: =S35-AQ35 -> 2.220446e-16 | AS35: =AS34 -> 0 | AT35: =AT34+AI35 -> 0 | AU35: =AU34+AM35 -> 0 | AV35: =AS35+AT35+AU35 -> 0 | AW35: =U35-AV35 -> 0 | AX35: 1.0658734 | AY35: 1.0699085 | AZ35: =S35-AY35 -> 2.220446e-16 | BA35: 0 | BB35: 0 | BC35: =U35-BB35 -> 0 | BD35: =SUM(IF(BL35="direct",CE35,0),IF(CG35="direct",CZ35,0),IF(DB35="direct",DU35,0),IF(DW35="direct",EP35,0),IF(ER35="direct",FK35,0),IF(FM35="direct",GF35,0),IF(GH35="direct",HA35,0),IF(HC35="direct",HV35,0),IF(HX35="direct",IQ35,0),IF(IS35="direct",JL35,0)) -> 0.0033866854 | BE35: =SUM(IF(BL35="treasury",CE35,0),IF(CG35="treasury",CZ35,0),IF(DB35="treasury",DU35,0),IF(DW35="treasury",EP35,0),IF(ER35="treasury",FK35,0),IF(FM35="treasury",GF35,0),IF(GH35="treasury",HA35,0),IF(HC35="treasury",HV35,0),IF(HX35="treasury",IQ35,0),IF(IS35="treasury",JL35,0)) -> 9.3724574e-05 | BF35: =SUM(IF(BL35="future",CE35,0),IF(CG35="future",CZ35,0),IF(DB35="future",DU35,0),IF(DW35="future",EP35,0),IF(ER35="future",FK35,0),IF(FM35="future",GF35,0),IF(GH35="future",HA35,0),IF(HC35="future",HV35,0),IF(HX35="future",IQ35,0),IF(IS35="future",JL35,0)) -> 0.00030529177 | BG35: =SUM(IF(BL35="cash",CE35,0),IF(CG35="cash",CZ35,0),IF(DB35="cash",DU35,0),IF(DW35="cash",EP35,0),IF(ER35="cash",FK35,0),IF(FM35="cash",GF35,0),IF(GH35="cash",HA35,0),IF(HC35="cash",HV35,0),IF(HX35="cash",IQ35,0),IF(IS35="cash",JL35,0)) -> 0 | BH35: =SUM(BD35:BG35) -> 0.0037857017 | BI35: =G35-BH35 -> -4.3368087e-19 | BJ35: =COUNTA(BK35,CF35,DA35,DV35,EQ35,FL35,GG35,HB35,HW35,IR35) -> 5 | BK35: Direct commodity holding | BL35: direct | BM35: lease | BN35: long | BP35: 1.829 | BQ35: 1.843 | BR35: 0.2580722 | BS35: 0.44284252 | BT35: 0.47201406 | BU35: 0.47201406 | BV35: 0.47562707 | BW35: 0.0036097779 | BX35: 3.232973e-06 | BY35: 1.829 | BZ35: 1.843 | CE35: =IFERROR(BW35/F35,0) -> 0.0033866854 | CF35: Treasury collateral | CG35: treasury | CH35: lease | CI35: long | CK35: 100.80973 | CL35: 100.82668 | CM35: 0.0058908934 | CN35: 0.55715748 | CO35: 0.59385934 | CP35: 0.59385934 | CQ35: 0.59395924 | CR35: 9.9898531e-05 | CS35: -5.7964159e-17 | CT35: 1.829 | CU35: 1.843 | CY35: 36 | CZ35: =IFERROR(CR35/F35,0) -> 9.3724574e-05 | DA35: SI69H | DB35: future | DC35: lease | DD35: long | DE35: regular | DF35: 1.825 | DG35: 1.826 | DH35: 0.32540238 | DI35: 0.55715748 | DJ35: 0.59385934 | DK35: 0 | DL35: 0 | DM35: 0.00032540238 | DN35: -0.00032540238 | DO35: 1.829 | DP35: 1.843 | DQ35: -0.0021869874 | DR35: 0.0614 | DS35: 0.083573623 | DT35: 36 | DU35: =IFERROR(DM35/F35,0) -> 0.00030529177 | DV35: Lease cash / margin / financing | DW35: cash | DX35: lease | DY35: cash | EA35: 1 | EB35: 1 | EC35: -2.220446e-16 | EE35: -2.220446e-16 | EF35: -2.220446e-16 | EG35: 0.00032216941 | EH35: 0 | EI35: 0.00032216941 | EJ35: 1.829 | EK35: 1.843 | EP35: =IFERROR(EH35/F35,0) -> 0 | EQ35: Keep cash / margin / financing | ER35: cash | ES35: keep | ET35: cash | EV35: 1 | EW35: 1 | EX35: 0 | EZ35: 0 | FA35: 0 | FB35: 0 | FC35: 0 | FD35: 0 | FE35: 1.829 | FF35: 1.843 | FK35: =IFERROR(FC35/F35,0) -> 0
